Workbook

Sheet DICIEMBRE
B1: PILU | G1: EMPLEADO | H1: HORAS TRABAJADAS | I1: HORAS EXTRAS | J1: NO REMUNERATIVO | K1: AGUINALDO | L1: VACACIONES | M1: ADELANTO | N1: DEPOSITO | O1: EFVO | P1: TOTALES
B2: DETALLE | C2: HS TRABAJADAS | D2: VALOR / HORA | E2: IMPORTE | G2: PILU | H2: =+E3 -> 28059 | I2: =+E4 -> 0 | J2: =+E7 -> 8000 | K2: =+E5 -> 14029.5 | L2: =+E6 -> 15792 | M2: =+E8 -> 20000 | N2: =+E9 -> 38888.07 | O2: =+H2+I2+J2+K2+L2-M2-N2 -> 6992.43 | P2: =+O2+N2+M2 -> 65880.5
B3: SUELDO | C3: 199 | D3: 141 | E3: =C3*D3 -> 28059 | G3: JAVI | H3: =+E14 -> 28059 | I3: =+E15 -> 1269 | J3: =+E18 -> 8000 | K3: =+E16 -> 14029.5 | L3: =+E17 -> 15792 | M3: =+E19 -> 20000 | N3: =+E20 -> 33799.31 | O3: =+H3+I3+J3+K3+L3-M3-N3 -> 13350.19 | P3: =+O3+N3+M3 -> 67149.5
B4: EXTRA | C4: 0 | D4: =+D3*1.5 -> 211.5 | E4: =C4*D4 -> 0 | G4: FACU | H4: =+E25 -> 32238 | I4: =+E26 -> 4860 | J4: =+E29 -> 8000 | K4: =+E27 -> 16119 | L4: =+E28 -> 0 | M4: =+E30 -> 20000 | N4: 0 | O4: =+H4+I4+J4+K4+L4-M4-N4 -> 41217 | P4: =+O4+N4+M4 -> 61217
B5: AGUINALDO | C5: =+E3/2 -> 14029.5 | E5: =+C5 -> 14029.5 | G5: CHACO | H5: =+E35 -> 25870 | I5: =+E36 -> 975 | J5: =+E39 -> 8000 | K5: =+E37 -> 12935 | L5: =+E38 -> 0 | M5: =+E40 -> 20000 | N5: 0 | O5: =+H5+I5+J5+K5+L5-M5-N5 -> 27780 | P5: =+O5+N5+M5 -> 47780
B6: VACACIONES | C6: =+D3*8*14 -> 15792 | E6: =+C6 -> 15792 | G6: JUANI | H6: =+E45 -> 32238 | I6: =+E46 -> 3280.5 | J6: =+E49 -> 8500 | K6: =+E47 -> 16120 | L6: =+E48 -> 0 | M6: =+E50 -> 20000 | N6: =+E51 -> 29219.96 | O6: =+H6+I6+J6+K6+L6-M6-N6 -> 10918.54 | P6: =+O6+N6+M6 -> 60138.5
B7: NO REMUNERATIVO | C7: 8000 | E7: =+C7 -> 8000 | G7: YONA | H7: =+E56 -> 29949.5 | I7: =+E57 -> 0 | J7: =+E60 -> 8000 | K7: =+E58 -> 14974 | L7: =+E59 -> 0 | M7: =+E61 -> 20000 | N7: 0 | O7: =+H7+I7+J7+K7+L7-M7-N7 -> 32923.5 | P7: =+O7+N7+M7 -> 52923.5
B8: ADELANTO | C8: 20000 | E8: =+C8 -> 20000 | G8: MATI | H8: =+E66 -> 21890 | I8: =+E67 -> 990 | J8: =+E70 -> 5000 | K8: =+E68 -> 10945 | L8: =+E69 -> 0 | M8: =+E71 -> 15000 | N8: 0 | O8: =+H8+I8+J8+K8+L8-M8-N8 -> 23825 | P8: =+O8+N8+M8 -> 38825
B9: DEPOSITO | C9: 38888.07 | E9: =+C9 -> 38888.07 | G9: TOTALES | M9: =SUM(M2:M8) -> 135000 | N9: =SUM(N2:N8) -> 101907.34 | O9: =SUM(O2:O8) -> 157006.66 | P9: =+M9+N9+O9 -> 393914
B10: TOTAL A COBRAR | E10: =+E3+E4+E5+E6+E7-E8-E9 -> 6992.43
B12: JAVI
B13: DETALLE | C13: HS TRABAJADAS | D13: VALOR / HORA | E13: IMPORTE
B14: SUELDO | C14: 199 | D14: 141 | E14: =C14*D14 -> 28059
B15: EXTRA | C15: 6 | D15: =+D14*1.5 -> 211.5 | E15: =C15*D15 -> 1269
B16: AGUINALDO | C16: =+E14/2 -> 14029.5 | E16: =+C16 -> 14029.5 | G16: EMPLEADOS | H16: ARCHIVO
B17: VACACIONES | C17: =+D14*8*14 -> 15792 | E17: =+C17 -> 15792
B18: NO REMUNERATIVO | C18: 8000 | E18: =+C18 -> 8000
B19: ADELANTO | C19: 20000 | E19: =+C19 -> 20000 | H19: DEFINIR AREA DE IMPRESIÓN
B20: DEPOSITO | C20: 33799.31 | E20: =+C20 -> 33799.31
B21: TOTAL A COBRAR | E21: =+E14+E15+E16+E17+E18-E19-E20 -> 13350.19
B23: FACU
B24: DETALLE | C24: HS TRABAJADAS | D24: VALOR / HORA | E24: IMPORTE
B25: SUELDO | C25: 199 | D25: 162 | E25: =C25*D25 -> 32238
B26: EXTRA | C26: 20 | D26: =+D25*1.5 -> 243 | E26: =C26*D26 -> 4860
B27: AGUINALDO | C27: =+E25/2 -> 16119 | E27: =+C27 -> 16119
B28: VACACIONES | C28: 0 | E28: =+C28 -> 0
B29: NO REMUNERATIVO | C29: 8000 | E29: =+C29 -> 8000
B30: (ADELANTO) | C30: 20000 | E30: =+C30 -> 20000
B31: TOTAL A COBRAR | E31: =+E25+E26+E27+E28+E29-E30 -> 41217
B33: CHACO
B34: DETALLE | C34: HS TRABAJADAS | D34: VALOR / HORA | E34: IMPORTE
B35: SUELDO | C35: 199 | D35: 130 | E35: =C35*D35 -> 25870
B36: EXTRA | C36: 5 | D36: =+D35*1.5 -> 195 | E36: =C36*D36 -> 975
B37: AGUINALDO | C37: =+E35/2 -> 12935 | E37: =+C37 -> 12935
B38: VACACIONES | C38: 0 | E38: =+C38 -> 0
B39: NO REMUNERATIVO | C39: 8000 | E39: =+C39 -> 8000
B40: ADELANTO | C40: 20000 | E40: =+C40 -> 20000
B41: TOTAL A COBRAR | E41: =+E35+E36+E37+E38+E39-E40 -> 27780
B43: JUANI
B44: DETALLE | C44: HS TRABAJADAS | D44: VALOR / HORA | E44: IMPORTE
B45: SUELDO | C45: 199 | D45: 162 | E45: =C45*D45 -> 32238
B46: EXTRA | C46: 13.5 | D46: =+D45*1.5 -> 243 | E46: =C46*D46 -> 3280.5
B47: AGUINALDO | C47: 16120 | E47: =+C47 -> 16120
B48: VACACIONES | C48: 0 | E48: =+C48 -> 0
B49: NO REMUNERATIVO | C49: 8500 | E49: =+C49 -> 8500
B50: ADELANTO | C50: 20000 | E50: =+C50 -> 20000
B51: DEPOSITO | C51: 29219.96 | E51: =+C51 -> 29219.96
B52: TOTAL A COBRAR | E52: =+E45+E46+E47+E48+E49-E50-E51 -> 10918.54
B54: YONA
B55: DETALLE | C55: HS TRABAJADAS | D55: VALOR / HORA | E55: IMPORTE
B56: SUELDO | C56: 199 | D56: 150.5 | E56: =C56*D56 -> 29949.5
B57: EXTRA | C57: 0 | D57: =+D56*1.5 -> 225.75 | E57: =C57*D57 -> 0
B58: AGUINALDO | C58: 14974 | E58: =+C58 -> 14974
B59: VACACIONES | C59: 0 | E59: =+C59 -> 0
B60: NO REMUNERATIVO | C60: 8000 | E60: =+C60 -> 8000
B61: ADELANTO | C61: 20000 | E61: =+C61 -> 20000
B62: TOTAL A COBRAR | E62: =+E56+E57+E58+E59+E60-E61 -> 32923.5
B64: MATI
B65: DETALLE | C65: HS TRABAJADAS | D65: VALOR / HORA | E65: IMPORTE
B66: SUELDO | C66: 199 | D66: 110 | E66: =C66*D66 -> 21890
B67: EXTRA | C67: 6 | D67: =+D66*1.5 -> 165 | E67: =C67*D67 -> 990
B68: AGUINALDO | C68: =+E66/2 -> 10945 | E68: =+C68 -> 10945
B69: VACACIONES | C69: 0 | E69: =+C69 -> 0
B70: NO REMUNERATIVO | C70: 5000 | E70: =+C70 -> 5000
B71: ADELANTO | C71: 15000 | E71: =+C71 -> 15000
B72: TOTAL A COBRAR | E72: =+E66+E67+E68+E69+E70-E71 -> 23825

Sheet ENERO
B1: PILU | G1: EMPLEADO | H1: HS TRABAJADAS | I1: HS EXTRAS | J1: NO REMUN. | K1: AGUINALDO | L1: VACACIONES | M1: TOTALES | N1: ADELANTO | O1: DEPOSITO | P1: EFVO
B2: DETALLE | C2: HS TRABAJADAS | D2: VALOR / HORA | E2: IMPORTE | G2: PILU | H2: =+E3 -> 12452 | I2: =+E4 -> 0 | J2: =+E7 -> 8000 | K2: =+E5 -> 0 | L2: =+E6 -> 0 | M2: =+H2+J2+I2+K2+L2 -> 20452 | N2: =+E8 -> 0 | O2: =+E9 -> 12227.28 | P2: =+H2+I2+J2+K2+L2-N2-O2 -> 8224.72
B3: SUELDO | C3: 88 | D3: 141.5 | E3: =C3*D3 -> 12452 | G3: JAVI | H3: =+E14 -> 12452 | I3: =+E15 -> 636.75 | J3: =+E18 -> 8000 | K3: =+E16 -> 0 | L3: =+E17 -> 0 | M3: =+H3+J3+I3+K3+L3 -> 21088.75 | N3: =+E19 -> 3000 | O3: =+E20 -> 10752.43 | P3: =+H3+I3+J3+K3+L3-N3-O3 -> 7336.32
B4: EXTRA | C4: 0 | D4: =+D3*1.5 -> 212.25 | E4: =C4*D4 -> 0 | G4: FACU | H4: =+E25 -> 27692 | I4: =+E26 -> 1806 | J4: =+E29 -> 8000 | K4: =+E27 -> 0 | L4: =+E28 -> 0 | M4: =+H4+J4+I4+K4+L4 -> 37498 | N4: =+E30 -> 3000 | O4: 0 | P4: =+H4+I4+J4+K4+L4-N4-O4 -> 34498
B5: AGUINALDO | C5: 0 | E5: =+C5 -> 0 | G5: CHACO | H5: =+E35 -> 23920 | I5: =+E36 -> 682.5 | J5: =+E39 -> 8000 | K5: =+E37 -> 0 | L5: =+E38 -> 0 | M5: =+H5+J5+I5+K5+L5 -> 32602.5 | N5: =+E40 -> 3000 | O5: 0 | P5: =+H5+I5+J5+K5+L5-N5-O5 -> 29602.5
B6: VACACIONES | C6: 0 | E6: =+C6 -> 0 | G6: JUANI | H6: =+E45 -> 29808 | I6: =+E46 -> 972 | J6: =+E49 -> 13500 | K6: =+E47 -> 0 | L6: =+E48 -> 18144 | M6: =+H6+J6+I6+K6+L6 -> 62424 | N6: =+E50 -> 33720 | O6: =+E51+E52 -> 22393.59 | P6: =+H6+I6+J6+K6+L6-N6-O6 -> 6310.41
B7: NO REMUNERATIVO | C7: 8000 | E7: =+C7 -> 8000 | G7: YONA | H7: =+E57 -> 27692 | I7: =+E58 -> 3837.75 | J7: =+E61 -> 13000 | K7: =+E59 -> 0 | L7: =+E60 -> 0 | M7: =+H7+J7+I7+K7+L7 -> 44529.75 | N7: 1000 | O7: 0 | P7: =+H7+I7+J7+K7+L7-N7-O7 -> 43529.75
B8: ADELANTO | C8: 0 | E8: =+C8 -> 0 | G8: MATI | H8: =+E67 -> 20240 | I8: =+E68 -> 990 | J8: =+E71 -> 5000 | K8: =+E69 -> 0 | L8: =+E70 -> 0 | M8: =+H8+J8+I8+K8+L8 -> 26230 | N8: =+E72 -> 0 | O8: 0 | P8: =+H8+I8+J8+K8+L8-N8-O8 -> 26230
B9: DEPOSITO | C9: 12227.28 | E9: =+C9 -> 12227.28 | G9: GUILLERMO | H9: =+E77 -> 8690 | I9: =+E78 -> 0 | K9: =+E79 -> 0 | L9: =+E80 -> 0 | M9: =+H9+J9+I9+K9+L9 -> 8690 | N9: =+E82 -> 0 | O9: 0 | P9: =+H9+I9+J9+K9+L9-N9-O9 -> 8690
B10: TOTAL A COBRAR | E10: =+E3+E4+E5+E6+E7-E8-E9 -> 8224.72 | G10: MARTIN | H10: =+E97 -> 33000 | M10: =+H10+J10+I10+K10+L10 -> 33000 | P10: =+H10+I10+J10+K10+L10-N10-O10 -> 33000
G11: SILVI | H11: =+E87 -> 25000 | I11: =+E88+E89 -> 9687.5 | J11: =+E91 -> 0 | K11: 0 | L11: =+E90 -> 0 | M11: =+H11+J11+I11+K11+L11 -> 34687.5 | N11: =+E92 -> 0 | O11: 0 | P11: =+H11+I11+J11+K11+L11-N11-O11 -> 34687.5
B12: JAVI | G12: TOTALES | M12: =SUM(M2:M11) -> 321202.5 | N12: =SUM(N2:N11) -> 43720 | O12: =SUM(O2:O11) -> 45373.3 | P12: =SUM(P2:P11) -> 232109.2
B13: DETALLE | C13: HS TRABAJADAS | D13: VALOR / HORA | E13: IMPORTE | N13: =+N12+O12+P12 -> 321202.5
B14: SUELDO | C14: 88 | D14: 141.5 | E14: =C14*D14 -> 12452
B15: EXTRA | C15: 3 | D15: =+D14*1.5 -> 212.25 | E15: =C15*D15 -> 636.75
B16: AGUINALDO | C16: 0 | E16: =+C16 -> 0
B17: VACACIONES | C17: 0 | E17: =+C17 -> 0
B18: NO REMUNERATIVO | C18: 8000 | E18: =+C18 -> 8000 | K18: HORA | L18: HORA X | M18: SOBRESUELDO | N18: NO REM.
B19: ADELANTO | C19: 3000 | E19: =+C19 -> 3000 | G19: EMPLEADOS | H19: ARCHIVO | J19: JUANI | K19: 162 | L19: 243 | M19: 3500 | N19: 5000
B20: DEPOSITO | C20: 10752.43 | E20: =+C20 -> 10752.43 | J20: JONA | K20: 150.5 | L20: 225.75 | M20: 3000 | N20: 5000
B21: TOTAL A COBRAR | E21: =+E14+E15+E16+E17+E18-E19-E20 -> 7336.32 | J21: FACU | K21: 150.5 | L21: 225.75 | M21: 3000 | N21: 5000
H22: DEFINIR AREA DE IMPRESIÓN | J22: PILU | K22: 141.25 | L22: 211.87 | M22: 3000 | N22: 5000
B23: FACU | J23: JAVI | K23: 141.25 | L23: 211.87 | M23: 3000 | N23: 5000
B24: DETALLE | C24: HS TRABAJADAS | D24: VALOR / HORA | E24: IMPORTE | J24: CHACO | K24: 130 | L24: 195 | M24: 3000 | N24: 5000
B25: SUELDO | C25: 184 | D25: 150.5 | E25: =C25*D25 -> 27692 | J25: GUILLERMO | K25: 110 | L25: 165
B26: EXTRA | C26: 8 | D26: =+D25*1.5 -> 225.75 | E26: =C26*D26 -> 1806 | J26: MATI | K26: 110 | L26: 165 | M26: 0 | N26: 5000
B27: AGUINALDO | C27: 0 | E27: =+C27 -> 0 | I27: 11 dias | J27: MARTIN MOLINA | K27: 3000 X DIA
B28: VACACIONES | C28: 0 | E28: =+C28 -> 0
B29: NO REMUNERATIVO | C29: 8000 | E29: =+C29 -> 8000
B30: ADELANTO | C30: 3000 | E30: =+C30 -> 3000
B31: TOTAL A COBRAR | E31: =+E25+E26+E27+E28+E29-E30 -> 34498 | J31: DETALLE DE GASTOS ENERO
B33: CHACO | J33: GUILLE
B34: DETALLE | C34: HS TRABAJADAS | D34: VALOR / HORA | E34: IMPORTE | K34: epec | L34: 603.6
B35: SUELDO | C35: 184 | D35: 130 | E35: =C35*D35 -> 23920 | K35: cable | L35: 1495
B36: EXTRA | C36: 3.5 | D36: =+D35*1.5 -> 195 | E36: =C36*D36 -> 682.5 | K36: viaticos | L36: 2600
B37: AGUINALDO | C37: 0 | E37: =+C37 -> 0 | J37: 44214 | K37: ADELANTO | M37: 30000
B38: VACACIONES | C38: 0 | E38: =+C38 -> 0 | K38: SEGURO GOL | M38: 900
B39: NO REMUNERATIVO | C39: 8000 | E39: =+C39 -> 8000 | K39: PARABRISA | L39: 10310
B40: ADELANTO | C40: 3000 | E40: =+C40 -> 3000
B41: TOTAL A COBRAR | E41: =+E35+E36+E37+E38+E39-E40 -> 29602.5
B43: JUANI
B44: DETALLE | C44: HS TRABAJADAS | D44: VALOR / HORA | E44: IMPORTE | G44: =31+162 -> 193 | J44: GERARDO
B45: SUELDO | C45: 184 | D45: 162 | E45: =C45*D45 -> 29808
B46: EXTRA | C46: 4 | D46: =+D45*1.5 -> 243 | E46: =C46*D46 -> 972 | K46: COMBUSTIBLE | M46: 1000
B47: AGUINALDO | C47: 0 | E47: =+C47 -> 0 | J47: 44214 | K47: ADELANTO | M47: 30000
B48: VACACIONES DIF | C48: 18144 | E48: =+C48 -> 18144 | F48: proximo mes se pasan 5000 al sueldo para influir en hs extras | K48: DEPOSITO | M48: 45000
B49: NO REMUNERATIVO | C49: =8500+5000 -> 13500 | E49: =+C49 -> 13500 | K49: SEGURO MOTO
B50: ADELANTO | C50: 33720 | E50: =+C50 -> 33720 | F50: 30000 | K50: ALINEADO 50% | L50: 2000
B51: DEPOSITO | C51: 12345.99 | E51: =+C51 -> 12345.99
B52: DEPOSITO VACACIONES | C52: 10047.6 | E52: =+C52 -> 10047.6
B53: TOTAL A COBRAR | E53: =+E45+E46+E48+E49-E50-E51-E52 -> 6310.41
B55: JONA | J55: CRISTIAN
B56: DETALLE | C56: HS TRABAJADAS | D56: VALOR / HORA | E56: IMPORTE | J56: 44214 | K56: ADELANTO | M56: 30000
B57: SUELDO | C57: 184 | D57: 150.5 | E57: =C57*D57 -> 27692 | K57: SEGUROS
B58: EXTRA | C58: 17 | D58: =+D57*1.5 -> 225.75 | E58: =C58*D58 -> 3837.75
B59: AGUINALDO | C59: 0 | E59: =+C59 -> 0
B60: VACACIONES | C60: 0 | E60: =+C60 -> 0
B61: NO REMUNERATIVO | C61: 13000 | E61: =+C61 -> 13000
B62: ADELANTO | C62: 1000 | E62: =+C62 -> 1000
B63: TOTAL A COBRAR | E63: =+E57+E58+E59+E60+E61-E62 -> 43529.75 | F63: 51503.75
B65: MATI
B66: DETALLE | C66: HS TRABAJADAS | D66: VALOR / HORA | E66: IMPORTE
B67: SUELDO | C67: 184 | D67: 110 | E67: =C67*D67 -> 20240
B68: EXTRA | C68: 6 | D68: =+D67*1.5 -> 165 | E68: =C68*D68 -> 990
B69: AGUINALDO | C69: 0 | E69: =+C69 -> 0
B70: VACACIONES | C70: 0 | E70: =+C70 -> 0
B71: NO REMUNERATIVO | C71: 5000 | E71: =+C71 -> 5000
B72: ADELANTO | C72: 0 | E72: =+C72 -> 0
B73: TOTAL A COBRAR | E73: =+E67+E68+E69+E70+E71-E72 -> 26230
B75: GUILLERMO
B76: DETALLE | C76: HS TRABAJADAS | D76: VALOR / HORA | E76: IMPORTE
B77: SUELDO | C77: =+(7*9)+(2*8) -> 79 | D77: 110 | E77: =C77*D77 -> 8690
B78: EXTRA | C78: 0 | D78: =+D77*1.5 -> 165 | E78: =+C78*D78 -> 0
B79: AGUINALDO | C79: 0 | E79: =+C79 -> 0
B80: VACACIONES | C80: 0 | E80: =+C80 -> 0
B81: NO REMUNERATIVO | C81: 0 | D81: 0 | E81: =+C81 -> 0
B82: ADELANTO | C82: 0 | E82: =+C82 -> 0
B83: TOTAL A COBRAR | E83: =+E77+E78+E79+E80+E81-E82 -> 8690
B85: SILVINA
B86: DETALLE | C86: HS TRABAJADAS | D86: VALOR / HORA | E86: IMPORTE
B87: SUELDO | E87: 25000
B88: EXTRA | C88: 4 | D88: =+E87/8/20*(1.5) -> 234.375 | E88: =C88*D88 -> 937.5
B89: DIAS EXTRAS DIC | C89: 7 | D89: =+E87/20 -> 1250 | E89: =+C89*D89 -> 8750
B90: VACACIONES | C90: 0 | E90: =+C90 -> 0
B91: NO REMUNERATIVO | C91: 0 | E91: =+C91 -> 0
B92: ADELANTO | C92: 0 | E92: =+C92 -> 0
B93: TOTAL A COBRAR | E93: =+E87+E88+E89+E90+E91-E92 -> 34687.5
B95: MARTIN
B96: DETALLE | C96: HS TRABAJADAS | D96: VALOR / HORA | E96: IMPORTE
B97: SUELDO | C97: 88 | D97: 375 | E97: =+C97*D97 -> 33000
B98: EXTRA | E98: =C98*D98 -> 0
B99: ADELANTO | C99: 0 | E99: =+C99 -> 0
B100: TOTAL A COBRAR | E100: =+E97+E98-E99 -> 33000

Sheet FEB
B1: PILU | G1: EMPLEADO | H1: HS TRABAJADAS | I1: HS EXTRAS | J1: NO REMUN. | K1: VACACIONES | L1: TOTALES | M1: ADELANTO | N1: DEPOSITO | O1: EFVO
B2: DETALLE | C2: HS TRABAJADAS | D2: VALOR / HORA | E2: IMPORTE | G2: PILU | H2: =+E3 -> 29440.8 | I2: =+E4 -> 0 | J2: =+E5 -> 8000 | K2: 0 | L2: =+H2+I2+J2+K2 -> 37440.8 | M2: =+E6 -> 0 | N2: =+E7 -> 20152.27 | O2: =+L2-M2-N2 -> 17288.53
B3: SUELDO | C3: 174 | D3: 169.2 | E3: =C3*D3 -> 29440.8 | G3: JAVI | H3: =+E12 -> 29440.8 | I3: =+E13 -> 0 | J3: =+E14 -> 8000 | K3: 0 | L3: =+H3+I3+J3+K3 -> 37440.8 | M3: =+E15 -> 11000 | N3: =+E16 -> 17674.95 | O3: =+L3-M3-N3 -> 8765.85
B4: EXTRA | D4: =+D3*1.5 -> 253.8 | E4: =C4*D4 -> 0 | G4: FACU | H4: =+E21 -> 23400 | I4: =+E22+E25 -> 9370 | J4: =+E24 -> 8000 | K4: =+E23 -> 8428 | L4: =+H4+I4+J4+K4 -> 49198 | M4: =+E27+E26 -> 10428 | N4: 0 | O4: =+L4-M4-N4 -> 38770
B5: NO REMUNERATIVO | C5: 8000 | E5: =+C5 -> 8000 | G5: CHACO | H5: =+E32 -> 16770 | I5: =+E33 -> 780 | J5: =+E36 -> 8000 | K5: =+E35 -> 14560 | L5: =+H5+I5+J5+K5 -> 40110 | M5: =+E37 -> 0 | N5: 0 | O5: =+L5-M5-N5 -> 40110
B6: ADELANTO | E6: =+C6 -> 0 | G6: JUANI | H6: =+E42 -> 33756 | I6: =+E43 -> 727.5 | J6: =+E44 -> 8500 | L6: =+H6+I6+J6+K6 -> 42983.5 | M6: =+E45 -> 18144 | N6: =+E46 -> 20348.89 | O6: =+H6+I6+J6-K6-M6-N6 -> 4490.61
B7: DEPOSITO | E7: 20152.27 | G7: YONA | H7: =+E51 -> 31320 | I7: =+E52 -> 0 | J7: =+E53 -> 8000 | K7: 0 | L7: =+H7+I7+J7+K7 -> 39320 | M7: =+E54 -> 10000 | N7: 0 | O7: =+H7+J7-M7 -> 29320
B8: TOTAL A COBRAR | E8: =+E3+E4+E5-E6-E7 -> 17288.53 | F8: AUMENTO DE HORA 20 % | G8: MATI | H8: =+E60 -> 22968 | I8: =+E61 -> 1782 | J8: =+E62 -> 5000 | K8: 0 | L8: =+H8+I8+J8+K8 -> 29750 | M8: 0 | N8: 0 | O8: =+L8-M8-N8 -> 29750
G9: GUILLERMO | H9: =+E68 -> 19140 | I9: =+E69 -> 0 | J9: 0 | K9: 0 | L9: =K9+H9+I9+J9 -> 19140 | M9: =+E70 -> 0 | N9: 0 | O9: =+L9-M9-N9 -> 19140
B10: JAVI | G10: MARTIN | H10: =+E81 -> 54000 | L10: =K10+H10+I10+J10 -> 54000 | O10: =+L10-M10-N10 -> 54000
B11: DETALLE | C11: HS TRABAJADAS | D11: VALOR / HORA | E11: IMPORTE | G11: SILVI | H11: =+E75 -> 25000 | I11: =+E76 -> 0 | J11: 0 | K11: 0 | L11: =K11+H11+I11+J11 -> 25000 | M11: 0 | N11: 0 | O11: =+L11-M11-N11 -> 25000
B12: SUELDO | C12: 174 | D12: 169.2 | E12: =C12*D12 -> 29440.8 | G12: TOTALES | M12: =SUM(M2:M11) -> 49572 | N12: =SUM(N2:N11) -> 58176.11 | O12: =SUM(O2:O11) -> 266634.99
B13: EXTRA | D13: =+D12*1.5 -> 253.8 | E13: =C13*D13 -> 0 | M13: =+N12+O12+M12 -> 374383.1
B14: NO REMUNERATIVO | C14: 8000 | E14: =+C14 -> 8000
B15: ADELANTO | E15: 11000 | G15: FEBRERO 174 HS
B16: DEPOSITO | E16: 17674.95
B17: TOTAL A COBRAR | E17: =+E12+E13+E14-E15-E16 -> 8765.85
K18: HORA | L18: HORA X | M18: SOBRESUELDO | N18: NO REM.
B19: FACU | G19: EMPLEADOS | H19: ARCHIVO | J19: JUANI | K19: 194 | L19: =+K19*1.5 -> 291 | N19: 8500
B20: DETALLE | C20: HS TRABAJADAS | D20: VALOR / HORA | E20: IMPORTE | J20: JONA | K20: 180 | L20: =+K20*1.5 -> 270 | N20: 8000
B21: SUELDO | C21: 130 | D21: 180 | E21: =C21*D21 -> 23400 | J21: FACU | K21: 180 | L21: =+K21*1.5 -> 270 | N21: 8000
B22: EXTRA | C22: 11 | D22: =+D21*1.5 -> 270 | E22: =C22*D22 -> 2970 | H22: DEFINIR AREA DE IMPRESIÓN | J22: PILU | K22: 169.2 | L22: =+K22*1.5 -> 253.8 | N22: 8000
B23: VACACIONES (Pagado) | C23: 56 | D23: 150.5 | E23: =+C23*D23 -> 8428 | J23: JAVI | K23: 169.2 | L23: =+K23*1.5 -> 253.8 | N23: 8000
B24: NO REMUNERATIVO | C24: 8000 | E24: =+C24 -> 8000 | J24: CHACO | K24: 156 | L24: =+K24*1.5 -> 234 | N24: 8000
B25: viaticos febrero | E25: 6400 | J25: GUILLERMO | K25: 110 | L25: =+K25*1.5 -> 165
B26: VACACIONES 7 DIAS | E26: 8428 | J26: MATI | K26: 132 | L26: =+K26*1.5 -> 198 | M26: 0 | N26: 5000
B27: A CUENTA VIATICOS | E27: 2000 | J27: MARTIN MOLINA | K27: 3000 X DIA
B28: TOTAL A COBRAR | E28: =+E21+E22+E23+E24+E25-E26-E27 -> 38770 | F28: =+E21+E22+E23+E24+E25 -> 49198
B30: CHACO
B31: DETALLE | C31: HS TRABAJADAS | D31: VALOR / HORA | E31: IMPORTE | J31: DETALLE DE GASTOS ENERO / FEBRERO
B32: SUELDO | C32: 129 | D32: 130 | E32: =C32*D32 -> 16770 | G32: =130*1.2 -> 156
B33: EXTRA | C33: 4 | D33: =+D32*1.5 -> 195 | E33: =C33*D33 -> 780 | J33: GUILLE
B34: AGUINALDO | E34: =+C34 -> 0 | F34: =150-C32 -> 21 | G34: =+D32*F34 -> 2730 | K34: epec ENERO | L34: 603.6
B35: VACACIONES | C35: 112 | D35: 130 | E35: =+C35*D35 -> 14560 | K35: cable ENERO | L35: 1495
B36: NO REMUNERATIVO | C36: 8000 | E36: =+C36 -> 8000 | K36: cable FEBRERO | L36: 1495
B37: ADELANTO | E37: =+C37 -> 0 | G37: PAGADO PPIO MES SE DEBE EL 20% | K37: viaticos | L37: 2600
B38: TOTAL A COBRAR | E38: =+E32+E33+E34+E35+E36-E37 -> 40110 | K38: DIF. ADELANTO | L38: -2200
J39: FEBRERO | K39: SEGURO GOL | M39: 903.62
B40: JUANI | J40: FEBRERO | K40: SEGURO CLIO | M40: 903.62
B41: DETALLE | C41: HS TRABAJADAS | D41: VALOR / HORA | E41: IMPORTE | K41: PARABRISA | L41: 10310
B42: SUELDO | C42: 174 | D42: 194 | E42: =C42*D42 -> 33756 | K42: 931 | L42: 42116.29
B43: EXTRA | C43: 2.5 | D43: =+D42*1.5 -> 291 | E43: =C43*D43 -> 727.5 | J43: FEB/MAR | K43: MONOT FACU | L43: 3931.01
B44: NO REMUNERATIVO | C44: 8500 | E44: =+C44 -> 8500 | J44: FEB/MAR | K44: MONOT GERA | L44: 6566.42
B45: VACACIONES abonadas | C45: 112 | D45: 162 | E45: 18144 | J45: FEB/MAR | K45: AUTON. CRISTIAN | L45: 6909.79
B46: DEPOSITO | E46: 20348.89 | J46: FEB/MAR | K46: AUTON GUILLE | L46: =3433.43+3419.2 -> 6852.63
B47: TOTAL A COBRAR | E47: =+E42+E43+E44-E45-E46 -> 4490.61
J48: A TRANSFERIR | L48: =SUM(L34:L47) -> 80679.74 | M48: =SUM(M34:M47) -> 1807.24 | N48: =+L48-M48 -> 78872.5
B49: JONA
B50: DETALLE | C50: HS TRABAJADAS | D50: VALOR / HORA | E50: IMPORTE
B51: SUELDO | C51: 174 | D51: 180 | E51: =C51*D51 -> 31320
B52: EXTRA | D52: =+D51*1.5 -> 270 | E52: =C52*D52 -> 0 | J52: GERARDO
B53: NO REMUNERATIVO | C53: 8000 | E53: =+C53 -> 8000
B54: ADELANTO | D54: 10000 | E54: =+D54 -> 10000 | J54: FEBRERO | K54: COMBUSTIBLE | M54: 1000
B55: VACACIONES PAGAS ENERO | C55: 53 | D55: 150.5 | E55: =+C55*D55 -> 7976.5 | J55: MARZO | K55: SEGURO MOTO | M55: 254.11
B56: TOTAL A COBRAR | E56: =+E51+E53-E54 -> 29320 | K56: ALINEADO 50% | L56: 2000
B58: MATI | J58: DEVOLVER | L58: =SUM(L54:L57) -> 2000 | M58: =SUM(M54:M57) -> 1254.11 | N58: =+L58-M58 -> 745.89
B59: DETALLE | C59: HS TRABAJADAS | D59: VALOR / HORA | E59: IMPORTE
B60: SUELDO | C60: 174 | D60: 132 | E60: =C60*D60 -> 22968 | J60: CRISTIAN
B61: EXTRA | C61: 9 | D61: =+D60*1.5 -> 198 | E61: =C61*D61 -> 1782 | K61: REPARACION | L61: 3600
B62: NO REMUNERATIVO | C62: 5000 | E62: =+C62 -> 5000 | K62: SEGUROS | M62: 3482
B63: ADELANTO | E63: =+C63 -> 0
B64: TOTAL A COBRAR | E64: =+E60+E61+E62-E63 -> 29750 | J64: DEVOLVER | L64: =SUM(L61:L63) -> 3600 | M64: =SUM(M61:M63) -> 3482 | N64: =+L64-M64 -> 118
B66: GUILLERMO
B67: DETALLE | C67: HS TRABAJADAS | D67: VALOR / HORA | E67: IMPORTE
B68: SUELDO | C68: 174 | D68: 110 | E68: =C68*D68 -> 19140
B69: EXTRA | D69: =+D68*1.5 -> 165 | E69: =+C69*D69 -> 0
B70: ADELANTO | E70: =+C70 -> 0
B71: TOTAL A COBRAR | E71: =+E68-E69 -> 19140
B73: SILVINA
B74: DETALLE | C74: HS TRABAJADAS | D74: VALOR / HORA | E74: IMPORTE
B75: SUELDO | E75: 25000
B76: EXTRA | D76: =+E75/8/20*(1.5) -> 234.375 | E76: =C76*D76 -> 0
B77: TOTAL A COBRAR | E77: =+E75+E76 -> 25000
B79: MARTIN
B80: DETALLE | C80: HS TRABAJADAS | D80: VALOR / HORA | E80: IMPORTE
B81: SUELDO | C81: 144 | D81: 375 | E81: =+C81*D81 -> 54000
B82: ADELANTO | C82: 0 | E82: =+C82 -> 0
B83: TOTAL A COBRAR | E83: =+E81-E82 -> 54000
B97: JONA
B98: DETALLE | C98: HS TRABAJADAS | D98: VALOR / HORA | E98: IMPORTE
B99: SUELDO | C99: 184 | D99: 150.5 | E99: =C99*D99 -> 27692
B100: EXTRA | C100: 17 | D100: =+D99*1.5 -> 225.75 | E100: =C100*D100 -> 3837.75
B101: AGUINALDO | C101: 0 | E101: =+C101 -> 0
B102: VACACIONES | C102: 14974 | E102: =+C102 -> 14974
B103: NO REMUNERATIVO | C103: 8000 | E103: =+C103 -> 8000
B104: ADELANTO | C104: 3000 | E104: =+C104 -> 3000
B105: total pagado febrero | E105: =+E99+E100+E101+E102+E103-E104 -> 51503.75
E108: =+E105-43529.75 -> 7974

Sheet MARZO
B2: PILU | I2: MARZO
B3: DETALLE | C3: HS TRABAJADAS | D3: VALOR / HORA | E3: IMPORTE | I3: EMPLEADO | J3: HS TRABAJADAS | K3: HS EXTRAS | L3: NO REMUN. | M3: VACACIONES | N3: TOTALES | O3: ADELANTO | P3: DEPOSITO | Q3: EFVO
B4: SUELDO | C4: 194 | D4: 169.2 | E4: =C4*D4 -> 32824.8 | I4: PILU | J4: =+E4 -> 32824.8 | K4: =+E5 -> 0 | L4: =+E6 -> 8000 | M4: 0 | N4: =+J4+K4+L4+M4 -> 40824.8 | O4: =+E7 -> 0 | P4: =+E8 -> 20348.89 | Q4: =+N4-O4-P4 -> 20475.91
B5: EXTRA | C5: 0 | D5: =+D4*1.5 -> 253.8 | E5: =C5*D5 -> 0 | I5: JAVI | J5: =+E13 -> 32824.8 | K5: =+E14 -> 0 | L5: =+E15 -> 8000 | M5: 0 | N5: =+J5+K5+L5+M5 -> 40824.8 | O5: =+E16 -> 6000 | P5: =+E17 -> 17674.95 | Q5: =+N5-O5-P5 -> 17149.85
B6: NO REMUNERATIVO | C6: 8000 | E6: =+C6 -> 8000 | I6: FACU | J6: =+E22 -> 34920 | K6: =+E23+E26 -> 810 | L6: =+E24 -> 8000 | M6: 0 | N6: =+J6+K6+L6+M6 -> 43730 | O6: 0 | P6: 0 | Q6: =+N6 -> 43730
B7: ADELANTO | E7: 0 | I7: CHACO | J7: =+E31 -> 23400 | K7: =+E32 -> 2709 | L7: =+E34 -> 8000 | M7: 0 | N7: =+J7+K7+L7+M7 -> 34109 | O7: =+E35 -> 7000 | P7: 0 | Q7: =+N7-O7 -> 27109
B8: DEPOSITO | E8: 20348.89 | I8: JUANI | J8: =+E40 -> 37636 | K8: =+E41 -> 2473.5 | L8: =+E42 -> 13500 | N8: =+J8+K8+L8+M8 -> 53609.5 | O8: 0 | P8: =+E43 -> 20348.89 | Q8: =+N8-O8-P8 -> 33260.61
B9: TOTAL A COBRAR | E9: =+E4+E5+E6-E7-E8 -> 20475.91 | I9: JONA | J9: =+E48 -> 34920 | K9: =+E49 -> 0 | L9: =+E50 -> 13000 | M9: 0 | N9: =+J9+K9+L9+M9 -> 47920 | O9: =+E51 -> 13000 | P9: 0 | Q9: =+N9-O9-P9 -> 34920
I10: MATI | J10: =+E56 -> 25608 | K10: =+E57 -> 1089 | L10: =+E58 -> 5000 | M10: 0 | N10: =+J10+K10+L10+M10 -> 31697 | O10: 0 | P10: 0 | Q10: =+N10-O10-P10 -> 31697
B11: JAVI | I11: FABIAN | J11: =+E64 -> 21340 | K11: =+E65 -> 495 | L11: 0 | M11: 0 | N11: =M11+J11+K11+L11 -> 21835 | O11: =+E66 -> 0 | P11: 0 | Q11: =+N11-O11-P11 -> 21835
B12: DETALLE | C12: HS TRABAJADAS | D12: VALOR / HORA | E12: IMPORTE | I12: MARTIN | J12: =+E77 -> 63000 | N12: =M12+J12+K12+L12 -> 63000 | O12: 0 | Q12: =+N12-O12-P12 -> 63000
B13: SUELDO | C13: 194 | D13: 169.2 | E13: =C13*D13 -> 32824.8 | I13: SILVI | J13: =+E71 -> 25000 | K13: =+E72 -> 2343.75 | L13: 0 | M13: 0 | N13: =M13+J13+K13+L13 -> 27343.75 | O13: 0 | P13: 0 | Q13: =+N13-O13-P13 -> 27343.75
B14: EXTRA | C14: 0 | D14: =+D13*1.5 -> 253.8 | E14: =C14*D14 -> 0 | I14: TOTALES | O14: =SUM(O4:O13) -> 26000 | P14: =SUM(P4:P13) -> 58372.73 | Q14: =SUM(Q4:Q13) -> 320521.12
B15: NO REMUNERATIVO | C15: 8000 | E15: =+C15 -> 8000 | O15: =+P14+Q14+O14 -> 404893.85
B16: ADELANTO | E16: 6000
B17: DEPOSITO | E17: 17674.95 | I17: marzo 194 HS
B18: TOTAL A COBRAR | E18: =+E13+E14+E15-E16-E17 -> 17149.85
B20: FACU | M20: HORA | N20: HORA X | O20: SOBRESUELDO | P20: NO REM.
B21: DETALLE | C21: HS TRABAJADAS | D21: VALOR / HORA | E21: IMPORTE | I21: EMPLEADOS | J21: ARCHIVO | L21: JUANI | M21: 194 | N21: =+M21*1.5 -> 291 | P21: 13500
B22: SUELDO | C22: 194 | D22: 180 | E22: =C22*D22 -> 34920 | L22: JONA | M22: 180 | N22: =+M22*1.5 -> 270 | P22: 13000
B23: EXTRA | C23: 3 | D23: =+D22*1.5 -> 270 | E23: =C23*D23 -> 810 | L23: FACU | M23: 180 | N23: =+M23*1.5 -> 270 | P23: 8000
B24: NO REMUNERATIVO | C24: 8000 | E24: =+C24 -> 8000 | J24: DEFINIR AREA DE IMPRESIÓN | L24: PILU | M24: 169.2 | N24: =+M24*1.5 -> 253.8 | P24: 8000
B25: VIATICOS DEL 29/03 AL 01/04 | C25: 4 | D25: 1600 | E25: =+C25*D25 -> 6400 | L25: JAVI | M25: 169.2 | N25: =+M25*1.5 -> 253.8 | P25: 8000
B26: ADELANTO | C26: 0 | E26: 0 | L26: CHACO | M26: 156 | N26: =+M26*1.5 -> 234 | P26: 3000
B27: TOTAL A COBRAR | E27: =+E22+E23+E24+E25 -> 50130 | L27: FABIAN | M27: 110 | N27: =+M27*1.5 -> 165 | P27: 7000
H28: DIAS | I28: HS | L28: MATI | M28: 132 | N28: =+M28*1.5 -> 198 | O28: 0 | P28: 5000
B29: CHACO | F29: PAGADO} SE DEBE EL 20% | H29: 18 | I29: 9 | J29: =+H29*I29 -> 162 | L29: MARTIN MOLINA | M29: 3000 X DIA
B30: DETALLE | C30: HS TRABAJADAS | D30: VALOR / HORA | E30: IMPORTE | H30: 4 | I30: 8 | J30: =+H30*I30 -> 32
B31: SUELDO | C31: 150 | D31: 156 | E31: =C31*D31 -> 23400 | H31: hs mes | J31: =SUM(J29:J30) -> 194
B32: DIFERENCIA AUMENTO FEB | C32: 129 | D32: 21 | E32: =+C32*D32 -> 2709
B33: EXTRA | D33: =+D31*1.5 -> 234 | E33: =C33*D33 -> 0
B34: NO REMUNERATIVO | C34: 8000 | E34: =+C34 -> 8000
B35: ADELANTO | E35: 7000
B36: TOTAL A COBRAR | E36: =+E31+E32+E33+E34-E35 -> 27109
B38: JUANI
B39: DETALLE | C39: HS TRABAJADAS | D39: VALOR / HORA | E39: IMPORTE
B40: SUELDO | C40: 194 | D40: 194 | E40: =C40*D40 -> 37636
B41: EXTRA | C41: 8.5 | D41: =+D40*1.5 -> 291 | E41: =C41*D41 -> 2473.5
B42: NO REMUNERATIVO | C42: 13500 | E42: =+C42 -> 13500 | F42: AUMENTO 5000
B43: DEPOSITO | E43: 20348.89
B44: TOTAL A COBRAR | E44: =+E40+E41+E42-E43 -> 33260.61
B46: JONA | F46: FALTA PAGO DE VACACIONES
B47: DETALLE | C47: HS TRABAJADAS | D47: VALOR / HORA | E47: IMPORTE | F47: FEBRERO 53 HS PAGADAS
B48: SUELDO | C48: 194 | D48: 180 | E48: =C48*D48 -> 34920 | F48: FALTAN 59 HS. (7,5 DIAS)
B49: EXTRA | D49: =+D48*1.5 -> 270 | E49: =C49*D49 -> 0
B50: NO REMUNERATIVO | C50: 13000 | E50: =+C50 -> 13000 | F50: AUMENTO 5000
B51: ADELANTO | E51: 13000 | F51: FEBRERO
B52: TOTAL A COBRAR | E52: =+E48+E49+E50-E51 -> 34920
B54: MATI
B55: DETALLE | C55: HS TRABAJADAS | D55: VALOR / HORA | E55: IMPORTE
B56: SUELDO | C56: 194 | D56: 132 | E56: =C56*D56 -> 25608
B57: EXTRA | C57: 5.5 | D57: =+D56*1.5 -> 198 | E57: =C57*D57 -> 1089
B58: NO REMUNERATIVO | C58: 5000 | E58: =+C58 -> 5000
B59: ADELANTO | E59: =+C59 -> 0
B60: TOTAL A COBRAR | E60: =+E56+E57+E58-E59 -> 31697
B62: FABIAN
B63: DETALLE | C63: HS TRABAJADAS | D63: VALOR / HORA | E63: IMPORTE
B64: SUELDO | C64: 194 | D64: 110 | E64: =C64*D64 -> 21340
B65: EXTRA | C65: 3 | D65: =+D64*1.5 -> 165 | E65: =+C65*D65 -> 495
B66: ADELANTO | E66: =+C66 -> 0
B67: TOTAL A COBRAR | E67: =+E64+E65-E66 -> 21835
B69: SILVINA
B70: DETALLE | C70: HS TRABAJADAS | D70: VALOR / HORA | E70: IMPORTE
B71: SUELDO | E71: 25000
B72: EXTRA | C72: 10 | D72: =+E71/8/20*(1.5) -> 234.375 | E72: =C72*D72 -> 2343.75
B73: TOTAL A COBRAR | E73: =+E71+E72 -> 27343.75
B75: MARTIN | F75: un dia menos + feriado
B76: DETALLE | C76: HS TRABAJADAS | D76: VALOR / HORA | E76: IMPORTE
B77: SUELDO | C77: 168 | D77: 375 | E77: =+C77*D77 -> 63000
B78: ADELANTO | C78: 0 | E78: =+C78 -> 0
B79: TOTAL A COBRAR | E79: =+E77-E78 -> 63000
B92: ERROR DE ENERO
B93: JONA
B94: DETALLE | C94: HS TRABAJADAS | D94: VALOR / HORA | E94: IMPORTE
B95: SUELDO | C95: 184 | D95: 150.5 | E95: =C95*D95 -> 27692
B96: EXTRA | C96: 17 | D96: =+D95*1.5 -> 225.75 | E96: =C96*D96 -> 3837.75
B97: AGUINALDO | C97: 0 | E97: =+C97 -> 0
B98: VACACIONES | C98: 14974 | E98: =+C98 -> 14974
B99: NO REMUNERATIVO | C99: 8000 | E99: =+C99 -> 8000
B100: ADELANTO | C100: 3000 | E100: =+C100 -> 3000
B101: total pagado febrero | E101: =+E95+E96+E97+E98+E99-E100 -> 51503.75
E104: =+E101-43529.75 -> 7974

Sheet ABRIL
B1: PILU | G1: EMPLEADO | H1: HS TRABAJADAS | I1: HS EXTRAS | J1: NO REMUN. | K1: VACACIONES | L1: TOTALES | M1: ADELANTO | N1: DEPOSITO | O1: EFVO
B2: DETALLE | C2: HS TRABAJADAS | D2: VALOR / HORA | E2: IMPORTE | G2: PILU | H2: =+E3 -> 32486.4 | I2: =+E4 -> 507.6 | J2: =+E5 -> 8000 | K2: 0 | L2: =+H2+I2+J2+K2 -> 40994 | M2: =+E7 -> 0 | N2: =+E8 -> 25616.57 | O2: =+L2-M2-N2 -> 15377.43
B3: SUELDO | C3: 192 | D3: 169.2 | E3: =C3*D3 -> 32486.4 | G3: JAVI | H3: =+E13 -> 32486.4 | I3: =+E14 -> 0 | J3: =+E15 -> 8000 | K3: 0 | L3: =+H3+I3+J3+K3 -> 40486.4 | M3: =+E17 -> 10000 | N3: =+E18 -> 22240.27 | O3: =+L3-M3-N3 -> 8246.13
B4: EXTRA | C4: 2 | D4: =+D3*1.5 -> 253.8 | E4: =C4*D4 -> 507.6 | G4: FACU | H4: =+E23 -> 34560 | I4: =+E24+E27 -> 810 | J4: =+E25 -> 8000 | K4: 0 | L4: =+H4+I4+J4+K4 -> 43370 | M4: 0 | N4: 0 | O4: =+L4 -> 43370
B5: NO REMUNERATIVO | C5: 8000 | E5: =+C5 -> 8000 | G5: CHACO | H5: =+E32 -> 29952 | I5: =+E33 -> 117 | J5: =+E34 -> 8000 | K5: 0 | L5: =+H5+I5+J5+K5 -> 38069 | M5: =+E36 -> 10000 | N5: 0 | O5: =+L5-M5 -> 28069
B6: TOTAL SUELDO | E6: =+E3+E4+E5 -> 40994 | G6: JUANI | H6: =+E41 -> 37248 | I6: =+E42 -> 1891.5 | J6: =+E43 -> 13500 | L6: =+H6+I6+J6+K6 -> 52639.5 | M6: 0 | N6: =+E45 -> 25616.57 | O6: =+L6-M6-N6 -> 27022.93
B7: ADELANTO | E7: 0 | G7: JONA | H7: =+E50 -> 34560 | I7: =+E51 -> 0 | J7: =+E52 -> 13000 | K7: 0 | L7: =+H7+I7+J7+K7 -> 47560 | M7: =+E54 -> 10000 | N7: 0 | O7: =+L7-M7-N7 -> 37560
B8: DEPOSITO | E8: 25616.57 | G8: MATI | H8: =+E59 -> 25344 | I8: =+E60 -> 891 | J8: =+E61 -> 5000 | K8: 0 | L8: =+H8+I8+J8+K8 -> 31235 | M8: 0 | N8: 0 | O8: =+L8-M8-N8 -> 31235
B9: TOTAL A COBRAR | E9: =+E3+E4+E5-E7-E8 -> 15377.43 | G9: FABIAN | H9: =+E68 -> 21120 | I9: =+E69 -> 165 | J9: 0 | K9: 0 | L9: =K9+H9+I9+J9 -> 21285 | M9: =+E71 -> 0 | N9: 0 | O9: =+L9-M9-N9 -> 21285
G10: SILVI | H10: =+E76 -> 25000 | I10: =+E77 -> 820.3125 | J10: 0 | K10: 0 | L10: =K10+H10+I10+J10 -> 25820.312 | M10: 0 | N10: 0 | O10: =+L10-M10-N10 -> 25820.312
B11: JAVI | G11: TOTALES | M11: =SUM(M2:M10) -> 30000 | N11: =SUM(N2:N10) -> 73473.41 | O11: =SUM(O2:O10) -> 237985.8
B12: DETALLE | C12: HS TRABAJADAS | D12: VALOR / HORA | E12: IMPORTE | M12: =+N11+O11+M11 -> 341459.21
B13: SUELDO | C13: 192 | D13: 169.2 | E13: =C13*D13 -> 32486.4
B14: EXTRA | C14: 0 | D14: =+D13*1.5 -> 253.8 | E14: =C14*D14 -> 0 | G14: FALTA FERIADO DE MARZO
B15: NO REMUNERATIVO | C15: 8000 | E15: =+C15 -> 8000
B16: TOTAL SUELDO | E16: =+E13+E14+E15 -> 40486.4
B17: ADELANTO | E17: 10000 | K17: HORA | L17: HORA X | M17: SOBRESUELDO | N17: NO REM.
B18: DEPOSITO | E18: 22240.27 | G18: EMPLEADOS | H18: ARCHIVO | J18: JUANI | K18: 194 | L18: =+K18*1.5 -> 291 | N18: 13500
B19: TOTAL A COBRAR | E19: =+E13+E14+E15-E17-E18 -> 8246.13 | J19: JONA | K19: 180 | L19: =+K19*1.5 -> 270 | N19: 13000
J20: FACU | K20: 180 | L20: =+K20*1.5 -> 270 | N20: 8000
B21: FACU | H21: DEFINIR AREA DE IMPRESIÓN | J21: PILU | K21: 169.2 | L21: =+K21*1.5 -> 253.8 | N21: 8000
B22: DETALLE | C22: HS TRABAJADAS | D22: VALOR / HORA | E22: IMPORTE | J22: JAVI | K22: 169.2 | L22: =+K22*1.5 -> 253.8 | N22: 8000
B23: SUELDO | C23: 192 | D23: 180 | E23: =C23*D23 -> 34560 | J23: CHACO | K23: 156 | L23: =+K23*1.5 -> 234 | N23: 3000
B24: EXTRA | C24: 3 | D24: =+D23*1.5 -> 270 | E24: =C24*D24 -> 810 | J24: FABIAN | K24: 110 | L24: =+K24*1.5 -> 165 | N24: 7000
B25: NO REMUNERATIVO | C25: 8000 | E25: =+C25 -> 8000 | J25: MATI | K25: 132 | L25: =+K25*1.5 -> 198 | M25: 0 | N25: 5000
B26: TOTAL SUELDO | E26: =+E23+E24+E25 -> 43370
B27: ADELANTO | C27: 0 | E27: 0
B28: TOTAL A COBRAR | E28: =+E23+E24+E25-E27 -> 43370 | H28: DIAS | I28: HS
H29: 16 | I29: 9 | J29: =+H29*I29 -> 144
B30: CHACO | H30: 6 | I30: 8 | J30: =+H30*I30 -> 48
B31: DETALLE | C31: HS TRABAJADAS | D31: VALOR / HORA | E31: IMPORTE | H31: hs mes | J31: =SUM(J29:J30) -> 192
B32: SUELDO | C32: 192 | D32: 156 | E32: =C32*D32 -> 29952
B33: EXTRA | C33: 0.5 | D33: =+D32*1.5 -> 234 | E33: =C33*D33 -> 117
B34: NO REMUNERATIVO | C34: 8000 | E34: =+C34 -> 8000
B35: TOTAL SUELDO | E35: =+E34+E33+E32 -> 38069
B36: ADELANTO | E36: 10000
B37: TOTAL A COBRAR | E37: =+E32+E33+E34-E36 -> 28069
B39: JUANI
B40: DETALLE | C40: HS TRABAJADAS | D40: VALOR / HORA | E40: IMPORTE
B41: SUELDO | C41: 192 | D41: 194 | E41: =C41*D41 -> 37248
B42: EXTRA | C42: 6.5 | D42: =+D41*1.5 -> 291 | E42: =C42*D42 -> 1891.5
B43: NO REMUNERATIVO | C43: 13500 | E43: =+C43 -> 13500
B44: TOTAL SUELDO | E44: =+E43+E42+E41 -> 52639.5
B45: DEPOSITO | E45: 25616.57
B46: TOTAL A COBRAR | E46: =+E41+E42+E43-E45 -> 27022.93
B48: JONA
B49: DETALLE | C49: HS TRABAJADAS | D49: VALOR / HORA | E49: IMPORTE
B50: SUELDO | C50: 192 | D50: 180 | E50: =C50*D50 -> 34560 | F50: FALTA PAGO DE VACACIONES
B51: EXTRA | D51: =+D50*1.5 -> 270 | E51: =C51*D51 -> 0 | F51: FEBRERO 53 HS PAGADAS
B52: NO REMUNERATIVO | C52: 13000 | E52: =+C52 -> 13000 | F52: FALTAN 59 HS. (7,5 DIAS)
B53: TOTAL SUELDO | E53: =+E52+E51+E50 -> 47560
B54: ADELANTO | E54: 10000
B55: TOTAL A COBRAR | E55: =+E50+E51+E52-E54 -> 37560
B57: MATI
B58: DETALLE | C58: HS TRABAJADAS | D58: VALOR / HORA | E58: IMPORTE
B59: SUELDO | C59: 192 | D59: 132 | E59: =C59*D59 -> 25344
B60: EXTRA | C60: 4.5 | D60: =+D59*1.5 -> 198 | E60: =C60*D60 -> 891
B61: NO REMUNERATIVO | C61: 5000 | E61: =+C61 -> 5000
B62: TOTAL SUELDO | E62: =+E61+E60+E59 -> 31235
B63: ADELANTO | E63: =+C63 -> 0
B64: TOTAL A COBRAR | E64: =+E59+E60+E61-E63 -> 31235
B66: FABIAN
B67: DETALLE | C67: HS TRABAJADAS | D67: VALOR / HORA | E67: IMPORTE
B68: SUELDO | C68: 192 | D68: 110 | E68: =C68*D68 -> 21120
B69: EXTRA | C69: 1 | D69: =+D68*1.5 -> 165 | E69: =+C69*D69 -> 165
B70: TOTAL SUELDO | E70: =+E69+E68 -> 21285
B71: ADELANTO | E71: =+C71 -> 0
B72: TOTAL A COBRAR | E72: =+E68+E69-E71 -> 21285
B74: SILVINA
B75: DETALLE | C75: HS TRABAJADAS | D75: VALOR / HORA | E75: IMPORTE
B76: SUELDO | E76: 25000
B77: EXTRA | C77: 3.5 | D77: =+E76/8/20*(1.5) -> 234.375 | E77: =C77*D77 -> 820.3125
B78: TOTAL A COBRAR | E78: =+E76+E77 -> 25820.312

Sheet MAYO
B1: PILU | G1: EMPLEADO | H1: HS TRABAJADAS | I1: HS EXTRAS | J1: NO REMUN. | K1: VACACIONES | L1: TOTALES | M1: ADELANTO | N1: DEPOSITO | O1: EFVO
B2: DETALLE | C2: HS TRABAJADAS | D2: VALOR / HORA | E2: IMPORTE | G2: PILU | H2: =+E3 -> 32317.2 | I2: =+E4 -> 1015.2 | J2: =+E5 -> 8000 | K2: 0 | L2: =+H2+I2+J2+K2 -> 41332.4 | M2: =+E7 -> 0 | N2: =+E8 -> 25616.57 | O2: =+L2-M2-N2 -> 15715.83
B3: SUELDO | C3: 191 | D3: 169.2 | E3: =C3*D3 -> 32317.2 | G3: JAVI | H3: =+E13 -> 7444.8 | I3: 20000 | J3: =+E16 -> 2000 | K3: =+E17+E18 -> 21589.58 | L3: =+H3+I3+J3+K3 -> 51034.38 | M3: =+E20 -> 0 | N3: =+E21 -> 19199.24 | O3: =+L3-M3-N3 -> 31835.14
B4: EXTRA | C4: 4 | D4: =+D3*1.5 -> 253.8 | E4: =C4*D4 -> 1015.2 | G4: FACU | H4: =+E26 -> 34380 | I4: =+E27+E30 -> 1080 | J4: =+E28 -> 8000 | K4: 0 | L4: =+H4+I4+J4+K4 -> 43460 | M4: 0 | N4: 0 | O4: =+L4 -> 43460
B5: NO REMUNERATIVO | C5: 8000 | E5: =+C5 -> 8000 | G5: CHACO | H5: =+E35 -> 29796 | I5: =+E36 -> 2223 | J5: =+E37 -> 8000 | K5: 0 | L5: =+H5+I5+J5+K5 -> 40019 | M5: =+E39 -> 10000 | N5: 0 | O5: =+L5-M5 -> 30019
B6: TOTAL SUELDO | E6: =+E3+E4+E5 -> 41332.4 | G6: JUANI | H6: =+E44 -> 37054 | I6: =+E45 -> 2764.5 | J6: =+E46 -> 13500 | L6: =+H6+I6+J6+K6 -> 53318.5 | M6: 0 | N6: =+E48 -> 25616.57 | O6: =+L6-M6-N6 -> 27701.93
B7: ADELANTO | E7: 0 | G7: JONA | H7: =+E53 -> 26280 | I7: =+E54 -> 0 | J7: =+E56 -> 13000 | K7: =+E55 -> 10620 | L7: =+H7+I7+J7+K7 -> 49900 | M7: =+E58 -> 10000 | N7: 0 | O7: =+L7-M7-N7 -> 39900
B8: DEPOSITO | E8: 25616.57 | G8: MATI | H8: =+E63 -> 19272 | I8: =+E64 -> 0 | J8: =+E65 -> 7000 | K8: =+E66 -> 7392 | L8: =+H8+I8+J8+K8 -> 33664 | M8: 0 | N8: 0 | O8: =+L8-M8-N8 -> 33664
B9: TOTAL A COBRAR | E9: =+E3+E4+E5-E7-E8 -> 15715.83 | G9: FABIAN | H9: =+E73 -> 21010 | I9: =+E74 -> 660 | J9: =+E75 -> 3000 | K9: 0 | L9: =+H9+I9+J9+K9 -> 24670 | M9: =+E77 -> 0 | N9: 0 | O9: =+L9-M9-N9 -> 24670
G10: SILVI | H10: =+E82 -> 25000 | I10: =+E83 -> 0 | J10: 0 | K10: 0 | L10: =K10+H10+I10+J10 -> 25000 | M10: 0 | N10: 0 | O10: =+L10-M10-N10 -> 25000
B11: JAVI | G11: TOTALES MAYO | M11: =SUM(M2:M10) -> 20000 | N11: =SUM(N2:N10) -> 70432.38 | O11: =SUM(O2:O10) -> 271965.9
B12: DETALLE | C12: HS TRABAJADAS | D12: VALOR / HORA | E12: IMPORTE | M12: =+N11+O11+M11 -> 362398.28
B13: SUELDO | C13: 44 | D13: 169.2 | E13: =C13*D13 -> 7444.8
B14: EXTRA | C14: 0 | D14: =+D13*1.5 -> 253.8 | E14: =C14*D14 -> 0 | G14: FALTA FERIADO DE MARZO
B15: EXTRA | E15: 20000
B16: PROPORC. NO REMUN. | C16: 2000 | E16: =+C16 -> 2000
B17: PROP. VACACIONES | E17: 9964.42
B18: PROPORC. AGUINALDO | E18: 11625.16
B19: TOTAL SUELDO | E19: =+E13+E16+E17+E18+E15 -> 51034.38 | K19: HORA | L19: HORA X | M19: SOBRESUELDO | N19: NO REM.
B20: ADELANTO | E20: 0 | G20: EMPLEADOS | H20: ARCHIVO | J20: JUANI | K20: 194 | L20: =+K20*1.5 -> 291 | N20: 13500
B21: DEPOSITO | E21: 19199.24 | J21: JONA | K21: 180 | L21: =+K21*1.5 -> 270 | N21: 13000
B22: TOTAL A COBRAR | E22: =+E19-E20-E21 -> 31835.14 | J22: FACU | K22: 180 | L22: =+K22*1.5 -> 270 | N22: 8000
H23: DEFINIR AREA DE IMPRESIÓN | J23: PILU | K23: 169.2 | L23: =+K23*1.5 -> 253.8 | N23: 8000
B24: FACU | J24: JAVI | K24: 169.2 | L24: =+K24*1.5 -> 253.8 | N24: 8000
B25: DETALLE | C25: HS TRABAJADAS | D25: VALOR / HORA | E25: IMPORTE | J25: CHACO | K25: 156 | L25: =+K25*1.5 -> 234 | N25: 3000
B26: SUELDO | C26: 191 | D26: 180 | E26: =C26*D26 -> 34380 | J26: FABIAN | K26: 110 | L26: =+K26*1.5 -> 165 | N26: 7000
B27: EXTRA | C27: 4 | D27: =+D26*1.5 -> 270 | E27: =C27*D27 -> 1080 | J27: MATI | K27: 132 | L27: =+K27*1.5 -> 198 | M27: 0 | N27: 5000
B28: NO REMUNERATIVO | C28: 8000 | E28: =+C28 -> 8000
B29: TOTAL SUELDO | E29: =+E26+E27+E28 -> 43460
B30: ADELANTO | C30: 0 | E30: 0
B31: TOTAL A COBRAR | E31: =+E29-E30 -> 43460
G32: DIAS | H32: HS
B33: CHACO | G33: 15 | H33: 9 | I33: =+G33*H33 -> 135
B34: DETALLE | C34: HS TRABAJADAS | D34: VALOR / HORA | E34: IMPORTE | G34: 7 | H34: 8 | I34: =+G34*H34 -> 56
B35: SUELDO | C35: 191 | D35: 156 | E35: =C35*D35 -> 29796 | G35: hs mes | I35: =SUM(I33:I34) -> 191
B36: EXTRA | C36: 9.5 | D36: =+D35*1.5 -> 234 | E36: =C36*D36 -> 2223
B37: NO REMUNERATIVO | C37: 8000 | E37: =+C37 -> 8000
B38: TOTAL SUELDO | E38: =+E37+E36+E35 -> 40019
B39: ADELANTO | E39: 10000
B40: TOTAL A COBRAR | E40: =+E35+E36+E37-E39 -> 30019
B42: JUANI
B43: DETALLE | C43: HS TRABAJADAS | D43: VALOR / HORA | E43: IMPORTE
B44: SUELDO | C44: 191 | D44: 194 | E44: =C44*D44 -> 37054
B45: EXTRA | C45: 9.5 | D45: =+D44*1.5 -> 291 | E45: =C45*D45 -> 2764.5
B46: NO REMUNERATIVO | C46: 13500 | E46: =+C46 -> 13500
B47: TOTAL SUELDO | E47: =+E46+E45+E44 -> 53318.5
B48: DEPOSITO | E48: 25616.57
B49: TOTAL A COBRAR | E49: =+E44+E45+E46-E48 -> 27701.93
B51: JONA
B52: DETALLE | C52: HS TRABAJADAS | D52: VALOR / HORA | E52: IMPORTE
B53: SUELDO | C53: 146 | D53: 180 | E53: =C53*D53 -> 26280 | F53: FALTA PAGO DE VACACIONES
B54: EXTRA | D54: =+D53*1.5 -> 270 | E54: =C54*D54 -> 0 | F54: FEBRERO 53 HS PAGADAS
B55: VACACIONES RESTO | C55: 59 | E55: =+C55*D53 -> 10620 | F55: FALTAN 59 HS. (7,5 DIAS)
B56: NO REMUNERATIVO | C56: 13000 | E56: =+C56 -> 13000 | F56: VACACIONES DEL 3 AL 7
B57: TOTAL SUELDO | E57: =+E56+E54+E53+E55 -> 49900
B58: ADELANTO | E58: 10000
B59: TOTAL A COBRAR | E59: =+E57-E58 -> 39900
B61: MATI
B62: DETALLE | C62: HS TRABAJADAS | D62: VALOR / HORA | E62: IMPORTE | F62: VACACIONES DEL 3 AL 7
B63: SUELDO | C63: 146 | D63: 132 | E63: =C63*D63 -> 19272
B64: EXTRA | D64: =+D63*1.5 -> 198 | E64: =C64*D64 -> 0
B65: NO REMUNERATIVO | C65: 7000 | E65: =+C65 -> 7000
B66: VACACIONES | C66: =8*7 -> 56 | D66: 132 | E66: =+C66*D66 -> 7392
B67: TOTAL SUELDO | E67: =+E63+E64+E65+E66 -> 33664
B68: ADELANTO | E68: =+C68 -> 0
B69: TOTAL A COBRAR | E69: =+E67 -> 33664
B71: FABIAN
B72: DETALLE | C72: HS TRABAJADAS | D72: VALOR / HORA | E72: IMPORTE
B73: SUELDO | C73: 191 | D73: 110 | E73: =C73*D73 -> 21010
B74: EXTRA | C74: 4 | D74: =+D73*1.5 -> 165 | E74: =+C74*D74 -> 660
B75: NO REMUNERATIVO | C75: 3000 | E75: =+C75 -> 3000
B76: TOTAL SUELDO | E76: =+E75+E74+E73 -> 24670
B77: ADELANTO | E77: =+C77 -> 0
B78: TOTAL A COBRAR | E78: =+E76-E77 -> 24670
B80: SILVINA
B81: DETALLE | C81: HS TRABAJADAS | D81: VALOR / HORA | E81: IMPORTE
B82: SUELDO | E82: 25000
B83: EXTRA | D83: =+E82/8/20*(1.5) -> 234.375 | E83: =C83*D83 -> 0
B84: TOTAL A COBRAR | E84: =+E82+E83 -> 25000

Sheet JUNIO
B1: PILU | G1: EMPLEADO | H1: HS TRABAJADAS | I1: FERIADOS | J1: HS EXTRAS | K1: NO REMUN. | L1: aguinaldo (mayor mes) | M1: TOTALES | N1: ADELANTO | O1: DEPOSITO | P1: EFVO
B2: DETALLE | C2: HS TRABAJADAS | D2: VALOR / HORA | E2: IMPORTE | G2: PILU | H2: =+E3 -> 31302 | I2: =+E4 -> 1353.6 | J2: =+E5 -> 0 | K2: =+E7 -> 8000 | L2: =+E6 -> 16497 | M2: =SUM(H2:L2) -> 57152.6 | N2: =+E9 -> 0 | O2: =+E10 -> 37221.48 | P2: =+M2-N2-O2 -> 19931.12
B3: SUELDO | C3: 185 | D3: 169.2 | E3: =C3*D3 -> 31302 | G3: FACU | H3: =+E15 -> 33300 | I3: =+E16 -> 1440 | J3: =+E17+E21 -> 1350 | K3: =+E19 -> 8000 | L3: =+E18 -> 18045 | M3: =SUM(H3:L3) -> 62135 | N3: 0 | O3: 0 | P3: =+M3 -> 62135
B4: FERIADO | C4: 8 | D4: 169.2 | E4: =C4*D4 -> 1353.6 | G4: CHACO | H4: =+E26 -> 28860 | I4: =+E27 -> 1248 | J4: =+E28 -> 936 | K4: =+E30 -> 8000 | L4: =+E29 -> 16009.5 | M4: =SUM(H4:L4) -> 55053.5 | N4: =+E32 -> 10000 | O4: 0 | P4: =+M4-N4 -> 45053.5
B5: EXTRA | C5: 0 | D5: =+D3*1.5 -> 253.8 | E5: =C5*D5 -> 0 | G5: JUANI | H5: =+E37 -> 35890 | I5: =+E38 -> 1552 | J5: =+E39 -> 1891.5 | K5: =+E41 -> 13500 | L5: =+E40 -> 20055 | M5: =SUM(H5:L5) -> 72888.5 | N5: 0 | O5: =+E44 -> 0 | P5: =+M5-N5-O5 -> 72888.5
B6: AGUINALDO (base Abril) | E6: =32994/2 -> 16497 | G6: JONA | H6: =+E49 -> 33300 | I6: =+E50 -> 1440 | J6: =+E51 -> 405 | K6: =+E53 -> 13000 | L6: =+E52 -> 17872.5 | M6: =SUM(H6:L6) -> 66017.5 | N6: =+E55 -> 10000 | O6: 0 | P6: =+M6-N6-O6 -> 56017.5
B7: NO REMUNERATIVO | C7: 8000 | E7: =+C7 -> 8000 | G7: MATI | H7: =+E60 -> 24420 | I7: =+E61 -> 1056 | J7: =+E62 -> 1584 | K7: =+E64 -> 7000 | L7: =+E63 -> 13580 | M7: =SUM(H7:L7) -> 47640 | N7: =+E66 -> 0 | O7: 0 | P7: =+M7-N7-O7 -> 47640
B8: TOTAL SUELDO | E8: =SUM(E3:E7) -> 57152.6 | G8: FABIAN | H8: =+E71 -> 20350 | I8: =+E72 -> 880 | J8: =+E73 -> 330 | K8: =+E75 -> 3000 | L8: =+E74 -> 7276.6667 | M8: =SUM(H8:L8) -> 31836.667 | N8: =+E77 -> 4000 | O8: 0 | P8: =+M8-N8-O8 -> 27836.667
B9: ADELANTO | E9: 0 | G9: SILVI | H9: =+E82 -> 25000 | I9: + | J9: =+E84 -> 468.75 | K9: 0 | L9: =+E83 -> 13650 | M9: =SUM(H9:L9) -> 39118.75 | N9: 0 | O9: 0 | P9: =+M9-N9-O9 -> 39118.75
B10: DEPOSITO | E10: 37221.48 | G10: TOTALES JUNIO | N10: =SUM(N2:N9) -> 24000 | O10: =SUM(O2:O9) -> 37221.48 | P10: =SUM(P2:P9) -> 370621.04
B11: TOTAL A COBRAR | E11: =+E8-E10 -> 19931.12 | N11: =+O10+P10+N10 -> 431842.52
G12: DIAS | H12: HS
B13: FACU | F13: LABORAL | G13: 17 | H13: 9 | J13: =+G13*H13 -> 153 | L13: aguinaldo (mayor mes) :194 HS
B14: DETALLE | C14: HS TRABAJADAS | D14: VALOR / HORA | E14: IMPORTE | F14: FERIADO | G14: 1 | H14: 8 | J14: =+G14*H14 -> 8 | L14: sumar hs extras
B15: SUELDO | C15: 185 | D15: 180 | E15: =C15*D15 -> 33300 | F15: VIERNES | G15: 4 | H15: 8 | J15: =+G15*H15 -> 32
B16: FERIADO | C16: 8 | D16: 180 | E16: =C16*D16 -> 1440 | G16: hs mes | J16: =SUM(J13:J15) -> 193
B17: EXTRA | C17: 5 | D17: =+D15*1.5 -> 270 | E17: =C17*D17 -> 1350
B18: AGUINALDO (Base Junio) | E18: =36090/2 -> 18045 | L18: HORA | M18: HORA X | O18: NO REM.
B19: NO REMUNERATIVO | C19: 8000 | E19: =+C19 -> 8000 | K19: JUANI | L19: 194 | M19: =+L19*1.5 -> 291 | O19: 13500
B20: TOTAL SUELDO | E20: =SUM(E15:E19) -> 62135 | G20: EMPLEADOS | H20: ARCHIVO | K20: JONA | L20: 180 | M20: =+L20*1.5 -> 270 | O20: 13000
B21: ADELANTO | C21: 0 | E21: 0 | K21: FACU | L21: 180 | M21: =+L21*1.5 -> 270 | O21: 8000
B22: TOTAL A COBRAR | E22: =+E20-E21 -> 62135 | K22: PILU | L22: 169.2 | M22: =+L22*1.5 -> 253.8 | O22: 8000
H23: DEFINIR AREA DE IMPRESIÓN | K23: CHACO | L23: 156 | M23: =+L23*1.5 -> 234 | O23: 8000
B24: CHACO | K24: FABIAN | L24: 110 | M24: =+L24*1.5 -> 165 | O24: 3000
B25: DETALLE | C25: HS TRABAJADAS | D25: VALOR / HORA | E25: IMPORTE | K25: MATI | L25: 132 | M25: =+L25*1.5 -> 198 | O25: 7000
B26: SUELDO | C26: 185 | D26: 156 | E26: =C26*D26 -> 28860
B27: FERIADO | C27: 8 | D27: 156 | E27: =C27*D27 -> 1248
B28: EXTRA | C28: 4 | D28: =+D26*1.5 -> 234 | E28: =C28*D28 -> 936
B29: AGUINALDO (Base Mayo) | E29: 16009.5
B30: NO REMUNERATIVO | C30: 8000 | E30: =+C30 -> 8000
B31: TOTAL SUELDO | E31: =SUM(E26:E30) -> 55053.5
B32: ADELANTO | E32: 10000
B33: TOTAL A COBRAR | E33: =+E31-E32 -> 45053.5
B35: JUANI
B36: DETALLE | C36: HS TRABAJADAS | D36: VALOR / HORA | E36: IMPORTE
B37: SUELDO | C37: 185 | D37: 194 | E37: =C37*D37 -> 35890
B38: FERIADO | C38: 8 | D38: 194 | E38: =C38*D38 -> 1552
B39: EXTRA | C39: 6.5 | D39: =+D37*1.5 -> 291 | E39: =C39*D39 -> 1891.5
B40: AGUINALDO (Base Marzo) | E40: =40110/2 -> 20055
B41: NO REMUNERATIVO | C41: 13500 | E41: =+C41 -> 13500
B42: TOTAL SUELDO | E42: =SUM(E37:E41) -> 72888.5
B43: ADELANTO | E43: 0
B44: DEPOSITO | E44: 0
B45: TOTAL A COBRAR | E45: =+E42-E43-E44 -> 72888.5
B47: JONA
B48: DETALLE | C48: HS TRABAJADAS | D48: VALOR / HORA | E48: IMPORTE
B49: SUELDO | C49: 185 | D49: 180 | E49: =C49*D49 -> 33300
B50: FERIADO | C50: 8 | D50: 180 | E50: =C50*D50 -> 1440
B51: EXTRA | C51: 1.5 | D51: =+D49*1.5 -> 270 | E51: =C51*D51 -> 405
B52: AGUINALDO (Base Junio) | E52: =35745/2 -> 17872.5
B53: NO REMUNERATIVO | C53: 13000 | E53: =+C53 -> 13000
B54: TOTAL SUELDO | E54: =SUM(E49:E53) -> 66017.5
B55: ADELANTO | E55: 10000
B56: TOTAL A COBRAR | E56: =+E54-E55 -> 56017.5
B58: MATI
B59: DETALLE | C59: HS TRABAJADAS | D59: VALOR / HORA | E59: IMPORTE
B60: SUELDO | C60: 185 | D60: 132 | E60: =C60*D60 -> 24420
B61: FERIADO | C61: 8 | D61: 132 | E61: =C61*D61 -> 1056
B62: EXTRA | C62: 8 | D62: =+D60*1.5 -> 198 | E62: =C62*D62 -> 1584
B63: AGUINALDO (Base Junio) | E63: 13580
B64: NO REMUNERATIVO | C64: 7000 | E64: =+C64 -> 7000
B65: TOTAL SUELDO | E65: =SUM(E60:E64) -> 47640
B66: ADELANTO | E66: 0
B67: TOTAL A COBRAR | E67: =+E65-E66 -> 47640
B69: FABIAN
B70: DETALLE | C70: HS TRABAJADAS | D70: VALOR / HORA | E70: IMPORTE
B71: SUELDO | C71: 185 | D71: 110 | E71: =C71*D71 -> 20350
B72: FERIADO | C72: 8 | D72: 110 | E72: =C72*D72 -> 880
B73: EXTRA | C73: 2 | D73: =+D71*1.5 -> 165 | E73: =+C73*D73 -> 330
B74: AGUINALDO (Base Marzo) | C74: 4 meses | E74: =10915/6*4 -> 7276.6667
B75: NO REMUNERATIVO | C75: 3000 | E75: =+C75 -> 3000
B76: TOTAL SUELDO | E76: =SUM(E71:E75) -> 31836.667
B77: ADELANTO | E77: 4000
B78: TOTAL A COBRAR | E78: =+E76-E77 -> 27836.667
B80: SILVINA
B81: DETALLE | C81: HS TRABAJADAS | D81: VALOR / HORA | E81: IMPORTE
B82: SUELDO | E82: 25000
B83: AGUINALDO | E83: 13650
B84: EXTRA | C84: 2 | D84: =+E82/8/20*(1.5) -> 234.375 | E84: =C84*D84 -> 468.75
B85: TOTAL A COBRAR | E85: =+E83+E82+E84 -> 39118.75

Sheet JULIO
B1: PILU | H1: EMPLEADO | I1: HS TRABAJADAS | J1: FERIADOS | K1: HS EXTRAS | L1: NO REMUN. | M1: TOTALES | N1: ADELANTO | O1: DEPOSITO | P1: EFVO
B2: DETALLE | C2: HS TRABAJADAS | D2: VALOR / HORA | E2: IMPORTE | H2: PILU | I2: =+E3 -> 31302 | J2: =+E5 -> 1353.6 | K2: =+E6+E7+E4 -> 3634.5 | L2: =+E8 -> 8000 | M2: =SUM(I2:L2) -> 44290.1 | N2: =+E10 -> 0 | O2: =+E11 -> 25616.57 | P2: =+M2-N2-O2 -> 18673.53
B3: SUELDO | C3: 185 | D3: 169.2 | E3: =C3*D3 -> 31302 | H3: FACU | I3: =+E16 -> 33300 | J3: =+E18 -> 1440 | K3: =+E20+E19+E17 -> 5655 | L3: =+E21 -> 8000 | M3: =SUM(I3:L3) -> 48395 | N3: 0 | O3: 0 | P3: =+M3 -> 48395
B4: EXTRA POR VIAJE | E4: 3000 | H4: CHACO | I4: =+E28 -> 28860 | J4: =+E30 -> 1248 | K4: =+E31+E32+E29 -> 3585 | L4: =+E33 -> 8000 | M4: =SUM(I4:L4) -> 41693 | N4: =+E35 -> 10000 | O4: 0 | P4: =+M4-N4 -> 31693
B5: FERIADO | C5: 8 | D5: 169.2 | E5: =C5*D5 -> 1353.6 | H5: JUANI | I5: =+E40 -> 35890 | J5: =+E41 -> 1552 | K5: =+E43+E42 -> 3152.5 | L5: =+E44 -> 13500 | M5: =SUM(I5:L5) -> 54094.5 | N5: 0 | O5: =+E47 -> 25616.57 | P5: =+M5-N5-O5 -> 28477.93
B6: EXTRA | C6: 2.5 | D6: =+D3*1.5 -> 253.8 | E6: =C6*D6 -> 634.5 | H6: JONA | I6: =+E52+E56+E57+E58 -> 31500 | J6: =+E53 -> 1440 | K6: =+E54+E55 -> 2385 | L6: =+E59 -> 13000 | M6: =SUM(I6:L6) -> 48325 | N6: =+E61 -> 6000 | O6: 0 | P6: =+M6-N6-O6 -> 42325
B7: EXTRA AL 100% | C7: 0 | D7: =+D5*2 -> 338.4 | E7: =+C7*D7 -> 0 | H7: MATI | I7: =+E66+E68 -> 23100 | J7: =+E67 -> 1056 | K7: =+E69+E70 -> 1650 | L7: =+E71 -> 12000 | M7: =SUM(I7:L7) -> 37806 | N7: =+E73 -> 0 | O7: 0 | P7: =+M7-N7-O7 -> 37806
B8: NO REMUNERATIVO | C8: 8000 | E8: =+C8 -> 8000 | H8: FABIAN | I8: =+E78 -> 4840 | J8: 0 | K8: =+E79 -> 160 | L8: 0 | M8: =SUM(I8:L8) -> 5000 | N8: =+E81 -> 0 | O8: 0 | P8: =+M8-N8-O8 -> 5000
B9: TOTAL SUELDO | E9: =SUM(E3:E8) -> 44290.1 | H9: SILVI | I9: =+E86 -> 25000 | J9: 0 | K9: =+E87 -> 3281.25 | L9: 0 | M9: =SUM(I9:L9) -> 28281.25 | N9: 0 | O9: 0 | P9: =+M9-N9-O9 -> 28281.25
B10: ADELANTO | E10: 0 | H10: TOTALES JULIO | N10: =SUM(N2:N9) -> 16000 | O10: =SUM(O2:O9) -> 51233.14 | P10: =SUM(P2:P9) -> 240651.71
B11: DEPOSITO | E11: 25616.57 | N11: =+O10+P10+N10 -> 307884.85
B12: TOTAL A COBRAR | E12: =+E9-E11 -> 18673.53 | H12: DIAS | I12: HS | J12: JULIO
G13: LABORAL | H13: 17 | I13: 9 | J13: =+H13*I13 -> 153
B14: FACU | G14: FERIADO | H14: 1 | I14: 8 | J14: =+H14*I14 -> 8
B15: DETALLE | C15: HS TRABAJADAS | D15: VALOR / HORA | E15: IMPORTE | G15: VIERNES | H15: 4 | I15: 8 | J15: =+H15*I15 -> 32
B16: SUELDO | C16: 185 | D16: 180 | E16: =C16*D16 -> 33300 | H16: hs mes | J16: =SUM(J13:J15) -> 193
B17: EXTRA POR VIAJE | E17: 3000
B18: FERIADO | C18: 8 | D18: 180 | E18: =C18*D18 -> 1440 | M18: HORA | N18: HORA X | O18: NO REM.
B19: EXTRA AL 100% | C19: 1 | D19: =+D16*2 -> 360 | E19: =C19*D19 -> 360 | L19: JUANI | M19: 194 | N19: =+M19*1.5 -> 291 | O19: 13500
B20: EXTRA | C20: 8.5 | D20: =+D16*1.5 -> 270 | E20: =C20*D20 -> 2295 | H20: EMPLEADOS | I20: ARCHIVO | L20: JONA | M20: 180 | N20: =+M20*1.5 -> 270 | O20: 13000
B21: NO REMUNERATIVO | C21: 8000 | E21: =+C21 -> 8000 | L21: FACU | M21: 180 | N21: =+M21*1.5 -> 270 | O21: 8000
B22: TOTAL SUELDO | E22: =SUM(E16:E21) -> 48395 | L22: PILU | M22: 169.2 | N22: =+M22*1.5 -> 253.8 | O22: 8000
B23: ADELANTO | E23: 0 | I23: DEFINIR AREA DE IMPRESIÓN | L23: CHACO | M23: 156 | N23: =+M23*1.5 -> 234 | O23: 8000
B24: TOTAL A COBRAR | E24: =+E22-E23 -> 48395 | L24: FABIAN | M24: 110 | N24: =+M24*1.5 -> 165 | O24: 3000
L25: MATI | M25: 132 | N25: =+M25*1.5 -> 198 | O25: 12000
B26: CHACO
B27: DETALLE | C27: HS TRABAJADAS | D27: VALOR / HORA | E27: IMPORTE
B28: SUELDO | C28: 185 | D28: 156 | E28: =C28*D28 -> 28860
B29: EXTRA POR VIAJE | E29: 3000
B30: FERIADO | C30: 8 | D30: 156 | E30: =C30*D30 -> 1248 | G30: RAFAELA
B31: EXTRA AL 100% | C31: 0 | D31: =+D28*2 -> 312 | E31: =C31*D31 -> 0 | G31: 44390 | H31: 6,30 A 17 HS | I31: 1.5
B32: EXTRA | C32: 2.5 | D32: =+D28*1.5 -> 234 | E32: =C32*D32 -> 585 | G32: 44391 | H32: 9 A 18 HS | I32: 0
B33: NO REMUNERATIVO | C33: 8000 | E33: =+C33 -> 8000 | G33: 44396 | H33: 7 a 17 hs | I33: 1
B34: TOTAL SUELDO | E34: =SUM(E28:E33) -> 41693 | G34: 44397 | H34: 8,30 a 17,30 hs | I34: 0
B35: ADELANTO | E35: 10000 | G35: 44398 | H35: 8,00 a 17,30 hs | I35: 0
B36: TOTAL A COBRAR | E36: =+E34-E35 -> 31693 | G36: hs. Extras | I36: 2.5
B38: JUANI | G38: plasticos san fco | H38: 6 hs | I38: 1 h. al 100%
B39: DETALLE | C39: HS TRABAJADAS | D39: VALOR / HORA | E39: IMPORTE | G39: juani/jona/facu/mati
B40: SUELDO | C40: 185 | D40: 194 | E40: =C40*D40 -> 35890
B41: FERIADO | C41: 8 | D41: 194 | E41: =C41*D41 -> 1552
B42: EXTRA AL 100% | C42: 1 | D42: =+D40*2 -> 388 | E42: =C42*D42 -> 388
B43: EXTRA | C43: 9.5 | D43: =+D40*1.5 -> 291 | E43: =C43*D43 -> 2764.5
B44: NO REMUNERATIVO | C44: 13500 | E44: =+C44 -> 13500
B45: TOTAL SUELDO | E45: =SUM(E40:E44) -> 54094.5
B46: ADELANTO | E46: 0
B47: DEPOSITO | E47: 25616.57
B48: TOTAL A COBRAR | E48: =+E45-E46-E47 -> 28477.93 | G48: 4 DIAS
B50: JONA | F50: 07/07 9,30 SE FUE POR DOLOR DE PANZA
B51: DETALLE | C51: HS TRABAJADAS | D51: VALOR / HORA | E51: IMPORTE | F51: 19/07 ACCIDENTE | G51: =11*9 -> 99
B52: SUELDO | C52: 131 | D52: 180 | E52: =C52*D52 -> 23580 | F52: 27/07 se pidio el dia | G52: =4*8 -> 32
B53: FERIADO | C53: 8 | D53: 180 | E53: =C53*D53 -> 1440 | G53: =4*8 -> 32
B54: EXTRA AL 100% | C54: 1 | D54: =+D52*2 -> 360 | E54: =C54*D54 -> 360 | F54: 11 DIAS DE 9 HS | G54: =1*8 -> 8
B55: EXTRA | C55: =6+1.5 -> 7.5 | D55: =+D52*1.5 -> 270 | E55: =C55*D55 -> 2025 | F55: 4 DIAS DE 8 HS
B56: 4 DIAS POR SINIESTRO | C56: 32 | D56: =+D52 -> 180 | E56: =+C56*D56 -> 5760 | F56: 4 DIAS DE ACCIDENTE
B57: 07/07 RETIRO 9,30 HS | C57: 2 | D57: =+C57*D52 -> 360 | E57: =+C57*D57 -> 720 | F57: 1 DIA VACACIONES
B58: 27/07 DIA VACAC. | C58: 8 | D58: =+D52 -> 180 | E58: =+C58*D58 -> 1440
B59: NO REMUNERATIVO | C59: 13000 | E59: =+C59 -> 13000 | F59: quedan dos dias de vacaciones
B60: TOTAL SUELDO | E60: =SUM(E52:E59) -> 48325
B61: ADELANTO | E61: 6000
B62: TOTAL A COBRAR | E62: =+E60-E61 -> 42325
B64: MATI
B65: DETALLE | C65: HS TRABAJADAS | D65: VALOR / HORA | E65: IMPORTE
B66: SUELDO | C66: 167 | D66: 132 | E66: =C66*D66 -> 22044 | F66: 05/07 NO TRABAJO
B67: FERIADO | C67: 8 | D67: 132 | E67: =C67*D67 -> 1056 | F67: 20/07 fallece abuelo | G67: =15*9 -> 135
B68: LICENCIA X FALLEC. | C68: 8 | D68: 132 | E68: =C68*D68 -> 1056 | G68: 8
B69: EXTRA AL 100% | C69: 1 | D69: =+D66*2 -> 264 | E69: =C69*D69 -> 264 | G69: =4*8 -> 32
B70: EXTRA | C70: 7 | D70: =+D66*1.5 -> 198 | E70: =C70*D70 -> 1386 | F70: 15 DIAS TRABAJADOS
B71: NO REMUNERATIVO | C71: 12000 | E71: =+C71 -> 12000 | F71: 1 DIA POR LICENCIA
B72: TOTAL SUELDO | E72: =SUM(E66:E71) -> 37806 | F72: 4 VIERNES
B73: ADELANTO | E73: 0
B74: TOTAL A COBRAR | E74: =+E72-E73 -> 37806
B76: FABIAN
B77: DETALLE | C77: HS TRABAJADAS | D77: VALOR / HORA | E77: IMPORTE
B78: SUELDO | C78: 44 | D78: 110 | E78: =C78*D78 -> 4840
B79: EXTRA | C79: 1 | D79: 160 | E79: =+C79*D79 -> 160
B80: TOTAL SUELDO | E80: =SUM(E78:E79) -> 5000
B81: ADELANTO
B82: TOTAL A COBRAR | E82: =+E80-E81 -> 5000
B84: SILVINA
B85: DETALLE | C85: HS TRABAJADAS | D85: VALOR / HORA | E85: IMPORTE
B86: SUELDO | E86: 25000
B87: EXTRA | C87: 14 | D87: =+E86/8/20*(1.5) -> 234.375 | E87: =C87*D87 -> 3281.25
B88: TOTAL A COBRAR | E88: =+E86+E87 -> 28281.25

Sheet AGOSTO
B1: PILU | H1: EMPLEADO | I1: HS TRABAJADAS | J1: FERIADOS | K1: HS EXTRAS | L1: NO REMUN. | M1: TOTALES | N1: ADELANTO | O1: DEPOSITO | P1: EFVO
B2: DETALLE | C2: HS TRABAJADAS | D2: VALOR / HORA | E2: IMPORTE | H2: PILU | I2: =+E3 -> 35735.04 | J2: =+E5 -> 3248.64 | K2: =+E6+E7+E4 -> 761.4 | L2: =+E8 -> 8000 | M2: =SUM(I2:L2) -> 47745.08 | N2: =+E10 -> 0 | O2: =+E11 -> 26672.78 | P2: =+M2-N2-O2 -> 21072.3
B3: SUELDO | C3: 176 | D3: 203.04 | E3: =C3*D3 -> 35735.04 | H3: FACU | I3: =+E16 -> 40972.8 | J3: =+E18 -> 3724.8 | K3: =+E20+E19+E17 -> 3666.6 | L3: =+E21 -> 13000 | M3: =SUM(I3:L3) -> 61364.2 | N3: =+E23 -> 10000 | O3: 0 | P3: =+M3-N3-O3 -> 51364.2
B4: EXTRA POR VIAJE | C4: 0 | H4: CHACO | I4: =+E28 -> 32947.2 | J4: =+E30 -> 2496 | K4: =+E31+E32+E29 -> 3229.2 | L4: =+E33 -> 8000 | M4: =SUM(I4:L4) -> 46672.4 | N4: =+E35 -> 10000 | O4: 0 | P4: =+M4-N4-O4 -> 36672.4
B5: FERIADO | C5: 16 | D5: 203.04 | E5: =C5*D5 -> 3248.64 | H5: JUANI | I5: =+E40 -> 40972.8 | J5: =+E41 -> 3724.8 | K5: =+E43+E42 -> 2793.6 | L5: =+E44 -> 13500 | M5: =SUM(I5:L5) -> 60991.2 | N5: =+E46 -> 0 | O5: =+E47 -> 26672.78 | P5: =+M5-N5-O5 -> 34318.42
B6: EXTRA | C6: 2.5 | D6: =+D3*1.5 -> 304.56 | E6: =C6*D6 -> 761.4 | H6: JONA | I6: =+E52+E54 -> 38016 | J6: =+E53 -> 3456 | K6: =+E55+E56 -> 1458 | L6: =+E57 -> 13000 | M6: =SUM(I6:L6) -> 55930 | N6: =+E59 -> 10000 | O6: 0 | P6: =+M6-N6-O6 -> 45930
B7: EXTRA AL 100% | C7: 0 | D7: =+D5*2 -> 406.08 | E7: =+C7*D7 -> 0 | H7: MATI | I7: =+E64+E66 -> 27720 | J7: =+E65 -> 2534.4 | K7: =+E67+E68 -> 2257.2 | L7: =+E69 -> 8000 | M7: =SUM(I7:L7) -> 40511.6 | N7: =+E71 -> 0 | O7: 0 | P7: =+M7-N7-O7 -> 40511.6
B8: NO REMUNERATIVO | C8: 8000 | E8: =+C8 -> 8000 | H8: SILVI | I8: =+E77 -> 30000 | J8: 0 | K8: =+E78 -> 3375 | L8: 0 | M8: =SUM(I8:L8) -> 33375 | N8: 0 | O8: 0 | P8: =+M8-N8-O8 -> 33375
B9: TOTAL SUELDO | E9: =SUM(E3:E8) -> 47745.08 | H9: TOTALES JULIO | N9: =SUM(N2:N8) -> 30000 | O9: =SUM(O2:O8) -> 53345.56 | P9: =SUM(P2:P8) -> 263243.92
B10: ADELANTO | E10: 0 | N10: =+O9+P9+N9 -> 346589.48
B11: DEPOSITO | E11: 26672.78
B12: TOTAL A COBRAR | E12: =+E9-E11 -> 21072.3 | M12: HORA | N12: HORA X | O12: NO REM.
L13: JUANI | M13: =194*1.2 -> 232.8 | N13: =+M13*1.5 -> 349.2 | O13: 13500
B14: FACU | H14: DIAS | I14: HS | J14: JULIO | L14: JONA | M14: =180*1.2 -> 216 | N14: =+M14*1.5 -> 324 | O14: 13000
B15: DETALLE | C15: HS TRABAJADAS | D15: VALOR / HORA | E15: IMPORTE | G15: LABORAL | H15: 16 | I15: 9 | J15: =+H15*I15 -> 144 | L15: FACU | M15: =180*1.2 -> 216 | N15: =+M15*1.5 -> 324 | O15: 13000
B16: SUELDO | C16: 176 | D16: 232.8 | E16: =C16*D16 -> 40972.8 | G16: FERIADO | H16: 2 | I16: 8 | J16: =+H16*I16 -> 16 | L16: PILU | M16: =169.2*1.2 -> 203.04 | N16: =+M16*1.5 -> 304.56 | O16: 8000
B17: EXTRA POR VIAJE | C17: 0 | E17: 0 | G17: VIERNES | H17: 4 | I17: 8 | J17: =+H17*I17 -> 32 | L17: CHACO | M17: =156*1.2 -> 187.2 | N17: =+M17*1.5 -> 280.8 | O17: 8000
B18: FERIADO | C18: 16 | D18: 232.8 | E18: =C18*D18 -> 3724.8 | H18: hs mes | J18: =SUM(J15:J17) -> 192 | L18: MATI | M18: =132*1.2 -> 158.4 | N18: =+M18*1.5 -> 237.6 | O18: 8000
B19: EXTRA AL 100% | C19: 0 | D19: =+D16*2 -> 465.6 | E19: =C19*D19 -> 0
B20: EXTRA | C20: 10.5 | D20: =+D16*1.5 -> 349.2 | E20: =C20*D20 -> 3666.6 | F20: faltaban declarar 9 Hs | I20: RAFAELA (extras)
B21: NO REMUNERATIVO | C21: 13000 | E21: =+C21 -> 13000 | F21: =9*D20 -> 3142.8 | I21: Chaco, Pilu, Mati
B22: TOTAL SUELDO | E22: =SUM(E16:E21) -> 61364.2 | I22: 44419 | J22: 3
B23: ADELANTO | E23: 10000 | I23: 44425 | J23: 2
B24: TOTAL A COBRAR | E24: =+E22-E23 -> 51364.2 | I24: 44426 | J24: 1.5
I25: 44439 | J25: 1 | K25: chaco y pilu
B26: CHACO | I26: hs. Extras
B27: DETALLE | C27: HS TRABAJADAS | D27: VALOR / HORA | E27: IMPORTE
B28: SUELDO | C28: 176 | D28: 187.2 | E28: =C28*D28 -> 32947.2 | G28: SABADO | H28: 5
B29: EXTRA POR VIAJE | C29: 0 | E29: 0 | G29: CHACO
B30: FERIADO | C30: 16 | D30: 156 | E30: =C30*D30 -> 2496
B31: EXTRA AL 100% | C31: 0 | D31: =+D28*2 -> 374.4 | E31: =C31*D31 -> 0
B32: EXTRA | C32: 11.5 | D32: =+D28*1.5 -> 280.8 | E32: =C32*D32 -> 3229.2
B33: NO REMUNERATIVO | C33: 8000 | E33: =+C33 -> 8000
B34: TOTAL SUELDO | E34: =SUM(E28:E33) -> 46672.4
B35: ADELANTO | E35: 10000
B36: TOTAL A COBRAR | E36: =+E34-E35 -> 36672.4
B38: JUANI
B39: DETALLE | C39: HS TRABAJADAS | D39: VALOR / HORA | E39: IMPORTE
B40: SUELDO | C40: 176 | D40: 232.8 | E40: =C40*D40 -> 40972.8
B41: FERIADO | C41: 16 | D41: 232.8 | E41: =C41*D41 -> 3724.8
B42: EXTRA AL 100% | C42: 0 | D42: =+D40*2 -> 465.6 | E42: =C42*D42 -> 0
B43: EXTRA | C43: 8 | D43: =+D40*1.5 -> 349.2 | E43: =C43*D43 -> 2793.6
B44: NO REMUNERATIVO | C44: 13500 | E44: =+C44 -> 13500
B45: TOTAL SUELDO | E45: =SUM(E40:E44) -> 60991.2
B46: ADELANTO | E46: 0
B47: DEPOSITO | E47: 26672.78
B48: TOTAL A COBRAR | E48: =+E45-E46-E47 -> 34318.42
B50: JONA
B51: DETALLE | C51: HS TRABAJADAS | D51: VALOR / HORA | E51: IMPORTE
B52: SUELDO | C52: 160 | D52: 216 | E52: =+C52*D52 -> 34560
B53: FERIADO | C53: 16 | D53: 216 | E53: =C53*D53 -> 3456
B54: 2 DIAS POR ENFERMEDAD | C54: 16 | D54: =+D52 -> 216 | E54: =+C54*D54 -> 3456 | F54: 24/08 ENFERMO
B55: EXTRA AL 100% | C55: 0 | D55: =+D52*2 -> 432 | E55: =C55*D55 -> 0 | F55: 25/08 ENFERMO
B56: EXTRA | C56: 4.5 | D56: =+D52*1.5 -> 324 | E56: =C56*D56 -> 1458 | F56: quedan 2 dias de vacac.
B57: NO REMUNERATIVO | C57: 13000 | E57: =+C57 -> 13000
B58: TOTAL SUELDO | E58: =SUM(E52:E57) -> 55930
B59: ADELANTO | E59: 10000
B60: TOTAL A COBRAR | E60: =+E58-E59 -> 45930
B62: MATI
B63: DETALLE | C63: HS TRABAJADAS | D63: VALOR / HORA | E63: IMPORTE | F63: 10/08 NO TRABAJO
B64: SUELDO | C64: 167 | D64: 158.4 | E64: =C64*D64 -> 26452.8 | F64: DEBE 1,5 HS.
B65: FERIADO | C65: 16 | D65: 158.4 | E65: =C65*D65 -> 2534.4
B66: DIA POR ENFERMEDAD | C66: 8 | D66: =+D65 -> 158.4 | E66: =C66*D66 -> 1267.2
B67: EXTRA AL 100% | C67: 0 | D67: =+D64*2 -> 316.8 | E67: =C67*D67 -> 0
B68: EXTRA (-1,5 Hs x retiro) | C68: 9.5 | D68: =+D64*1.5 -> 237.6 | E68: =C68*D68 -> 2257.2
B69: NO REMUNERATIVO | C69: 8000 | E69: 8000
B70: TOTAL SUELDO | E70: =SUM(E64:E69) -> 40511.6
B71: ADELANTO | E71: 0
B72: TOTAL A COBRAR | E72: =+E70-E71 -> 40511.6
B75: SILVINA
B76: DETALLE | C76: HS TRABAJADAS | D76: VALOR / HORA | E76: IMPORTE
B77: SUELDO | E77: 30000
B78: EXTRA | C78: 12 | D78: =+E77/8/20*(1.5) -> 281.25 | E78: =C78*D78 -> 3375
B79: TOTAL A COBRAR | E79: =+E77+E78 -> 33375

Sheet SEPT
B1: PILU | H1: EMPLEADO | I1: HS TRABAJADAS | J1: FERIADOS | K1: HS EXTRAS | L1: NO REMUN. | M1: TOTALES | N1: ADELANTO | O1: DEPOSITO | P1: EFVO
B2: DETALLE | C2: HS TRABAJADAS | D2: VALOR / HORA | E2: IMPORTE | H2: PILU | I2: =+E3 -> 39389.76 | J2: =+E5 -> 0 | K2: =+E6+E7+E4 -> 304.56 | L2: =+E8 -> 8000 | M2: =SUM(I2:L2) -> 47694.32 | N2: =+E10 -> 0 | O2: =+E11 -> 28979.54 | P2: =+M2-N2-O2 -> 18714.78
B3: SUELDO | C3: 194 | D3: 203.04 | E3: =C3*D3 -> 39389.76 | H3: FACU | I3: =+E16 -> 45163.2 | J3: =+E18 -> 0 | K3: =+E21+E20+E17 -> 0 | L3: =+E22 -> 13000 | M3: =SUM(I3:L3) -> 58163.2 | N3: =+E24 -> 0 | O3: 0 | P3: =+M3-N3-O3 -> 58163.2
B4: EXTRA POR VIAJE | C4: 0 | H4: CHACO | I4: =+E29 -> 36316.8 | J4: =+E31 -> 0 | K4: =+E32+E33+E30 -> 0 | L4: =+E34 -> 8000 | M4: =SUM(I4:L4) -> 44316.8 | N4: =+E36 -> 10000 | O4: 0 | P4: =+M4-N4-O4 -> 34316.8
B5: FERIADO | C5: 0 | D5: 203.04 | E5: =C5*D5 -> 0 | H5: JUANI | I5: =+E41 -> 45163.2 | J5: =+E42 -> 0 | K5: =+E44+E43 -> 1746 | L5: =+E45 -> 13500 | M5: =SUM(I5:L5) -> 60409.2 | N5: =+E47 -> 0 | O5: =+E48 -> 29538.76 | P5: =+M5-N5-O5 -> 30870.44
B6: EXTRA | C6: 1 | D6: =+D3*1.5 -> 304.56 | E6: =C6*D6 -> 304.56 | H6: JONA | I6: =+E53 -> 41904 | J6: =+E54 -> 0 | K6: =+E55+E56 -> 0 | L6: =+E57 -> 13000 | M6: =SUM(I6:L6) -> 54904 | N6: =+E59 -> 12000 | O6: 0 | P6: =+M6-N6-O6 -> 42904
B7: EXTRA AL 100% | C7: 0 | D7: =+D5*2 -> 406.08 | E7: =+C7*D7 -> 0 | H7: MATI | I7: =+E64 -> 30729.6 | J7: =+E65 -> 0 | K7: =+E66+E67 -> 0 | L7: =+E68 -> 8000 | M7: =SUM(I7:L7) -> 38729.6 | N7: =+E70 -> 0 | O7: 0 | P7: =+M7-N7-O7 -> 38729.6
B8: NO REMUNERATIVO | C8: 8000 | E8: =+C8 -> 8000 | H8: LUCAS | I8: =+E83 -> 27720 | J8: =+E84 -> 0 | K8: =+E85 -> 0 | L8: =+E87 -> 8000 | M8: =SUM(I8:L8) -> 35720 | N8: =+E89 -> 8000 | O8: 0 | P8: =+M8-N8 -> 27720
B9: TOTAL SUELDO | E9: =SUM(E3:E8) -> 47694.32 | H9: SILVI | I9: =+E76 -> 30000 | J9: 0 | K9: =+E77 -> 4050 | L9: 0 | M9: =SUM(I9:L9) -> 34050 | N9: 0 | O9: 0 | P9: =+M9-N9-O9 -> 34050
B10: ADELANTO | E10: 0 | H10: TOTALES JULIO | N10: =SUM(N2:N9) -> 30000 | O10: =SUM(O2:O9) -> 58518.3 | P10: =SUM(P2:P9) -> 285468.82
B11: DEPOSITO | E11: 28979.54 | N11: =+O10+P10+N10 -> 373987.12
B12: TOTAL A COBRAR | E12: =+E9-E11 -> 18714.78
M13: HORA | N13: HORA X | O13: NO REM.
B14: FACU | L14: JUANI | M14: =194*1.2 -> 232.8 | N14: =+M14*1.5 -> 349.2 | O14: 13500
B15: DETALLE | C15: HS TRABAJADAS | D15: VALOR / HORA | E15: IMPORTE | H15: DIAS | I15: HS | J15: SEPT | L15: JONA | M15: =180*1.2 -> 216 | N15: =+M15*1.5 -> 324 | O15: 13000
B16: SUELDO | C16: 194 | D16: 232.8 | E16: =C16*D16 -> 45163.2 | G16: LABORAL | H16: 18 | I16: 9 | J16: =+H16*I16 -> 162 | L16: FACU | M16: =180*1.2 -> 216 | N16: =+M16*1.5 -> 324 | O16: 13000
B17: EXTRA POR VIAJE | C17: 0 | E17: 0 | F17: 08/09/21 RETIRO 11,30 | G17: FERIADO | H17: 0 | I17: 8 | J17: =+H17*I17 -> 0 | L17: PILU | M17: =169.2*1.2 -> 203.04 | N17: =+M17*1.5 -> 304.56 | O17: 8000
B18: FERIADO | C18: 0 | D18: 232.8 | E18: =C18*D18 -> 0 | G18: VIERNES | H18: 4 | I18: 8 | J18: =+H18*I18 -> 32 | L18: CHACO | M18: =156*1.2 -> 187.2 | N18: =+M18*1.5 -> 280.8 | O18: 8000
B19: HORAS EXTRAS AGOSTO | C19: 9 | D19: =+D21 -> 349.2 | E19: =C19*D19 -> 3142.8 | H19: hs mes | J19: =SUM(J16:J18) -> 194 | L19: LUCAS | M19: 165 | N19: =+M19*1.5 -> 247.5 | O19: 8000
B20: EXTRA AL 100% | C20: 0 | D20: =+D16*2 -> 465.6 | E20: =C20*D20 -> 0 | F20: faltaban declarar 9 Hs | L20: MATI | M20: =132*1.2 -> 158.4 | N20: =+M20*1.5 -> 237.6 | O20: 8000
B21: EXTRA | C21: 0 | D21: =+D16*1.5 -> 349.2 | E21: =C21*D21 -> 0 | F21: =9*D21 -> 3142.8
B22: NO REMUNERATIVO | C22: 13000 | E22: =+C22 -> 13000
B23: TOTAL SUELDO | E23: =SUM(E16:E22) -> 61306
B24: ADELANTO | E24: 0
B25: TOTAL A COBRAR | E25: =+E23-E24 -> 61306
B27: CHACO
B28: DETALLE | C28: HS TRABAJADAS | D28: VALOR / HORA | E28: IMPORTE
B29: SUELDO | C29: 194 | D29: 187.2 | E29: =C29*D29 -> 36316.8
B30: EXTRA POR VIAJE | C30: 0 | E30: 0
B31: FERIADO | C31: 0 | D31: 156 | E31: =C31*D31 -> 0
B32: EXTRA AL 100% | C32: 0 | D32: =+D29*2 -> 374.4 | E32: =C32*D32 -> 0
B33: EXTRA | C33: 0 | D33: =+D29*1.5 -> 280.8 | E33: =C33*D33 -> 0
B34: NO REMUNERATIVO | C34: 8000 | E34: =+C34 -> 8000
B35: TOTAL SUELDO | E35: =SUM(E29:E34) -> 44316.8
B36: ADELANTO | E36: 10000
B37: TOTAL A COBRAR | E37: =+E35-E36 -> 34316.8
B39: JUANI
B40: DETALLE | C40: HS TRABAJADAS | D40: VALOR / HORA | E40: IMPORTE
B41: SUELDO | C41: 194 | D41: 232.8 | E41: =C41*D41 -> 45163.2
B42: FERIADO | C42: 0 | D42: 232.8 | E42: =C42*D42 -> 0
B43: EXTRA AL 100% | C43: 0 | D43: =+D41*2 -> 465.6 | E43: =C43*D43 -> 0
B44: EXTRA | C44: 5 | D44: =+D41*1.5 -> 349.2 | E44: =C44*D44 -> 1746
B45: NO REMUNERATIVO | C45: 13500 | E45: =+C45 -> 13500
B46: TOTAL SUELDO | E46: =SUM(E41:E45) -> 60409.2
B47: ADELANTO | E47: 0
B48: DEPOSITO | E48: 29538.76
B49: TOTAL A COBRAR | E49: =+E46-E47-E48 -> 30870.44
B51: JONA
B52: DETALLE | C52: HS TRABAJADAS | D52: VALOR / HORA | E52: IMPORTE
B53: SUELDO | C53: 194 | D53: 216 | E53: =+C53*D53 -> 41904
B54: FERIADO | C54: 0 | D54: 216 | E54: =C54*D54 -> 0
B55: EXTRA AL 100% | C55: 0 | D55: =+D53*2 -> 432 | E55: =C55*D55 -> 0
B56: EXTRA | C56: 0 | D56: =+D53*1.5 -> 324 | E56: =C56*D56 -> 0 | F56: quedan 2 dias de vacac.
B57: NO REMUNERATIVO | C57: 13000 | E57: =+C57 -> 13000
B58: TOTAL SUELDO | E58: =SUM(E53:E57) -> 54904
B59: ADELANTO | E59: 12000
B60: TOTAL A COBRAR | E60: =+E58-E59 -> 42904
B62: MATI
B63: DETALLE | C63: HS TRABAJADAS | D63: VALOR / HORA | E63: IMPORTE
B64: SUELDO | C64: 194 | D64: 158.4 | E64: =C64*D64 -> 30729.6
B65: FERIADO | C65: 0 | D65: 158.4 | E65: =C65*D65 -> 0
B66: EXTRA AL 100% | C66: 0 | D66: =+D64*2 -> 316.8 | E66: =C66*D66 -> 0
B67: EXTRA | C67: 0 | D67: =+D64*1.5 -> 237.6 | E67: =C67*D67 -> 0
B68: NO REMUNERATIVO | C68: 8000 | E68: 8000
B69: TOTAL SUELDO | E69: =SUM(E64:E68) -> 38729.6
B70: ADELANTO | E70: 0
B71: TOTAL A COBRAR | E71: =+E69-E70 -> 38729.6
B74: SILVINA
B75: DETALLE | C75: HS TRABAJADAS | D75: VALOR / HORA | E75: IMPORTE
B76: SUELDO | E76: 30000
B77: EXTRA | C77: 9 | D77: =300*1.5 -> 450 | E77: =C77*D77 -> 4050
B78: TOTAL A COBRAR | E78: =+E76+E77 -> 34050
B81: LUCA
B82: DETALLE | C82: HS TRABAJADAS | D82: VALOR / HORA | E82: IMPORTE
B83: SUELDO | C83: 168 | D83: 165 | E83: =C83*D83 -> 27720 | F83: ARRANCA EL LUNES 6
B84: FERIADO | C84: 0 | E84: =C84*D84 -> 0 | F84: =194-26 -> 168
B85: EXTRA | C85: 0 | D85: =+D83*1.5 -> 247.5 | E85: =C85*D85 -> 0
B86: EXTRA AL 100% | C86: 0 | D86: =+D84*2 -> 0 | E86: =+C86*D86 -> 0
B87: NO REMUNERATIVO | D87: 8000 | E87: 8000
B88: TOTAL SUELDO | E88: =SUM(E83:E87) -> 35720
B89: ADELANTO | E89: 8000
B90: TOTAL A COBRAR | E90: =+E88-E89 -> 27720

Sheet OCTUBRE
B1: PILU | H1: EMPLEADO | I1: HS TRABAJADAS | J1: FERIADOS | K1: VACACIONES | L1: HS EXTRAS | M1: NO REMUN. | N1: TOTALES | O1: ADELANTO | P1: DEPOSITO | Q1: EFVO
B2: DETALLE | C2: HS TRABAJADAS | D2: VALOR / HORA | E2: IMPORTE | H2: PILU | I2: =+E3 -> 32080.32 | J2: =+E6 -> 4872.96 | L2: =+E7+E8+E5+E4 -> 3609.12 | M2: =+E9 -> 8000 | N2: =SUM(I2:M2) -> 48562.4 | O2: =+E11 -> 0 | P2: =+E12 -> 29425.38 | Q2: =+N2-O2-P2 -> 19137.02
B3: SUELDO | C3: 158 | D3: 203.04 | E3: =C3*D3 -> 32080.32 | H3: FACU | I3: =+E19+E22 -> 32592 | J3: =+E21 -> 5587.2 | K3: =+E20 -> 13036.8 | L3: =+E23+E24 -> 1629.6 | M3: =+E25 -> 13000 | N3: =SUM(I3:M3) -> 65845.6 | O3: =+E27 -> 5000 | P3: 0 | Q3: =+N3-O3-P3 -> 60845.6
B4: PREMIO | D4: 3000 | E4: 3000 | H4: CHACO | I4: =+E32 -> 29577.6 | J4: =+E34 -> 3744 | L4: =+E35+E36+E33 -> 421.2 | M4: =+E37 -> 8000 | N4: =SUM(I4:M4) -> 41742.8 | O4: =+E39 -> 10000 | P4: 0 | Q4: =+N4-O4-P4 -> 31742.8
B5: EXTRA POR VIAJE | C5: 0 | D5: 0 | H5: JUANI | I5: =+E44 -> 36782.4 | J5: =+E45 -> 5587.2 | L5: =+E48+E47+E46 -> 7550.2 | M5: =+E49 -> 13500 | N5: =SUM(I5:M5) -> 63419.8 | O5: 0 | P5: =+E52 -> 30064.45 | Q5: =+N5-O5-P5 -> 33355.35
B6: FERIADO | C6: 24 | D6: 203.04 | E6: =C6*D6 -> 4872.96 | H6: JONA | I6: =+E57 -> 34128 | J6: =+E59 -> 5184 | K6: =+E58 -> 3456 | L6: =+E60+E61 -> 2160 | M6: =+E62 -> 13000 | N6: =SUM(I6:M6) -> 57928 | O6: =+E65 -> 6000 | P6: =+E64 -> 11023.23 | Q6: =+N6-O6-P6 -> 40904.77
B7: EXTRA | C7: 2 | D7: =+D3*1.5 -> 304.56 | E7: =C7*D7 -> 609.12 | H7: MATI | I7: =+E70 -> 25027.2 | J7: =+E71 -> 3801.6 | L7: =+E72+E73 -> 0 | M7: =+E74 -> 8000 | N7: =SUM(I7:M7) -> 36828.8 | O7: =+E76 -> 0 | P7: 0 | Q7: =+N7-O7-P7 -> 36828.8
B8: EXTRA AL 100% | C8: 0 | D8: =+D6*2 -> 406.08 | E8: =+C8*D8 -> 0 | H8: LUCA | I8: =+E90 -> 26070 | J8: =+E91 -> 3960 | L8: =+E92 -> 0 | M8: =+E94 -> 8000 | N8: =SUM(I8:M8) -> 38030 | O8: =+E96 -> 5000 | P8: 0 | Q8: =+N8-O8 -> 33030
B9: NO REMUNERATIVO | C9: 8000 | E9: =+C9 -> 8000 | H9: SILVI | I9: =+E82 -> 30000 | L9: =+E83+E84 -> 3375 | M9: 0 | N9: =SUM(I9:M9) -> 33375 | O9: 0 | P9: 0 | Q9: =+N9-O9-P9 -> 33375
B10: TOTAL SUELDO | E10: =SUM(E3:E9) -> 48562.4 | H10: TOTALES JULIO | O10: =SUM(O2:O9) -> 26000 | P10: =SUM(P2:P9) -> 70513.06 | Q10: =SUM(Q2:Q9) -> 289219.34
B11: ADELANTO | E11: 0 | O11: =+P10+Q10+O10 -> 385732.4
B12: DEPOSITO | E12: 29425.38
B13: TOTAL A COBRAR | E13: =+E10-E12 -> 19137.02 | N13: HORA | O13: HORA X | P13: NO REM.
M14: JUANI | N14: =194*1.2 -> 232.8 | O14: =+N14*1.5 -> 349.2 | P14: 13500
H15: DIAS | I15: HS | J15: SEPT | M15: JONA | N15: =180*1.2 -> 216 | O15: =+N15*1.5 -> 324 | P15: 13000
G16: LABORAL | H16: 14 | I16: 9 | J16: =+H16*I16 -> 126 | M16: FACU | N16: =180*1.2 -> 216 | O16: =+N16*1.5 -> 324 | P16: 13000
B17: FACU | G17: FERIADO | H17: 3 | I17: 8 | J17: =+H17*I17 -> 24 | M17: PILU | N17: =169.2*1.2 -> 203.04 | O17: =+N17*1.5 -> 304.56 | P17: 8000
B18: DETALLE | C18: HS TRABAJADAS | D18: VALOR / HORA | E18: IMPORTE | G18: VIERNES | H18: 4 | I18: 8 | J18: =+H18*I18 -> 32 | M18: CHACO | N18: =156*1.2 -> 187.2 | O18: =+N18*1.5 -> 280.8 | P18: 8000
B19: SUELDO | C19: 158 | D19: 232.8 | E19: =C19*D19 -> 36782.4 | H19: hs mes | J19: =SUM(J16:J18) -> 182 | M19: LUCA | N19: 165 | O19: =+N19*1.5 -> 247.5 | P19: 8000
B20: VACACIONES 2020 (7 D) | C20: 56 | D20: =+D19 -> 232.8 | E20: =C20*D20 -> 13036.8 | F20: se toma 07/10 y 12/10 | M20: MATI | N20: =132*1.2 -> 158.4 | O20: =+N20*1.5 -> 237.6 | P20: 8000
B21: FERIADO | C21: 24 | D21: 232.8 | E21: =C21*D21 -> 5587.2 | F21: ver vacaciones
B22: LICENCIA X VIAJE | C22: -18 | D22: 232.8 | E22: =C22*D22 -> -4190.4 | F22: SE DEBIAN 5 DIAS
B23: EXTRA AL 100% | C23: 3.5 | D23: =+D19*2 -> 465.6 | E23: =C23*D23 -> 1629.6
B24: EXTRA | C24: 0 | D24: =+D19*1.5 -> 349.2 | E24: =C24*D24 -> 0
B25: NO REMUNERATIVO | C25: 13000 | E25: =+C25 -> 13000
B26: TOTAL SUELDO | E26: =SUM(E19:E25) -> 65845.6
B27: ADELANTO | E27: 5000
B28: TOTAL A COBRAR | E28: =+E26-E27 -> 60845.6
B30: CHACO
B31: DETALLE | C31: HS TRABAJADAS | D31: VALOR / HORA | E31: IMPORTE
B32: SUELDO | C32: 158 | D32: 187.2 | E32: =C32*D32 -> 29577.6
B33: EXTRA POR VIAJE | C33: 0 | E33: 0
B34: FERIADO | C34: 24 | D34: 156 | E34: =C34*D34 -> 3744
B35: EXTRA AL 100% | C35: 0 | D35: =+D32*2 -> 374.4 | E35: =C35*D35 -> 0
B36: EXTRA | C36: 1.5 | D36: =+D32*1.5 -> 280.8 | E36: =C36*D36 -> 421.2
B37: NO REMUNERATIVO | C37: 8000 | E37: =+C37 -> 8000
B38: TOTAL SUELDO | E38: =SUM(E32:E37) -> 41742.8
B39: ADELANTO | E39: 10000
B40: TOTAL A COBRAR | E40: =+E38-E39 -> 31742.8
B42: JUANI
B43: DETALLE | C43: HS TRABAJADAS | D43: VALOR / HORA | E43: IMPORTE
B44: SUELDO | C44: 158 | D44: 232.8 | E44: =C44*D44 -> 36782.4
B45: FERIADO | C45: 24 | D45: 232.8 | E45: =C45*D45 -> 5587.2
B46: PREMIO | E46: 4000
B47: EXTRA AL 100% | C47: 3.5 | D47: =+D44*2 -> 465.6 | E47: =C47*D47 -> 1629.6
B48: EXTRA | C48: 5.5 | D48: =+D44*1.5 -> 349.2 | E48: =C48*D48 -> 1920.6
B49: NO REMUNERATIVO | C49: 13500 | E49: =+C49 -> 13500
B50: TOTAL SUELDO | E50: =SUM(E44:E49) -> 63419.8
B51: ADELANTO | E51: 0
B52: DEPOSITO | E52: 30064.45
B53: TOTAL A COBRAR | E53: =+E50-E51-E52 -> 33355.35
B55: JONA
B56: DETALLE | C56: HS TRABAJADAS | D56: VALOR / HORA | E56: IMPORTE
B57: SUELDO | C57: 158 | D57: 216 | E57: =+C57*D57 -> 34128
B58: VACACIONES 2020 (2 D) | C58: 16 | D58: =+D57 -> 216 | E58: =+C58*D58 -> 3456
B59: FERIADO | C59: 24 | D59: 216 | E59: =C59*D59 -> 5184
B60: EXTRA AL 100% | C60: 3.5 | D60: =+D57*2 -> 432 | E60: =C60*D60 -> 1512
B61: EXTRA | C61: 2 | D61: =+D57*1.5 -> 324 | E61: =C61*D61 -> 648 | F61: quedan 2 dias de vacac.
B62: NO REMUNERATIVO | C62: 13000 | E62: =+C62 -> 13000
B63: TOTAL SUELDO | E63: =SUM(E57:E62) -> 57928
B64: DEPOSITO | E64: 11023.23
B65: ADELANTO | E65: 6000
B66: TOTAL A COBRAR | E66: =+E63-E64-E65 -> 40904.77
B68: MATI
B69: DETALLE | C69: HS TRABAJADAS | D69: VALOR / HORA | E69: IMPORTE
B70: SUELDO | C70: 158 | D70: 158.4 | E70: =C70*D70 -> 25027.2
B71: FERIADO | C71: 24 | D71: 158.4 | E71: =C71*D71 -> 3801.6
B72: EXTRA AL 100% | C72: 0 | D72: =+D70*2 -> 316.8 | E72: =C72*D72 -> 0
B73: EXTRA | C73: 0 | D73: =+D70*1.5 -> 237.6 | E73: =C73*D73 -> 0
B74: NO REMUNERATIVO | C74: 8000 | E74: 8000
B75: TOTAL SUELDO | E75: =SUM(E70:E74) -> 36828.8
B76: ADELANTO | E76: 0
B77: TOTAL A COBRAR | E77: =+E75-E76 -> 36828.8
B80: SILVINA
B81: DETALLE | C81: HS TRABAJADAS | D81: VALOR / HORA | E81: IMPORTE
B82: SUELDO | E82: 30000
B83: EXTRA | C83: 12.5 | D83: =300*1.5 -> 450 | E83: =C83*D83 -> 5625
B84: DESCUENTO HS | C84: -5 | D84: 450 | E84: =C84*D84 -> -2250
B85: TOTAL A COBRAR | E85: =+E82+E83+E84 -> 33375
B88: LUCA
B89: DETALLE | C89: HS TRABAJADAS | D89: VALOR / HORA | E89: IMPORTE
B90: SUELDO | C90: 158 | D90: 165 | E90: =C90*D90 -> 26070
B91: FERIADO | C91: 24 | D91: 165 | E91: =C91*D91 -> 3960
B92: EXTRA | C92: 0 | D92: =+D90*1.5 -> 247.5 | E92: =C92*D92 -> 0
B93: EXTRA AL 100% | C93: 0 | D93: =+D91*2 -> 330 | E93: =+C93*D93 -> 0
B94: NO REMUNERATIVO | D94: 8000 | E94: 8000
B95: TOTAL SUELDO | E95: =SUM(E90:E94) -> 38030
B96: ADELANTO | E96: 5000
B97: TOTAL A COBRAR | E97: =+E95-E96 -> 33030

Sheet NOVIEMBRE
H1: NOVIEMBRE
B2: PILU | H2: EMPLEADO | I2: HS TRABAJADAS | J2: FERIADOS | K2: LICENCIA | L2: PRESENTISMO | M2: VARIOS | N2: HS EXTRAS | O2: NO REMUN. | P2: TOTALES | Q2: ADELANTO | R2: DEPOSITO | S2: EFVO
B3: DETALLE | C3: HS TRABAJADAS | D3: VALOR / HORA | E3: IMPORTE | H3: PILU | I3: =+E4 -> 37562.4 | J3: =+E7 -> 4872.96 | K3: =+E5 -> 0 | L3: =+E6 -> 5000 | M3: 0 | N3: =+E8+E9 -> 1218.24 | O3: =+E10 -> 11000 | P3: =SUM(I3:O3) -> 59653.6 | Q3: =+E12 -> 0 | R3: =+E13 -> 29425.38 | S3: =+P3-Q3-R3 -> 30228.22
B4: SUELDO | C4: 185 | D4: 203.04 | E4: =C4*D4 -> 37562.4 | H4: FACU | I4: =+E18 -> 43068 | J4: =+E20 -> 2793.6 | K4: =+E19 -> 0 | L4: =+E21 -> 5000 | M4: -990 | N4: =+E22+E23 -> 9195.6 | O4: =+E24 -> 16500 | P4: =SUM(I4:O4) -> 75567.2 | Q4: =+E27 -> 10000 | R4: 0 | S4: =+P4-Q4-R4 -> 65567.2
B5: FALTA/RETIRO | H5: CHACO | I5: =+E32 -> 33134.4 | J5: =+E36 -> 2246.4 | K5: =+E33 -> 1497.6 | L5: =+E35 -> 5000 | M5: 0 | N5: =+E37+E38 -> 5616 | O5: =+E39 -> 11000 | P5: =SUM(I5:O5) -> 58494.4 | Q5: =+E41 -> 10000 | R5: 0 | S5: =+P5-Q5-R5 -> 48494.4
B6: Presentismo | C6: 5000 | D6: 0 | E6: =+C6 -> 5000 | H6: JUANI | I6: =+E46 -> 38877.6 | J6: =+E48 -> 2793.6 | K6: =+E47 -> 13036.8 | L6: =+E49 -> 5000 | M6: 0 | N6: =+E52+E51+E50 -> 8089.8 | O6: =+E53 -> 16500 | P6: =SUM(I6:O6) -> 84297.8 | Q6: 0 | R6: =+E56 -> 30064.45 | S6: =+P6-Q6-R6 -> 54233.35
B7: FERIADO | C7: 12 | D7: =+D4*2 -> 406.08 | E7: =C7*D7 -> 4872.96 | H7: JONA | I7: =+E61 -> 36504 | J7: =+E65 -> 2592 | K7: =+E63+E64 -> 1728 | L7: =+E62 -> 0 | M7: 0 | N7: =+E66+E67 -> 0 | O7: =+E68 -> 16000 | P7: =SUM(I7:O7) -> 56824 | Q7: =+E71 -> 10000 | R7: =+E70 -> 24028.31 | S7: =+P7-Q7-R7 -> 22795.69
B8: EXTRA x 50% | C8: 4 | D8: =+D4*1.5 -> 304.56 | E8: =C8*D8 -> 1218.24 | H8: MATI | I8: =+E76 -> 29304 | J8: =+E77 -> 1900.8 | K8: =+E79 -> -4276.8 | L8: =+E78 -> 0 | M8: 0 | N8: =+E80+E81 -> 5385.6 | O8: =+E82 -> 11000 | P8: =SUM(I8:O8) -> 43313.6 | Q8: =+E84 -> 0 | R8: 0 | S8: =+P8-Q8-R8 -> 43313.6
B9: EXTRA AL 100% | C9: 0 | D9: =+D7*2 -> 812.16 | E9: =+C9*D9 -> 0 | H9: LUCA | I9: =+E96 -> 32214 | J9: =+E97 -> 2184 | K9: =+E99 -> 1456 | L9: =+E98 -> 5000 | M9: 0 | N9: =+E100+E101 -> 6870.5 | O9: =+E102 -> 11000 | P9: =SUM(I9:O9) -> 58724.5 | Q9: =+E104 -> 8000 | R9: 0 | S9: =+P9-Q9 -> 50724.5
B10: NO REMUNERATIVO | C10: 11000 | E10: =+C10 -> 11000 | H10: SILVI | I10: =+E89 -> 30000 | M10: 0 | N10: =+E90+E91 -> 11500 | O10: 0 | P10: =SUM(I10:O10) -> 41500 | Q10: 0 | R10: 0 | S10: =+P10-Q10-R10 -> 41500
B11: TOTAL SUELDO | E11: =SUM(E4:E10) -> 59653.6 | H11: ALEJO | I11: =+E109 -> 16005 | J11: =+E110 -> 1980 | K11: =+E111 -> -1650 | L11: 0 | N11: =+E112+E113 -> 247.5 | O11: =+E114 -> 8000 | P11: =SUM(I11:O11) -> 24582.5 | Q11: 0 | R11: 0 | S11: =+P11-Q11-R11 -> 24582.5
B12: ADELANTO | E12: 0 | H12: TOTALES NOVIEMBRE | Q12: =SUM(Q3:Q10) -> 38000 | R12: =SUM(R3:R10) -> 83518.14 | S12: =SUM(S3:S10) -> 356856.96
B13: DEPOSITO 03/11/21 | E13: 29425.38 | Q13: =+R12+S12+Q12 -> 478375.1
B14: TOTAL A COBRAR | E14: =+E11-E13 -> 30228.22 | L14: =+I4+L4+M4+N4+O4 -> 72773.6
B16: FACU | L16: =+O4+N4+M4+L4+K4+J4+I4 -> 75567.2 | Q16: HORA | R16: HORA X | S16: NO REM.
B17: DETALLE | C17: HS TRABAJADAS | D17: VALOR / HORA | E17: IMPORTE | P17: JUANI | Q17: =194*1.2 -> 232.8 | R17: =+Q17*1.5 -> 349.2 | S17: 13500
B18: SUELDO | C18: 185 | D18: 232.8 | E18: =C18*D18 -> 43068 | I18: DIAS | J18: HS | K18: NOV | P18: JONA | Q18: =180*1.2 -> 216 | R18: =+Q18*1.5 -> 324 | S18: 13000
B19: FALTA/RETIRO | E19: 0 | H19: LABORAL | I19: 17 | J19: 9 | K19: =+I19*J19 -> 153 | P19: FACU | Q19: =180*1.2 -> 216 | R19: =+Q19*1.5 -> 324 | S19: 13500
B20: FERIADO | C20: 12 | D20: 232.8 | E20: =C20*D20 -> 2793.6 | F20: PAGO FERIADO $1862,40 | H20: FERIADO | I20: 1.5 | J20: 8 | K20: =+I20*J20 -> 12 | P20: PILU | Q20: =169.2*1.2 -> 203.04 | R20: =+Q20*1.5 -> 304.56 | S20: 11000
B21: Presentismo | C21: 5000 | E21: 5000 | F21: =4*349 -> 1396 | H21: VIERNES | I21: 4 | J21: 8 | K21: =+I21*J21 -> 32 | P21: CHACO | Q21: =156*1.2 -> 187.2 | R21: =+Q21*1.5 -> 280.8 | S21: 11000
B22: EXTRA AL 100% feriado | C22: 13 | D22: =+D18*2 -> 465.6 | E22: =C22*D22 -> 6052.8 | I22: hs mes | K22: =SUM(K19:K21) -> 197 | P22: LUCA | Q22: 165 | R22: =+Q22*1.5 -> 247.5 | S22: 8000
B23: EXTRA al 50% | C23: 9 | D23: =+D18*1.5 -> 349.2 | E23: =C23*D23 -> 3142.8 | P23: ALEJO | Q23: =132*1.2 -> 158.4 | R23: =+Q23*1.5 -> 237.6 | S23: 8000
B24: NO REMUNERATIVO | C24: 16500 | E24: =+C24 -> 16500 | R24: =+Q24*1.5 -> 0
B25: TOTAL SUELDO | E25: =SUM(E18:E24) -> 76557.2
B26: SEGURO CLIO | E26: 990
B27: ADELANTO | E27: 10000
B28: TOTAL A COBRAR | E28: =+E25-E26-E27 -> 65567.2
B30: CHACO
B31: DETALLE | C31: HS TRABAJADAS | D31: VALOR / HORA | E31: IMPORTE
B32: SUELDO | C32: 177 | D32: 187.2 | E32: =C32*D32 -> 33134.4 | F32: =185-8 -> 177
B33: LICENCIA X ENFERMEDAD | C33: 8 | D33: 187.2 | E33: =+C33*D33 -> 1497.6
B34: FALTA/RETIRO | D34: -187.2 | E34: =+C34*D34 -> 0
B35: Presentismo | C35: 5000 | E35: 5000
B36: FERIADO no trabajado | C36: 12 | D36: =+D32 -> 187.2 | E36: =+C36*D36 -> 2246.4
B37: Feriado EXTRA AL 100% | C37: 9 | D37: =+D32*2 -> 374.4 | E37: =C37*D37 -> 3369.6
B38: EXTRA al 50% | C38: 8 | D38: =+D32*1.5 -> 280.8 | E38: =C38*D38 -> 2246.4
B39: NO REMUNERATIVO | C39: 11000 | E39: =+C39 -> 11000
B40: TOTAL SUELDO | E40: =SUM(E32:E39) -> 58494.4
B41: ADELANTO | E41: 10000
B42: TOTAL A COBRAR | E42: =+E40-E41 -> 48494.4
B44: JUANI | F44: ok
B45: DETALLE | C45: HS TRABAJADAS | D45: VALOR / HORA | E45: IMPORTE
B46: SUELDO | C46: 167 | D46: 232.8 | E46: =C46*D46 -> 38877.6 | F46: =185-18 -> 167
B47: VACACIONES 29/11 al 4/12 | C47: 56 | D47: =+D46 -> 232.8 | E47: =C47*D47 -> 13036.8 | F47: =7*8 -> 56
B48: FERIADO | C48: 12 | D48: 232.8 | E48: =C48*D48 -> 2793.6
B49: Presentismo | C49: 5000 | E49: 5000 | F49: 21 DIAS
B50: FALTA/RETIRO | C50: 0 | E50: 0 | F50: VACACIONES DEL 29/11 AL 4/12
B51: EXTRA AL 100% feriado | C51: 14 | D51: =+D46*2 -> 465.6 | E51: =C51*D51 -> 6518.4
B52: EXTRA al 50% | C52: 4.5 | D52: =+D46*1.5 -> 349.2 | E52: =C52*D52 -> 1571.4
B53: NO REMUNERATIVO | C53: 16500 | E53: =+C53 -> 16500
B54: TOTAL SUELDO | E54: =SUM(E46:E53) -> 84297.8
B55: ADELANTO | E55: 0
B56: DEPOSITO | E56: 30064.45
B57: TOTAL A COBRAR | E57: =+E54-E55-E56 -> 54233.35
B59: JONA
B60: DETALLE | C60: HS TRABAJADAS | D60: VALOR / HORA | E60: IMPORTE | F60: OK
B61: SUELDO | C61: 169 | D61: 216 | E61: =+C61*D61 -> 36504
B62: Presentismo | C62: 0 | E62: 0
B63: LICENCIA X ENFERMEDAD | C63: 8 | D63: 216 | E63: =+D63*C63 -> 1728
B64: FALTA/RETIRO | C64: 8 | D64: =+D61 -> 216
B65: FERIADO | C65: 12 | D65: 216 | E65: =C65*D65 -> 2592
B66: EXTRA AL 100% | D66: =+D61*2 -> 432 | E66: =C66*D66 -> 0
B67: EXTRA al 50% | D67: =+D61*1.5 -> 324 | E67: =C67*D67 -> 0
B68: NO REMUNERATIVO | C68: 16000 | E68: =+C68 -> 16000
B69: TOTAL SUELDO | E69: =SUM(E61:E68) -> 56824
B70: DEPOSITO | E70: 24028.31
B71: ADELANTO | E71: 10000
B72: TOTAL A COBRAR | E72: =+E69-E70-E71 -> 22795.69
B74: MATI
B75: DETALLE | C75: HS TRABAJADAS | D75: VALOR / HORA | E75: IMPORTE
B76: SUELDO | C76: 185 | D76: 158.4 | E76: =C76*D76 -> 29304
B77: FERIADO | C77: 12 | D77: 158.4 | E77: =C77*D77 -> 1900.8
B78: Presentismo | C78: 0 | E78: =C78*D78 -> 0
B79: FALTA/RETIRO | C79: -27 | D79: =+D77 -> 158.4 | E79: =C79*D79 -> -4276.8
B80: EXTRA AL 100% feriado | C80: 14 | D80: =+D76*2 -> 316.8 | E80: =C80*D80 -> 4435.2
B81: EXTRA AL 50% | C81: 4 | D81: =+D76*1.5 -> 237.6 | E81: =C81*D81 -> 950.4
B82: NO REMUNERATIVO | C82: 11000 | E82: 11000
B83: TOTAL SUELDO | E83: =SUM(E76:E82) -> 43313.6
B84: ADELANTO | E84: 0
B85: TOTAL A COBRAR | E85: =+E83-E84 -> 43313.6
B87: SILVINA
B88: DETALLE | C88: HS TRABAJADAS | D88: VALOR / HORA | E88: IMPORTE
B89: SUELDO | C89: 105 | D89: =+E89/C89 -> 285.71429 | E89: 30000
B90: Presentismo 1/2 dia | C90: 2500 | D90: 0 | E90: 2500
B91: hs TARDE (Mar/Jue 3,5) | C91: 31.5 | D91: =+D89 -> 285.71429 | E91: =C91*D91 -> 9000
B92: TOTAL A COBRAR | E92: =+E89+E90+E91 -> 41500
B94: LUCA | G94: LUCA
B95: DETALLE | C95: HS TRABAJADAS | D95: VALOR / HORA | E95: IMPORTE | G95: DETALLE | H95: HS TRABAJADAS | I95: VALOR / HORA | J95: IMPORTE
B96: SUELDO | C96: 177 | D96: 182 | E96: =C96*D96 -> 32214 | G96: SUELDO | H96: 185 | I96: 182 | J96: =H96*I96 -> 33670
B97: FERIADO | C97: 12 | D97: 182 | E97: =C97*D97 -> 2184 | G97: FERIADO | H97: 0 | I97: 165 | J97: =H97*I97 -> 0
B98: Presentismo | C98: 5000 | E98: 5000 | G98: Presentismo | H98: 5000 | J98: 5000
B99: FALTA/RETIRO | C99: 8 | D99: 182 | E99: =C99*D99 -> 1456 | G99: FALTA/RETIRO | H99: -9 | I99: 165 | J99: =H99*I99 -> -1485
B100: EXTRA AL 50% | C100: 6.5 | D100: =+D96*1.5 -> 273 | E100: =C100*D100 -> 1774.5 | G100: EXTRA AL 50% | H100: 6.5 | I100: =+I96*1.5 -> 273 | J100: =H100*I100 -> 1774.5
B101: EXTRA AL 100% feriado | C101: 14 | D101: =+D96*2 -> 364 | E101: =+C101*D101 -> 5096 | G101: EXTRA AL 100% feriado | H101: 14 | I101: =+I96*2 -> 364 | J101: =+H101*I101 -> 5096
B102: NO REMUNERATIVO | D102: 11000 | E102: 11000 | G102: NO REMUNERATIVO | I102: 11000 | J102: 11000
B103: TOTAL SUELDO | E103: =SUM(E96:E102) -> 58724.5 | G103: TOTAL SUELDO | J103: =SUM(J96:J102) -> 55055.5
B104: ADELANTO | E104: 8000 | G104: ADELANTO | J104: 8000
B105: TOTAL A COBRAR | E105: =+E103-E104 -> 50724.5 | F105: =+J105-E105 -> -3669 | G105: TOTAL A COBRAR | J105: =+J103-J104 -> 47055.5
B107: ALEJO (Inc. 15/11) | F107: empieza 15/11
B108: DETALLE | C108: HS TRABAJADAS | D108: VALOR / HORA | E108: IMPORTE
...

Sheet DICIEMBRE21
B2: PILU | H2: DICIEMBRE
B3: DETALLE | C3: HS TRABAJADAS | D3: VALOR / HORA | E3: IMPORTE | H3: EMPLEADO | I3: HS TRABAJADAS | J3: FERIADOS | K3: LICENCIA | L3: PRESENTISMO | M3: aguinaldo | N3: HS EXTRAS | O3: NO REMUN. | P3: vs | Q3: TOTALES | R3: ADELANTO | S3: DEPOSITO | T3: EFVO
B4: SUELDO | C4: 181 | D4: 203.04 | E4: =C4*D4 -> 36750.24 | H4: PILU | I4: =+E4 -> 36750.24 | J4: =+E5 -> 2436.48 | K4: =+E6 -> 22740.48 | L4: =+E9 -> 5000 | M4: =+E7 -> 29825 | N4: =+E12+E11 -> 2284.2 | O4: =+E13 -> 11000 | Q4: =SUM(I4:O4) -> 110036.4 | R4: =+E15 -> 29825 | S4: =+E16 -> 30000 | T4: =+Q4-R4-S4 -> 50211.4
B5: FERIADO | C5: 12 | D5: =+D4 -> 203.04 | E5: =+C5*D5 -> 2436.48 | H5: =+++++++++++++F3 -> 0 | I5: =+E21 -> 42136.8 | J5: =+E22 -> 2793.6 | L5: =+E26 -> 5000 | M5: =+E24 -> 38250 | N5: =+E29+E28 -> 3317.4 | O5: =+E30 -> 16500 | P5: =+E33 -> 990 | Q5: =SUM(I5:P5) -> 108987.8 | R5: =+E36 -> 38250 | T5: =+Q5-R5 -> 70737.8
B6: VACACIONES | C6: =14*8 -> 112 | D6: =+D5 -> 203.04 | E6: =+C6*D6 -> 22740.48 | H6: CHACO | I6: =+E41 -> 33883.2 | J6: =+E42 -> 2246.4 | K6: =+E43 -> 20966.4 | L6: =+E46 -> 5000 | M6: =+E44 -> 29250 | N6: =+E48+E49 -> 982.8 | O6: =+E50 -> 11000 | Q6: =SUM(I6:O6) -> 103328.8 | R6: =+E52 -> 29250 | S6: =+E53 -> 20966.4 | T6: =+Q6-R6-S6 -> 53112.4
B7: AGUINALDO (Base: Dic.) | E7: 29825 | H7: JUANI | I7: =+E58 -> 36084 | J7: =+E59 -> 2793.6 | K7: =+E60 -> 0 | L7: =+E63 -> 5000 | M7: =+E61 -> 40300 | N7: =+E66+E65 -> 2793.6 | O7: =+E67 -> 16500 | Q7: =SUM(I7:O7) -> 103471.2 | R7: =+E69 -> 40300 | S7: =+E70 -> 24313.15 | T7: =+Q7-R7-S7 -> 38858.05
B8: FALTA/RETIRO sin justif | D8: =-D4 -> -203.04 | E8: =+C8*D8 -> 0 | H8: JONA | I8: =+E75 -> 15120 | J8: =+E76 -> 2592 | K8: =+E81 -> 21384 | L8: =+E80 -> 0 | M8: =+E78 -> 24800 | N8: =+E83+E82 -> 0 | O8: =+E84 -> 16000 | Q8: =SUM(I8:O8) -> 79896 | R8: =+E87 -> 28400 | S8: =+E86 -> 24028.31 | T8: =+Q8-R8-S8 -> 27467.69
B9: Presentismo | C9: 5000 | E9: =+C9 -> 5000 | H9: LUCA | I9: =+E101 -> 32942 | J9: =+E102 -> 2184 | L9: =+E106 -> 5000 | M9: =+E104 -> 18300 | N9: =+E109+E108 -> 2184 | O9: =+E110 -> 11000 | Q9: =SUM(I9:O9) -> 71610 | R9: =+E112 -> 18300 | T9: =+Q9-R9 -> 53310
B10: LICENCIA ENFERMEDAD | E10: =C10*D10 -> 0 | H10: SILVI | I10: =+E92 -> 30000 | L10: =+E93 -> 3600 | M10: =+E96 -> 21000 | O10: 0 | P10: =+E94 -> 8590.9091 | Q10: =SUM(I10:P10) -> 63190.909 | R10: =+E96 -> 21000 | T10: =+Q10-R10-S10 -> 42190.909
B11: HORA EXTRA x 50% | C11: 7.5 | D11: =+D4*1.5 -> 304.56 | E11: =C11*D11 -> 2284.2 | H11: LUIS | I11: =+E140 -> 25575 | J11: =+E141 -> 1980 | L11: =+E145 -> 5000 | M11: =+E143 -> 4000 | N11: =+E109+E108 -> 2184 | O11: =+E149 -> 8000 | Q11: =SUM(I11:O11) -> 46739 | R11: =+E151 -> 4000 | T11: =+Q11-R11-S11 -> 42739
B12: HORA EXTRA AL 100% | D12: =+D10*2 -> 0 | E12: =+C12*D12 -> 0 | H12: ALEJO | I12: =+E119 -> 29865 | J12: =+E120 -> 1980 | K12: =+E123+E124 -> 0 | L12: =+E125 -> 0 | M12: =+E122 -> 6000 | N12: =+E128+E127 -> 866.25 | O12: =+E129 -> 8000 | Q12: =SUM(I12:O12) -> 46711.25 | R12: =+E131 -> 6000 | T12: =+Q12-R12-S12 -> 40711.25
B13: NO REMUNERATIVO | C13: 11000 | E13: =+C13 -> 11000 | H13: TOTALES | R13: =SUM(R4:R12) -> 215325 | S13: =SUM(S4:S12) -> 99307.86 | T13: =SUM(T4:T12) -> 419338.5
B14: TOTAL SUELDO | E14: =SUM(E4:E13) -> 110036.4 | R14: =+S13+T13+R13 -> 733971.36
B15: AGUINALDO PAGO | E15: 29825 | T15: =+T13-T4-T6-T11 -> 273275.7
B16: DEPOSITO | E16: 30000
B17: TOTAL A COBRAR | E17: =+E14-E15-E16 -> 50211.4 | R17: HORA | S17: HORA X | T17: NO REM.
Q18: JUANI | R18: =194*1.2 -> 232.8 | S18: =+R18*1.5 -> 349.2 | T18: 13500
B19: FACU | I19: DIAS | J19: HS | K19: DIC | Q19: JONA | R19: =180*1.2 -> 216 | S19: =+R19*1.5 -> 324 | T19: 13000
B20: DETALLE | C20: HS TRABAJADAS | D20: VALOR / HORA | E20: IMPORTE | H20: LABORAL | I20: 17 | J20: 9 | K20: =+I20*J20 -> 153 | Q20: FACU | R20: =180*1.2 -> 216 | S20: =+R20*1.5 -> 324 | T20: 13500
B21: SUELDO | C21: 181 | D21: 232.8 | E21: =C21*D21 -> 42136.8 | H21: FERIADO | I21: 1.5 | J21: 8 | K21: =+I21*J21 -> 12 | Q21: PILU | R21: =169.2*1.2 -> 203.04 | S21: =+R21*1.5 -> 304.56 | T21: 11000
B22: FERIADO | C22: 12 | D22: =+D21 -> 232.8 | E22: =+C22*D22 -> 2793.6 | H22: VIERNES | I22: 4 | J22: 8 | K22: =+I22*J22 -> 32 | Q22: CHACO | R22: =156*1.2 -> 187.2 | S22: =+R22*1.5 -> 280.8 | T22: 11000
B23: VACACIONES | I23: hs mes | K23: =SUM(K20:K22) -> 197 | Q23: LUCA | R23: 165 | S23: =+R23*1.5 -> 247.5 | T23: 8000
B24: AGUINALDO (Base: Dic) | E24: 38250 | Q24: ALEJO | R24: =132*1.2 -> 158.4 | S24: =+R24*1.5 -> 237.6 | T24: 8000
B25: FALTA/RETIRO sin justif | D25: =-D21 -> -232.8 | E25: =C25*D25 -> 0 | Q25: LUIS | R25: =+R24 -> 158.4 | S25: =+R25*1.5 -> 237.6 | T25: 8000
B26: Presentismo | C26: 5000 | E26: 5000 | I26: 17 | J26: 9 | K26: =+I26*J26 -> 153
B27: LICENCIA ENFERMEDAD | I27: 3 | J27: 8 | K27: =+I27*J27 -> 24
B28: EXTRA AL 100% feriado | D28: =+D21*2 -> 465.6 | E28: =C28*D28 -> 0 | I28: 1 | J28: 4 | K28: =+I28*J28 -> 4
B29: EXTRA al 50% | C29: 9.5 | D29: =+D21*1.5 -> 349.2 | E29: =C29*D29 -> 3317.4 | I29: 1.5 | J29: 8 | K29: =+I29*J29 -> 12
B30: NO REMUNERATIVO | C30: 16500 | E30: =+C30 -> 16500
B31: OOSS / MONOT. / SEGURO | E31: =+C31 -> 0
B32: TOTAL SUELDO | E32: =SUM(E21:E30) -> 107997.8
B33: SEGURO CLIO (DEVOLUCION NOV) | E33: 990
B34: OBRA SOCIAL
B35: MONOTRIBUTO
B36: AGUINALDO PAGO | E36: 38250
B37: TOTAL A COBRAR | E37: =+E32+E33-E34-E35-E36 -> 70737.8
B39: CHACO
B40: DETALLE | C40: HS TRABAJADAS | D40: VALOR / HORA | E40: IMPORTE
B41: SUELDO | C41: 181 | D41: 187.2 | E41: =C41*D41 -> 33883.2
B42: FERIADO | C42: 12 | D42: 187.2 | E42: =+C42*D42 -> 2246.4
B43: VACACIONES | C43: 112 | D43: =+D41 -> 187.2 | E43: =+C43*D43 -> 20966.4
B44: AGUINALDO (Base: Dic) | E44: 29250
B45: FALTA/RETIRO sin justif | D45: =-D41 -> -187.2 | E45: =+C45*D45 -> 0
B46: Presentismo | C46: 5000 | E46: 5000
B47: LICENCIA ENFERMEDAD | D47: =+D41 -> 187.2 | E47: =C47*D47 -> 0
B48: EXTRA AL 100% feriado | D48: =+D41*2 -> 374.4 | E48: =C48*D48 -> 0
B49: EXTRA al 50% | C49: 3.5 | D49: =+D41*1.5 -> 280.8 | E49: =C49*D49 -> 982.8
B50: NO REMUNERATIVO | C50: 11000 | E50: =+C50 -> 11000
B51: TOTAL SUELDO | E51: =SUM(E41:E50) -> 103328.8
B52: AGUINALDO PAGO | E52: 29250
B53: DEPOSITO | E53: 20966.4
B54: TOTAL A COBRAR | E54: =+E51-E52-E53 -> 53112.4
B56: JUANI
B57: DETALLE | C57: HS TRABAJADAS | D57: VALOR / HORA | E57: IMPORTE
B58: SUELDO vacac. Hta 04/12 | C58: =181-26 -> 155 | D58: 232.8 | E58: =C58*D58 -> 36084 | F58: 21 DIAS
B59: FERIADO | C59: 12 | D59: =+D58 -> 232.8 | E59: =C59*D59 -> 2793.6 | F59: VACACIONES DEL 29/11 AL 4/12
B60: VACACIONES | D60: 232.8 | E60: =C60*D60 -> 0
B61: AGUINALDO (Base: Dic) | E61: 40300
B62: FALTA/RETIRO sin justif | C62: 0 | E62: 0
B63: Presentismo | C63: 5000 | E63: 5000
B64: LICENCIA ENFERMEDAD | E64: =+C64*D63 -> 0
B65: EXTRA AL 100% feriado | D65: =+D58*2 -> 465.6 | E65: =C65*D65 -> 0
B66: EXTRA al 50% | C66: 8 | D66: =+D58*1.5 -> 349.2 | E66: =C66*D66 -> 2793.6
B67: NO REMUNERATIVO | C67: 16500 | E67: =+C67 -> 16500
B68: TOTAL SUELDO | E68: =SUM(E58:E67) -> 103471.2
B69: AGUINALDO PAGO | E69: 40300
B70: DEPOSITO | E70: 24313.15
B71: TOTAL A COBRAR | E71: =+E68-E69-E70 -> 38858.05
B73: JONA
B74: DETALLE | C74: HS TRABAJADAS | D74: VALOR / HORA | E74: IMPORTE
B75: SUELDO | C75: 70 | D75: 216 | E75: =+C75*D75 -> 15120
B76: FERIADO | C76: 12 | D76: =+D75 -> 216 | E76: =+C76*D76 -> 2592
B77: VACACIONES
B78: AGUINALDO (Base Dic) | E78: 24800
B79: FALTA/RETIRO sin justif | D79: =-D76 -> -216
B80: Presentismo
B81: LICENCIA ENFERMEDAD | C81: 99 | D81: =+D75 -> 216 | E81: =+C81*D81 -> 21384
B82: EXTRA AL 100% feriado | D82: =+D75*2 -> 432 | E82: =+C82*D82 -> 0
B83: EXTRA al 50% | D83: =+D75*1.5 -> 324 | E83: =+D83*C83 -> 0
B84: NO REMUNERATIVO | C84: 16000 | E84: =+C84 -> 16000
B85: TOTAL SUELDO | E85: =SUM(E75:E84) -> 79896
B86: DEPOSITO | E86: 24028.31
B87: AGUINALDO PAGO | E87: 28400
B88: TOTAL A COBRAR | E88: =+E85-E86-E87 -> 27467.69
B90: SILVINA
B91: DETALLE | C91: HS TRABAJADAS | D91: VALOR / HORA | E91: IMPORTE
B92: SUELDO | C92: 110 | D92: =+E92/C92 -> 272.72727 | E92: 30000
B93: Presentismo % | C93: 3600 | D93: 0 | E93: 3600
B94: hs TARDE (Mar/Jue 3,5) | C94: 31.5 | D94: =+D92 -> 272.72727 | E94: =C94*D94 -> 8590.9091
B95: OOSS Y MONOTRIBUTO
B96: Aguinaldo pagado | E96: 21000
B97: TOTAL A COBRAR | E97: =+E92+E93+E94 -> 42190.909
B99: LUCA
B100: DETALLE | C100: HS TRABAJADAS | D100: VALOR / HORA | E100: IMPORTE
B101: SUELDO | C101: 181 | D101: 182 | E101: =C101*D101 -> 32942
B102: FERIADO | C102: 12 | D102: =+D101 -> 182 | E102: =C102*D102 -> 2184
B103: VACACIONES
B104: AGUINALDO (Base: Dic/4 meses) | E104: 18300
B105: FALTA/RETIRO sin justif
B106: Presentismo | C106: 5000 | E106: =+C106 -> 5000
...

Sheet ENE22
B2: PILU | H2: ENERO
B3: DETALLE | C3: HS TRABAJADAS | D3: VALOR / HORA | E3: IMPORTE | H3: EMPLEADO | I3: HS TRABAJADAS | J3: FERIADOS | K3: LICENCIA | L3: PRESENTISMO | M3: aguinaldo | N3: HS EXTRAS | O3: NO REMUN. | P3: vs | Q3: TOTALES | R3: ADELANTO | S3: DEPOSITO | T3: EFVO
B4: SUELDO | C4: 97 | D4: 203.04 | E4: =C4*D4 -> 19694.88 | H4: PILU | I4: =+E4 -> 19694.88 | J4: =+E5 -> 812.16 | K4: =+E6 -> 0 | L4: =+E9 -> 5000 | M4: =+E7 -> 0 | N4: =+E12+E11 -> 0 | O4: =+E13 -> 11000 | Q4: =SUM(I4:O4) -> 36507.04 | R4: =+E16 -> 0 | S4: =+E17 -> 18139.83 | T4: =+Q4-R4-S4 -> 18367.21
B5: FERIADO | C5: =+K22 -> 4 | D5: =+D4 -> 203.04 | E5: =+C5*D5 -> 812.16 | H5: FACU | I5: =+E22 -> 10243.2 | J5: =+E23 -> 931.2 | K5: =+E24+E28 -> 35385.6 | L5: =+E27 -> 2500 | M5: =+E25 -> 0 | N5: =+E30+E29 -> 0 | O5: =+E31 -> 16500 | P5: =+E34 -> 990 | Q5: =SUM(I5:O5) -> 65560 | R5: =+E35 -> 0 | T5: =+Q5-P5 -> 64570
B6: VACACIONES(pagado dic) | C6: 112 | D6: =+D5 -> 203.04 | H6: CHACO | I6: =+E42 -> 18158.4 | J6: =+E43 -> 748.8 | K6: =+E48 -> 0 | L6: =+E47 -> 5000 | M6: =+E45 -> 0 | N6: =+E49+E50 -> 0 | O6: =+E51 -> 11000 | Q6: =SUM(I6:O6) -> 34907.2 | R6: =+E54 -> 10000 | S6: =+E57 -> 0 | T6: =+Q6-R6-S6 -> 24907.2
B7: AGUINALDO | H7: JUANI | I7: =+E62 -> 36782.4 | J7: =+E63 -> 931.2 | K7: =+E68 -> 5587.2 | L7: =+E67 -> 2500 | M7: =+E65 -> 0 | N7: =+E70+E69 -> 1047.6 | O7: =+E71 -> 16500 | Q7: =SUM(I7:O7) -> 63348.4 | R7: =+E73 -> 0 | S7: =+E74 -> 30064.45 | T7: =+Q7-R7-S7 -> 33283.95
B8: FALTA/RETIRO sin justif | D8: =-D4 -> -203.04 | E8: =+C8*D8 -> 0 | H8: JONA | I8: =+E79 -> 30456 | J8: =+E80 -> 864 | K8: =+E85 -> 9504 | L8: =+E84 -> 2500 | M8: =+E82 -> 0 | N8: =+E87+E86 -> 486 | O8: =+E88 -> 16000 | Q8: =SUM(I8:O8) -> 59810 | R8: =+E91 -> 10000 | S8: =+E90 -> 24028.31 | T8: =+Q8-R8-S8 -> 25781.69
B9: Presentismo | D9: 5000 | E9: =+D9 -> 5000 | H9: LUCA | I9: =+E107 -> 33670 | J9: =+E108 -> 728 | K9: =+E111 -> 0 | L9: =+E112 -> 5000 | M9: =+E110 -> 0 | N9: =+E115+E114 -> 0 | O9: =+E116 -> 11000 | Q9: =SUM(I9:O9) -> 50398 | R9: =+E119 -> 8000 | T9: =+Q9-R9-S9 -> 42398
B10: LICENCIA ENFERMEDAD | D10: =+D4 -> 203.04 | E10: =C10*D10 -> 0 | H10: SILVI | I10: =+E96 -> 30000 | L10: =+E97 -> 3600 | M10: =+E101 -> 0 | N10: =+E100 -> 0 | O10: 0 | P10: =+E98 -> 8000 | Q10: =SUM(I10:P10) -> 41600 | R10: =+E101 -> 0 | T10: =+Q10-R10-S10 -> 41600
B11: HORA EXTRA x 50% | D11: =+D4*1.5 -> 304.56 | E11: =C11*D11 -> 0 | H11: GERMAN | I11: =+E146 -> 16005 | J11: =+E147 -> 0 | K11: =+E152 -> 0 | L11: =+E151 -> 2500 | M11: =+E149 -> 0 | N11: =+E115+E114 -> 0 | O11: =+E155 -> 8000 | Q11: =SUM(I11:O11) -> 26505 | R11: =+E157 -> 4000 | T11: =+Q11-R11-S11 -> 22505
B12: HORA EXTRA AL 100% | D12: =+D4*2 -> 406.08 | E12: =+C12*D12 -> 0 | H12: ALEJO | I12: =+E126 -> 23265 | J12: =+E127 -> 660 | K12: =+E132 -> 6600 | L12: =+E131 -> 2500 | M12: =+E129 -> 0 | N12: =+E134+E133 -> 247.5 | O12: =+E135 -> 8000 | Q12: =SUM(I12:O12) -> 41272.5 | R12: =+E141 -> 0 | T12: =+Q12-R12-S12 -> 41272.5
B13: NO REMUNERATIVO | C13: 11000 | E13: =+C13 -> 11000 | H13: TOTALES | R13: =SUM(R4:R12) -> 32000 | S13: =SUM(S4:S12) -> 72232.59 | T13: =SUM(T4:T12) -> 314685.55
B14: OOSS / MONOT. / SEGURO | E14: =+C14 -> 0
B15: TOTAL SUELDO | E15: =SUM(E4:E14) -> 36507.04
B16: ADELANTO
B17: DEPOSITO | E17: 18139.83
B18: TOTAL A COBRAR | E18: =+E15-E16-E17 -> 18367.21
B20: FACU | I20: DIAS | J20: HS | K20: ENE
B21: DETALLE | C21: HS TRABAJADAS | D21: VALOR / HORA | E21: IMPORTE | F21: =14*8 -> 112 | H21: LABORAL | I21: 17 | J21: 9 | K21: =+I21*J21 -> 153
B22: SUELDO | C22: 44 | D22: 232.8 | E22: =C22*D22 -> 10243.2 | F22: =7*9 -> 63 | H22: FERIADO | I22: 0.5 | J22: 8 | K22: =+I22*J22 -> 4
B23: FERIADO | C23: =+K22 -> 4 | D23: =+D22 -> 232.8 | E23: =+C23*D23 -> 931.2 | H23: VIERNES | I23: 4 | J23: 8 | K23: =+I23*J23 -> 32
B24: VACACIONES | C24: 112 | D24: =+D22 -> 232.8 | E24: =+C24*D24 -> 26073.6 | F24: =4*9 -> 36 | I24: hs mes | K24: =SUM(K21:K23) -> 189
B25: AGUINALDO | F25: 8
B26: FALTA/RETIRO sin justif | D26: =-D22 -> -232.8 | E26: =C26*D26 -> 0
B27: Presentismo 50% | E27: 2500
B28: LICENCIA ENFERMEDAD | C28: 40 | D28: 232.8 | E28: =+C28*D28 -> 9312
B29: EXTRA AL 100% feriado | D29: =+D22*2 -> 465.6 | E29: =C29*D29 -> 0 | J29: HORA | K29: HORA X | L29: NO REM.
B30: EXTRA al 50% | D30: =+D22*1.5 -> 349.2 | E30: =C30*D30 -> 0 | I30: JUANI | J30: =194*1.2 -> 232.8 | K30: =+J30*1.5 -> 349.2 | L30: 13500
B31: NO REMUNERATIVO | C31: 16500 | E31: =+C31 -> 16500 | I31: JONA | J31: =180*1.2 -> 216 | K31: =+J31*1.5 -> 324 | L31: 13000
B32: OOSS / MONOT. / SEGURO | E32: =+C32 -> 0 | I32: FACU | J32: =180*1.2 -> 216 | K32: =+J32*1.5 -> 324 | L32: 13500
B33: TOTAL SUELDO | E33: =SUM(E22:E31) -> 65560 | I33: PILU | J33: =169.2*1.2 -> 203.04 | K33: =+J33*1.5 -> 304.56 | L33: 11000
B34: SEGURO CLIO | E34: 990 | I34: CHACO | J34: =156*1.2 -> 187.2 | K34: =+J34*1.5 -> 280.8 | L34: 11000
B35: ADELANTO | I35: LUCA | J35: 165 | K35: =+J35*1.5 -> 247.5 | L35: 8000
B36: OBRA SOCIAL (NOBIS) | I36: ALEJO | J36: =132*1.2 -> 158.4 | K36: =+J36*1.5 -> 237.6 | L36: 8000
B37: MONOTRIBUTO | I37: GERMAN | J37: =+J36 -> 158.4 | K37: =+J37*1.5 -> 237.6 | L37: 8000
B38: TOTAL A COBRAR | E38: =+E33-E34-E35-E36-E37 -> 64570
B40: CHACO
B41: DETALLE | C41: HS TRABAJADAS | D41: VALOR / HORA | E41: IMPORTE
B42: SUELDO | C42: 97 | D42: 187.2 | E42: =C42*D42 -> 18158.4
B43: FERIADO | C43: =+K22 -> 4 | D43: 187.2 | E43: =+C43*D43 -> 748.8 | H43: FACU
B44: VACACIONES (pago dic) | C44: 112 | D44: =+D42 -> 187.2 | H44: DETALLE | I44: HS TRABAJADAS | J44: VALOR / HORA | K44: IMPORTE
B45: AGUINALDO | H45: SUELDO | I45: 71 | J45: 232.8 | K45: =I45*J45 -> 16528.8 | L45: =7*9 -> 63
B46: FALTA/RETIRO sin justif | D46: =-D42 -> -187.2 | E46: =+C46*D46 -> 0 | H46: FERIADO | I46: =+Q45 -> 0 | J46: =+J45 -> 232.8 | K46: =+I46*J46 -> 0 | L46: 8
B47: Presentismo | D47: 5000 | E47: 5000 | H47: VACACIONES | I47: 112 | J47: =+J45 -> 232.8 | K47: =+I47*J47 -> 26073.6
B48: LICENCIA ENFERMEDAD | D48: =+D42 -> 187.2 | E48: =C48*D48 -> 0 | H48: AGUINALDO
B49: EXTRA AL 100% feriado | D49: =+D42*2 -> 374.4 | E49: =C49*D49 -> 0 | H49: FALTA/RETIRO sin justif | J49: =-J45 -> -232.8 | K49: =I49*J49 -> 0
B50: EXTRA al 50% | D50: =+D42*1.5 -> 280.8 | E50: =C50*D50 -> 0 | H50: Presentismo 50% | K50: 2500
B51: NO REMUNERATIVO | C51: 11000 | E51: =+C51 -> 11000 | H51: LICENCIA ENFERMEDAD | I51: 44 | J51: 232.8 | K51: =+I51*J51 -> 10243.2
B52: OOSS / MONOT. / SEGURO | E52: =+C52 -> 0 | H52: EXTRA AL 100% feriado | J52: =+J45*2 -> 465.6 | K52: =I52*J52 -> 0
B53: TOTAL SUELDO | E53: =SUM(E42:E52) -> 34907.2 | H53: EXTRA al 50% | J53: =+J45*1.5 -> 349.2 | K53: =I53*J53 -> 0
B54: ADELANTO | E54: 10000 | H54: NO REMUNERATIVO | I54: 16500 | K54: =+I54 -> 16500
B55: DEPOSITO | H55: OOSS / MONOT. / SEGURO | K55: =+I55 -> 0
B56: OBRA SOCIAL | E56: - | H56: TOTAL SUELDO | K56: =SUM(K45:K54) -> 71845.6
B57: MONOTRIBUTO | H57: SEGURO CLIO | K57: 990
B58: TOTAL A COBRAR | E58: =+E53-E54-E57 -> 24907.2 | H58: ADELANTO
H59: OBRA SOCIAL (NOBIS)
B60: JUANI | H60: MONOTRIBUTO
B61: DETALLE | C61: HS TRABAJADAS | D61: VALOR / HORA | E61: IMPORTE | H61: TOTAL A COBRAR | K61: =+K56-K57-K58-K59-K60 -> 70855.6
B62: SUELDO | C62: 158 | D62: 232.8 | E62: =C62*D62 -> 36782.4
B63: FERIADO | C63: =+K22 -> 4 | D63: =+D62 -> 232.8 | E63: =C63*D63 -> 931.2 | K63: -64570
B64: VACACIONES (14 d. pend) | D64: 232.8 | E64: =C64*D64 -> 0
B65: AGUINALDO
B66: FALTA/RETIRO sin justif | C66: 0 | E66: 0
B67: Presentismo 50% | E67: 2500
B68: LICENCIA ENFERMEDAD | C68: 24 | D68: =+D62 -> 232.8 | E68: =+C68*D68 -> 5587.2 | F68: licencia 31/01
B69: EXTRA AL 100% feriado | D69: =+D62*2 -> 465.6 | E69: =C69*D69 -> 0
B70: EXTRA al 50% | C70: 3 | D70: =+D62*1.5 -> 349.2 | E70: =C70*D70 -> 1047.6
B71: NO REMUNERATIVO | C71: 16500 | E71: =+C71 -> 16500
B72: TOTAL SUELDO | E72: =+E62+E63+E64+E66+E67+E68+E69+E70+E71 -> 63348.4
B73: ADELANTO
B74: DEPOSITO | E74: 30064.45
B75: TOTAL A COBRAR | E75: =+E72-E74 -> 33283.95
B77: JONA
B78: DETALLE | C78: HS TRABAJADAS | D78: VALOR / HORA | E78: IMPORTE
B79: SUELDO | C79: 141 | D79: 216 | E79: =+C79*D79 -> 30456
B80: FERIADO | C80: =+K22 -> 4 | D80: =+D79 -> 216 | E80: =+C80*D80 -> 864
B81: VACACIONES
B82: AGUINALDO
B83: FALTA/RETIRO sin justif | D83: =-D80 -> -216
B84: Presentismo 50% | E84: 2500
B85: LICENCIA ENFERMEDAD | C85: 44 | D85: =+D79 -> 216 | E85: =+C85*D85 -> 9504 | F85: desde 14/01/22 a 21/01/22
B86: EXTRA AL 100% feriado | D86: =+D79*2 -> 432 | E86: =+C86*D86 -> 0
B87: EXTRA al 50% | C87: 1.5 | D87: =+D79*1.5 -> 324 | E87: =+D87*C87 -> 486
B88: NO REMUNERATIVO | C88: 16000 | E88: =+C88 -> 16000
B89: TOTAL SUELDO | E89: =SUM(E79:E88) -> 59810
B90: DEPOSITO | E90: 24028.31
B91: ADELANTO | E91: 10000
B92: TOTAL A COBRAR | E92: =+E89-E90-E91 -> 25781.69
B94: SILVINA
B95: DETALLE | C95: HS TRABAJADAS | D95: VALOR / HORA | E95: IMPORTE
B96: SUELDO | C96: 105 | D96: =+E96/C96 -> 285.71429 | E96: 30000
B97: Presentismo % | D97: 3600 | E97: 3600
B98: hs TARDE (Mar/Jue 3,5) | C98: 28 | D98: =+D96 -> 285.71429 | E98: =C98*D98 -> 8000
B99: VACACIONES
B100: OOSS Y MONOTRIBUTO
B101: AGUINALDO
B103: TOTAL A COBRAR | E103: =+E96+E97+E98 -> 41600
B105: LUCA
B106: DETALLE | C106: HS TRABAJADAS | D106: VALOR / HORA | E106: IMPORTE
B107: SUELDO | C107: =+K21++K23 -> 185 | D107: 182 | E107: =C107*D107 -> 33670
...

Sheet MARZO2022
B2: PILU
B3: DETALLE | C3: HS TRABAJADAS | D3: VALOR / HORA | E3: IMPORTE
B4: SUELDO | C4: 186 | D4: 264 | E4: =+C4*D4 -> 49104
B5: FERIADO | C5: =+E36 -> 16 | D5: =+D4 -> 264 | E5: =+C5*D5 -> 4224
B6: Presentismo | D6: 5000 | E6: =+D6 -> 5000
E7: =C7*D7 -> 0
B8: HORA EXTRA x 50% | C8: 6 | D8: =+D4*1.5 -> 396 | E8: =+C8*D8 -> 2376
B9: HORA EXTRA AL 100%
B10: NO REMUNERATIVO | C10: 11000 | E10: =+C10 -> 11000
B11: OOSS / MONOT. / SEGURO | E11: =+C11 -> 0
B12: TOTAL SUELDO | E12: =SUM(E4:E11) -> 71704
B13: ADELANTO
B14: DEPOSITO | E14: -29725.51
B15: TOTAL A COBRAR | E15: =+E12+E14 -> 41978.49
B17: FACU
B18: DETALLE | C18: HS TRABAJADAS | D18: VALOR / HORA | E18: IMPORTE
B19: SUELDO | C19: 186 | D19: 302.64 | E19: =C19*D19 -> 56291.04
B20: FERIADO | C20: =+E36 -> 16 | D20: =+D19 -> 302.64 | E20: =+C20*D20 -> 4842.24
B21: Presentismo 50% | E21: 5000
B23: EXTRA AL 100% feriado
B24: EXTRA al 50% | C24: 9.5 | D24: =+D20*1.5 -> 453.96 | E24: =+C24*D24 -> 4312.62
B25: NO REMUNERATIVO | C25: 16500 | E25: 16500
B26: OOSS / MONOT. / SEGURO
B27: TOTAL SUELDO | E27: =SUM(E19:E25) -> 86945.9
B28: SEGURO CLIO | E28: -1150
B29: ADELANTO
B30: TOTAL A COBRAR | E30: =+E27+E28 -> 85795.9
C34: DIAS | D34: HS | E34: MAR
B35: LABORAL | C35: 18 | D35: 9 | E35: =+C35*D35 -> 162
B36: FERIADO | C36: 2 | D36: 8 | E36: =+C36*D36 -> 16
B37: VIERNES | C37: 3 | D37: 8 | E37: =+C37*D37 -> 24
B47: HEINLEIN (CHACO)
B48: DETALLE | C48: HS TRABAJADAS | D48: VALOR / HORA | E48: IMPORTE
B49: SUELDO | C49: 186 | D49: 224.64 | E49: =C49*D49 -> 41783.04
B50: FERIADO | C50: =+E36 -> 16 | D50: 224.64 | E50: =+C50*D50 -> 3594.24
B52: Presentismo | D52: 5000 | E52: 5000
B53: EXTRA AL 100% feriado
B54: EXTRA al 50% | C54: 10 | D54: =+D49*1.5 -> 336.96 | E54: =C54*D54 -> 3369.6
B55: NO REMUNERATIVO | C55: 11000 | E55: =+C55 -> 11000
B56: OOSS / MONOT. / SEGURO | E56: =+C56 -> 0
B57: TOTAL SUELDO | E57: =SUM(E49:E56) -> 64746.88
B58: ADELANTO | E58: 15000
B60: TOTAL A COBRAR | E60: =+E57-E58 -> 49746.88
B62: JUANI
B63: DETALLE | C63: HS TRABAJADAS | D63: VALOR / HORA | E63: IMPORTE
B64: SUELDO | C64: 186 | D64: 302.64 | E64: =C64*D64 -> 56291.04
B65: FERIADO | C65: =+E36 -> 16 | D65: =+D64 -> 302.64 | E65: =C65*D65 -> 4842.24
B66: Presentismo 50% | E66: 5000
B67: EXTRA AL 100% feriado
B68: EXTRA al 50% | C68: 2.5 | D68: =+D64*1.5 -> 453.96 | E68: =C68*D68 -> 1134.9
B69: NO REMUNERATIVO | C69: 16500 | E69: =+C69 -> 16500
B70: TOTAL SUELDO | E70: =+E64+E65+E66+E68+E69 -> 83768.18
B71: ADELANTO
B72: DEPOSITO | E72: -30370.35
B74: TOTAL A COBRAR | E74: =+E70+E72 -> 53397.83
B76: JONA
B77: DETALLE | C77: HS TRABAJADAS | D77: VALOR / HORA | E77: IMPORTE
B78: SUELDO | C78: 186 | D78: 280.8 | E78: =+C78*D78 -> 52228.8
B79: FERIADO | C79: =+E36 -> 16 | D79: =+D78 -> 280.8 | E79: =+C79*D79 -> 4492.8
B80: Presentismo 50% | E80: 5000
B81: EXTRA AL 100% feriado
B82: EXTRA al 50% | C82: 12 | D82: =+D78*1.5 -> 421.2 | E82: =+D82*C82 -> 5054.4
B83: NO REMUNERATIVO | C83: 16000 | E83: =+C83 -> 16000
B84: TOTAL SUELDO | E84: =SUM(E78:E83) -> 82776
B85: DEPOSITO | E85: -24316.9
B86: ADELANTO | E86: -15000
B87: TOTAL A COBRAR | E87: =+E84+E85+E86 -> 43459.1
B99: ANDREA
B100: DETALLE | C100: HS TRABAJADAS | D100: VALOR / HORA | E100: IMPORTE
B101: SUELDO | C101: 150 | D101: 350 | E101: =+C101*D101 -> 52500
B102: Presentismo %
B103: Feriado
B104: HORAS EXTRAS 50% | C104: 11 | D104: =+D101*1.5 -> 525 | E104: =+C104*D104 -> 5775
B105: ADELANTO | E105: -15000
B108: TOTAL A COBRAR | E108: =+E101+E104+E105 -> 43275
B110: LUCA
B111: DETALLE | C111: HS TRABAJADAS | D111: VALOR / HORA | E111: IMPORTE
B112: SUELDO | C112: 186 | D112: 210 | E112: =C112*D112 -> 39060
B113: FERIADO | C113: =+E36 -> 16 | D113: =+D112 -> 210 | E113: =C113*D113 -> 3360
B115: Presentismo | D115: 5000 | E115: 5000
B116: EXTRA AL 100% feriado
B117: EXTRA al 50% | C117: 2.5 | D117: =+D112*1.5 -> 315 | E117: =+C117*D117 -> 787.5
B118: NO REMUNERATIVO | C118: 11000 | E118: =+C118 -> 11000
B119: OOSS / MONOT. / SEGURO | E119: =+C119 -> 0
B120: TOTAL SUELDO | E120: =SUM(E112:E119) -> 59207.5
B121: ADELANTO | E121: 10000
B124: TOTAL A COBRAR | E124: =+E120-E121 -> 49207.5
B126: SANDRONE(CORCHO)
B127: DETALLE | C127: HS TRABAJADAS | D127: VALOR / HORA | E127: IMPORTE
B128: SUELDO | C128: 98 | D128: 224.64 | E128: =+C128*D128 -> 22014.72
B129: FERIADO | C129: 8 | D129: 224.64 | E129: =+C129*D129 -> 1797.12
B130: Presentismo | E130: 2500
B131: EXTRA AL 100% feriado
B132: EXTRA al 50% | C132: 11.4 | D132: =+D128*1.5 -> 336.96 | E132: =+C132*D132 -> 3841.344
B133: NO REMUNERATIVO | C133: 5500 | E133: 5500
B134: OOSS / MONOT. / SEGURO
B136: TOTAL SUELDO | E136: =SUM(E128:E133) -> 35653.184
B138: CARLE GERMAN
B139: DETALLE | C139: HS TRABAJADAS | D139: VALOR / HORA | E139: IMPORTE
B140: SUELDO | C140: 186 | D140: 190 | E140: =C140*D140 -> 35340
...

Sheet RES422
B2: MARZO | C2: 2022
B4: DETALLE | C4: IMPORTE A COBRAR
B5: PILU | C5: 34154.34
B6: FACU | C6: 81737.4
B7: CHACO | C7: 47640.44
B8: JUANI | C8: 48743.81
B9: JONA | C9: 40092.81
B10: LUCA | C10: 48095.03
B11: GERMAN | C11: 51158.67
B12: CORCHO | C12: 61566.87
B13: ANDREA | C13: 55100
B15: TOTAL SUELDOS 03/2022 | C15: =+C5+C6+C7+C8+C9+C10+C11+C12+C13 -> 468289.37
B19: 44652
B20: DENOMINACION | C20: VALOR HORA | D20: PRESENTISMO
B21: PILU | C21: 280.37 | D21: 5000
B22: FACU | C22: 321.4 | D22: 5000
B23: CHACO | C23: 238.57 | D23: 5000
B24: JUANI | C24: 321.4 | D24: 5000
B25: JONA | C25: 298.21 | D25: 5000
B26: LUCA | C26: 223.02 | D26: 5000
B27: GERMAN | C27: 201.18 | D27: 5000
B28: CORCHO | C28: 238.57 | D28: 5000
B29: ANDREA | C29: 400
B31: 44682
B32: DENOMINACION | C32: VALOR HORA | D32: PRESENTISMO
B33: PILU | C33: 291.6 | D33: 5000
B34: FACU | C34: 334.3 | D34: 5000
B35: CHACO | C35: 248.15 | D35: 5000
B36: JUANI | C36: 334.3 | D36: 5000
B37: JONA | C37: 310.15 | D37: 5000
B38: LUCA | C38: 232 | D38: 5000
B39: GERMAN | C39: 209.25 | D39: 5000
B40: CORCHO | C40: 248.15 | D40: 5000
B41: ANDREA | C41: 400
B42: GABRIEL | C42: 310
B43: MAXI
B45: 44713
B46: DENOMINACION | C46: VALOR HORA | D46: PRESENTISMO
B47: PILU | C47: =291.6*1.1 -> 320.76 | D47: 5000
B48: FACU | C48: =334.3*1.1 -> 367.73 | D48: 5000
B49: CHACO | C49: =248.15*1.1 -> 272.965 | D49: 5000
B50: JUANI | C50: =334.3*1.1 -> 367.73 | D50: 5000
B51: JONA | C51: =310.15*1.1 -> 341.165 | D51: 5000
B52: LUCA | C52: =232*1.1 -> 255.2 | D52: 5000
B53: GERMAN | C53: =209.25*1.1 -> 230.175 | D53: 5000
B54: CORCHO | C54: =248.15*1.1 -> 272.965 | D54: 5000
B55: ANDREA | C55: 400 | D55: 5000
B56: GABRIEL | C56: 310 | D56: 2500
B57: MAXI | C57: 360 | D57: 5000
B61: DENOMINACION | C61: IMPORTE
B62: PILU | C62: 61062.48
B63: FACU | C63: 176404.15
B64: CHACO | C64: 107708.65
B65: JUANI | C65: 98095.3
B66: JONA | C66: 100660.98
B67: LUCA | C67: 96940.8
B68: CORCHO | C68: 101554.24
B69: GERMAN | C69: 79797.94
B70: GABRIEL | C70: 57100
B71: MAXI | C71: 20480
B72: ANDREA | C72: 85200
B73: TOTAL 06/2022 | C73: =SUM(C62:C72) -> 985004.54

Sheet ABRIL2022
D2: 44652
D4: PILU
D5: DETALLE | E5: HS TRABAJADAS | F5: VALOR / HORA | G5: IMPORTE
D6: SUELDO | E6: 176 | F6: 280.37 | G6: =+E6*F6 -> 49345.12
D7: FERIADO | E7: 8 | F7: 284.37 | G7: =+E7*F7 -> 2274.96
D8: Presentismo | E8: 0.5 | F8: 5000 | G8: =+F8*0.5 -> 2500
D9: FERIADO 2 ABRIL | E9: 4 | F9: 280.37 | G9: =+E9*F9 -> 1121.48
D10: HORA EXTRA x 50% | E10: 1.5 | F10: =+F6*1.5 -> 420.555 | G10: =+E10*F10 -> 630.8325
D11: HORA EXTRA AL 100%
D12: NO REMUNERATIVO | E12: 11000 | G12: =+E12 -> 11000
D14: TOTAL SUELDO | G14: =SUM(G6:G13) -> 66872.393
D15: ADELANTO
D16: DEPOSITO | G16: -32718.05
D17: TOTAL A COBRAR | G17: =+G14+G16 -> 34154.342
D19: FACU
D20: DETALLE | E20: HS TRABAJADAS | F20: VALOR / HORA | G20: IMPORTE
D21: SUELDO | E21: 176 | F21: 321.4 | G21: =E21*F21 -> 56566.4
D22: FERIADO | E22: 8 | F22: =+F21 -> 321.4 | G22: =+E22*F22 -> 2571.2
D23: Presentismo | G23: 5000
D24: FERIADO 2 DE ABRIL | E24: 4 | F24: 321.4 | G24: =+E24*F24 -> 1285.6
D25: EXTRA al 50% | E25: 2 | F25: =+F22*1.5 -> 482.1 | G25: =+E25*F25 -> 964.2
D26: NO REMUNERATIVO | G26: 16500
D28: TOTAL SUELDO | G28: =SUM(G21:G26) -> 82887.4
D29: SEGURO CLIO | G29: -1150
D31: TOTAL A COBRAR | G31: =+G28+G29 -> 81737.4
D33: CHACO
D34: DETALLE | E34: HS TRABAJADAS | F34: VALOR / HORA | G34: IMPORTE
D35: SUELDO | E35: 176 | F35: 238.57 | G35: =E35*F35 -> 41988.32
D36: FERIADO | E36: 8 | F36: 238.57 | G36: =+E36*F36 -> 1908.56
D37: Presentismo | F37: 5000 | G37: 5000
D38: FERIADO 2 DE ABRIL | E38: 4 | F38: 238.57 | G38: =+E38*F38 -> 954.28
D39: EXTRA al 50% | E39: 5 | F39: =+F35*1.5 -> 357.855 | G39: =E39*F39 -> 1789.275
D40: NO REMUNERATIVO | E40: 11000 | G40: =+E40 -> 11000
D42: TOTAL SUELDO | G42: =SUM(G35:G41) -> 62640.435
D43: ADELANTO | G43: -15000
D45: TOTAL A COBRAR | G45: =+G42+G43 -> 47640.435
D50: JUANI
D51: DETALLE | E51: HS TRABAJADAS | F51: VALOR / HORA | G51: IMPORTE
D52: SUELDO | E52: 176 | F52: 321.4 | G52: =E52*F52 -> 56566.4
D53: FERIADO | E53: 8 | F53: =+F52 -> 321.4 | G53: =E53*F53 -> 2571.2
D54: Presentismo | G54: 5000
D55: FERIADO 2 ABRIL | E55: 4 | F55: 321.4 | G55: =+E55*F55 -> 1285.6
D56: EXTRA al 50% | E56: 0.5 | F56: =+F52*1.5 -> 482.1 | G56: =E56*F56 -> 241.05
D57: NO REMUNERATIVO | E57: 16500 | G57: =+E57 -> 16500
D59: TOTAL SUELDO | G59: =+G52+G53+G54+G56+G57 -> 80878.65
D60: DEPOSITO | G60: -33420.44
D62: TOTAL A COBRAR | G62: =+G52+G53+G54+G55+G56+G57+G60 -> 48743.81
D64: JONA
D65: DETALLE | E65: HS TRABAJADAS | F65: VALOR / HORA | G65: IMPORTE
D66: SUELDO | E66: 176 | F66: 298.21 | G66: =+E66*F66 -> 52484.96
D67: FERIADO | E67: 8 | F67: =+F66 -> 298.21 | G67: =+E67*F67 -> 2385.68
D68: Presentismo | G68: 5000
D69: FERIADO 2 DE ABRIL | E69: 4 | F69: 298.21 | G69: =+E69*F69 -> 1192.84
D70: EXTRA al 50% | E70: 0.5 | F70: =+F66*1.5 -> 447.315 | G70: =+F70*E70 -> 223.6575
D71: NO REMUNERATIVO | E71: 16000 | G71: =+E71 -> 16000
D73: TOTAL SUELDO | G73: =SUM(G66:G71) -> 77287.137
D74: DEPOSITO | G74: -27194.33
D75: ADELANTO | G75: -10000
D76: TOTAL A COBRAR | G76: =+G73+G74+G75 -> 40092.807
D78: LUCA
D79: DETALLE | E79: HS TRABAJADAS | F79: VALOR / HORA | G79: IMPORTE
D80: SUELDO | E80: 176 | F80: 223.02 | G80: =E80*F80 -> 39251.52
D81: FERIADO | E81: 8 | F81: =+F80 -> 223.02 | G81: =E81*F81 -> 1784.16
D82: Presentismo | G82: 5000
D83: FERIADO 2 ABRIL | E83: 4 | F83: 223.02 | G83: =+E83*F83 -> 892.08
D84: EXTRA al 50% | E84: 0.5 | F84: =+F80*1.5 -> 334.53 | G84: =+E84*F84 -> 167.265
D85: NO REMUNERATIVO | E85: 11000 | G85: =+E85 -> 11000
D87: TOTAL SUELDO | G87: =SUM(G80:G86) -> 58095.025
D88: ADELANTO | G88: 10000
D90: TOTAL A COBRAR | G90: =+G87-G88 -> 48095.025
D96: SANDRONE(CORCHO)
D97: DETALLE | E97: HS TRABAJADAS | F97: VALOR / HORA | G97: IMPORTE
D98: SUELDO | E98: 176 | F98: 238.57 | G98: =+E98*F98 -> 41988.32
D99: FERIADO | E99: 8 | F99: 238.57 | G99: =+E99*F99 -> 1908.56
D100: Presentismo | G100: 5000
D101: FERIADO 2 ABRIL | E101: 4 | F101: 238.57 | G101: =+E101*F101 -> 954.28
D102: EXTRA al 50% | E102: 2 | F102: =+F98*1.5 -> 357.855 | G102: =+E102*F102 -> 715.71
D103: NO REMUNERATIVO | G103: 11000
D106: TOTAL A COBRAR | G106: =SUM(G98:G103) -> 61566.87
D108: CARLE GERMAN
D109: DETALLE | E109: HS TRABAJADAS | F109: VALOR / HORA | G109: IMPORTE
D110: SUELDO | E110: 176 | F110: 201.78 | G110: =E110*F110 -> 35513.28
D111: FERIADO | E111: 8 | F111: 201.78 | G111: =E111*F111 -> 1614.24
D112: Presentismo | F112: 5000 | G112: =+F112 -> 5000
D113: FERIADO 2 ABRIL | E113: 4 | F113: 201.78 | G113: =+E113*F113 -> 807.12
D114: EXTRA al 50% | E114: 9 | F114: =+F110*1.5 -> 302.67 | G114: =+F114*E114 -> 2724.03
D115: NO REMUNERATIVO | E115: 8000 | G115: =+E115 -> 8000
D117: TOTAL SUELDO | G117: =+G110+G111+G112+G113+G114+G115 -> 53658.67
D118: ADELANTO | G118: -2500
D119: TOTAL A COBRAR | G119: =+G110+G111+G112+G113+G114+G115+G118 -> 51158.67
D121: ANDREA
D122: DETALLE | E122: HS TRABAJADAS | F122: VALOR / HORA | G122: IMPORTE
D123: SUELDO | E123: 160 | F123: 400 | G123: =+E123*F123 -> 64000
D124: Feriado | E124: 8 | F124: 400 | G124: =+E124*F124 -> 3200
D125: HORAS EXTRAS 50% | E125: 5.5 | F125: =+F123*1.5 -> 600 | G125: =+E125*F125 -> 3300
D126: FERIADO 2 ABRIL | E126: 4 | F126: 400 | G126: =+E126*F126 -> 1600
D127: ADELANTO | G127: -12670
D128: ADELANTO | G128: -4330
D130: TOTAL A COBRAR | G130: =+G123+G124+G125+G126+G127+G128 -> 55100
E133: DIAS | F133: HS | G133: ABR
...

Sheet JUNIO2022
B2: PILU
B3: DETALLE | C3: HS TRABAJADAS | D3: VALOR / HORA | E3: IMPORTE
B4: SUELDO | C4: 177 | D4: 320.76 | E4: =+C4*D4 -> 56774.52
B5: FERIADO | C5: =+E169 -> 16 | D5: =+D4 -> 320.76 | E5: =+C5*D5 -> 5132.16
B6: Presentismo | E6: 2500
B7: HORA EXTRA x 50% | C7: 4.5 | D7: =+D4*1.5 -> 481.14 | E7: =+C7*D7 -> 2165.13
B8: HORA EXTRA AL 100%
B9: NO REMUNERATIVO | C9: 11000 | E9: =+C9 -> 11000
B10: PREMIO P/SAB.TRABAJADO | C10: 0.5 | D10: 1000 | E10: =+C10*D10 -> 500
B11: SAC JUNIO/2022 | E11: 39036
B12: TOTAL SUELDO | E12: =+E4+E5+E6+E7+E9+E10+E11 -> 117107.81
B13: DEPOSITO SAC06/2022 | E13: -17562.79
B14: DEPOSITO REMUNERACION 06/2022 | E14: -38482.54
B15: TOTAL A COBRAR | E15: =+E12+E13+E14 -> 61062.48
B18: FACU
B19: DETALLE | C19: HS TRABAJADAS | D19: VALOR / HORA | E19: IMPORTE
B20: SUELDO | C20: 177 | D20: 367.73 | E20: =C20*D20 -> 65088.21
B21: FERIADO | C21: =+E169 -> 16 | D21: =+D20 -> 367.73 | E21: =+C21*D21 -> 5883.68
B22: Presentismo | E22: 5000
B23: EXTRA AL 100% feriado | C23: 15.5 | D23: =+D20*2 -> 735.46 | E23: =+C23*D23 -> 11399.63
B24: EXTRA al 50% | C24: 14.5 | D24: =+D21*1.5 -> 551.595 | E24: =+C24*D24 -> 7998.1275
B25: NO REMUNERATIVO | C25: 16500 | E25: 20000
B26: PREMIO P/SAB.TRABAJADO | C26: 3 | D26: 1000 | E26: =+C26*D26 -> 3000
B27: SAC JUNIO/2022 | E27: 59184.5
B28: TOTAL SUELDO | E28: =+E20+E21+E22+E23+E24+E25+E26+E27 -> 177554.15
B29: SEGURO CLIO | E29: -1150
B30: TOTAL A COBRAR | E30: =+E28+E29 -> 176404.15
B33: HEINLEIN (CHACO)
B34: DETALLE | C34: HS TRABAJADAS | D34: VALOR / HORA | E34: IMPORTE
B35: SUELDO | C35: 177 | D35: 272.965 | E35: =C35*D35 -> 48314.805
B36: FERIADO | C36: =+E169 -> 16 | D36: 272.97 | E36: =+C36*D36 -> 4367.52
B37: Presentismo | D37: 5000 | E37: 5000
B38: EXTRA AL 100% feriado | C38: 14 | D38: =+D35*2 -> 545.93 | E38: =+C38*D38 -> 7643.02
B39: EXTRA al 50% | C39: 8.5 | D39: =+D35*1.5 -> 409.4475 | E39: =C39*D39 -> 3480.3038
B40: NO REMUNERATIVO | C40: 11000 | E40: =+C40 -> 11000
B41: PREMIO P/SAB.TRABAJADO | C41: 2 | D41: 1000 | E41: =+C41*D41 -> 2000
B42: SAC JUNIO 2022 | E42: 40903
B43: TOTAL SUELDO | E43: =+E35+E36+E37+E38+E39+E40+E41+E42 -> 122708.65
B44: ADELANTO | E44: -15000
B45: TOTAL A COBRAR | E45: =+E43+E44 -> 107708.65
B49: JUANI
B50: DETALLE | C50: HS TRABAJADAS | D50: VALOR / HORA | E50: IMPORTE
B51: SUELDO | C51: 177 | D51: 367.73 | E51: =C51*D51 -> 65088.21
B52: FERIADO | C52: =+E169 -> 16 | D52: =+D51 -> 367.73 | E52: =C52*D52 -> 5883.68
B53: Presentismo | E53: 5000
B54: EXTRA AL 100% | C54: 4 | D54: =+D51*2 -> 735.46 | E54: =+C54*D54 -> 2941.84
B55: EXTRA al 50% | C55: 11 | D55: =+D51*1.5 -> 551.595 | E55: =C55*D55 -> 6067.545
B56: NO REMUNERATIVO | C56: 16500 | E56: =+C56 -> 16500
B57: PREMIO P/SAB.TRABAJADO | C57: 2 | D57: 1000 | E57: =+C57*D57 -> 2000
B58: SAC JUNIO 2022 | E58: 51741
B59: TOTAL SUELDO | E59: =+E51+E52+E53+E54+E55+E56+E57+E58 -> 155222.28
B60: DEPOSITO SAC 06/2022 | E60: -17902.46
B61: DEPOSITO REMUNERACION 06/2022 | E61: -39224.52
B62: TOTAL A COBRAR | E62: =+E59+E60+E61 -> 98095.295
B65: JONA
B66: DETALLE | C66: HS TRABAJADAS | D66: VALOR / HORA | E66: IMPORTE
B67: SUELDO | C67: 177 | D67: 341.165 | E67: =+C67*D67 -> 60386.205
B68: FERIADO | C68: =+E169 -> 16 | D68: =+D67 -> 341.165 | E68: =+C68*D68 -> 5458.64
B69: Presentismo | E69: 5000
B70: EXTRA AL 100% | C70: 12 | D70: =+D67*2 -> 682.33 | E70: =+C70*D70 -> 8187.96
B71: EXTRA al 50% | C71: 11 | D71: =+D67*1.5 -> 511.7475 | E71: =+D71*C71 -> 5629.2225
B72: NO REMUNERATIVO | C72: 16000 | E72: =+C72 -> 16000
B73: PREMIO P/SAB.TRABAJADO | C73: 2.5 | D73: 1000 | E73: =+C73*D73 -> 2500
B74: SAC JUNIO 2022 | E74: 51581
B75: TOTAL SUELDO | E75: =+E67+E68+E69+E70+E71+E72+E73+E74 -> 154743.03
B76: DEPOSITO SAC 06/2022 | E76: -16983.45
B77: DEPOSITO REMUNERACION 06/2022 | E77: -37098.6
B78: TOTAL A COBRAR | E78: =+E75+E76+E77 -> 100660.98
B82: LUCA
B83: DETALLE | C83: HS TRABAJADAS | D83: VALOR / HORA | E83: IMPORTE
B84: SUELDO | C84: 177 | D84: 255.2 | E84: =C84*D84 -> 45170.4
B85: FERIADO | C85: =+E169 -> 16 | D85: =+D84 -> 255.2 | E85: =C85*D85 -> 4083.2
B86: Presentismo | D86: 5000 | E86: 5000
B87: EXTRA AL 100% | C87: 8 | D87: =+D84*2 -> 510.4 | E87: =+C87*D87 -> 4083.2
B88: EXTRA al 50% | C88: 2.5 | D88: =+D84*1.5 -> 382.8 | E88: =+C88*D88 -> 957
B89: NO REMUNERATIVO | C89: 11000 | E89: =+C89 -> 11000
B90: PREMIO P/SAB.TRABAJADO | C90: 1 | D90: 1000 | E90: =+C90*D90 -> 1000
B91: SAC JUNIO 2022 | E91: 35647
B92: TOTAL SUELDO | E92: =+E84+E85+E86+E87+E88+E89+E90+E91 -> 106940.8
B93: ADELANTO | E93: -10000
B94: TOTAL A COBRAR | E94: =+E92+E93 -> 96940.8
B99: SANDRONE(CORCHO)
B100: DETALLE | C100: HS TRABAJADAS | D100: VALOR / HORA | E100: IMPORTE
B101: SUELDO | C101: 177 | D101: 272.965 | E101: =+C101*D101 -> 48314.805
B102: FERIADO | C102: 16 | D102: 272.97 | E102: =+C102*D102 -> 4367.52
B103: Presentismo | E103: 5000
B104: EXTRA AL 100% feriado | C104: 4 | D104: =+D101*2 -> 545.93 | E104: =+C104*D104 -> 2183.72
B105: EXTRA al 50% | C105: 10.5 | D105: =+D101*1.5 -> 409.4475 | E105: =+C105*D105 -> 4299.1987
B106: NO REMUNERATIVO | C106: 5500 | E106: 11000
B107: PREMIO P/SAB.TRABAJADO | C107: 1 | D107: 1000 | E107: =+C107*D107 -> 1000
B108: SAC JUNIO 2022(PROP) | E108: 25389
B109: TOTAL SUELDO | E109: =+E101+E102+E103+E104+E105+E106+E107+E108 -> 101554.24
B113: CARLE GERMAN
B114: DETALLE | C114: HS TRABAJADAS | D114: VALOR / HORA | E114: IMPORTE
B115: SUELDO | C115: 177 | D115: 230.175 | E115: =C115*D115 -> 40740.975
B116: FERIADO | C116: 16 | D116: 230.18 | E116: =C116*D116 -> 3682.88
B117: Presentismo | E117: 2500
B118: EXTRA AL 100% | C118: 12 | D118: =+D115*2 -> 460.35 | E118: =+C118*D118 -> 5524.2
B119: EXTRA al 50% | C119: 11 | D119: =+D115*1.5 -> 345.2625 | E119: =+D119*C119 -> 3797.8875
B120: NO REMUNERATIVO | E120: 8000
...

Sheet JULIO2022
B2: PILU
B3: DETALLE | C3: HS TRABAJADAS | D3: VALOR / HORA | E3: IMPORTE
B4: SUELDO | C4: 180 | D4: 320.76 | E4: =+C4*D4 -> 57736.8
B5: FERIADO 9/7/22 | C5: 4 | D5: =+D4 -> 320.76 | E5: =+C5*D5 -> 1283.04
B6: Presentismo | E6: 5000
B7: HORA EXTRA x 50% | C7: 16.5 | D7: =+D4*1.5 -> 481.14 | E7: =+C7*D7 -> 7938.81
B8: NO REMUNERATIVO | C8: 11000 | E8: =+C8 -> 11000
B9: PREMIO P/SAB.TRABAJADO | C9: 1 | D9: 1000 | E9: =+C9*D9 -> 1000
B10: TOTAL SUELDO | E10: =SUM(E4:E9) -> 83958.65
B11: DEPOSITO 07/2022 | E11: -38482.54
B12: ADELANTO | E12: -10000
B13: TOTAL A COBRAR | E13: =+E10+E11+E12 -> 35476.11
B16: FACU
B17: DETALLE | C17: HS TRABAJADAS | D17: VALOR / HORA | E17: IMPORTE
B18: SUELDO | C18: 180 | D18: 367.73 | E18: =+C18*D18 -> 66191.4
B19: FERIADO 9/07/2022 | C19: 4 | D19: =+D18 -> 367.73 | E19: =+D19+C19 -> 371.73
B20: Presentismo | E20: 5000
B21: EXTRA al 50% | C21: 17.5 | D21: =+D19*1.5 -> 551.595 | E21: =+C21*D21 -> 9652.9125
B22: NO REMUNERATIVO | E22: 20000
B23: PREMIO P/SAB.TRABAJADO | C23: 1 | D23: 1000 | E23: =+C23*D23 -> 1000
B24: PREMIO P/LOZA | C24: 2 | D24: 3000 | E24: =+C24*D24 -> 6000
B25: TOTAL SUELDO | E25: =SUM(E18:E24) -> 108216.04
B26: SEGURO CLIO | E26: -1150
B27: ADELANTO | E27: -16000
B28: TOTAL A COBRAR | E28: =+E25+E26+E27 -> 91066.043
B31: HEINLEIN (CHACO)
B32: DETALLE | C32: HS TRABAJADAS | D32: VALOR / HORA | E32: IMPORTE
B33: SUELDO | C33: 162 | D33: 272.965 | E33: =C33*D33 -> 44220.33
B34: FERIADO 9/07/2022 | C34: 4 | D34: 272.97 | E34: =+C34*D34 -> 1091.88
B35: DIAS P/ENFERMEDAD | C35: 16 | D35: 272.97 | E35: =+C35*D35 -> 4367.52
B36: Presentismo | E36: 2500
B37: EXTRA al 50% | C37: 16 | D37: =+D33*1.5 -> 409.4475 | E37: =C37*D37 -> 6551.16
B38: NO REMUNERATIVO | C38: 11000 | E38: =+C38 -> 11000
B39: PREMIO P/SAB.TRABAJADO | C39: 1 | D39: 1000 | E39: =+C39*D39 -> 1000
B40: TOTAL SUELDO | E40: =SUM(E33:E39) -> 70730.89
B41: ADELANTO | E41: -15000
B42: TOTAL A COBRAR | E42: =+E40+E41 -> 55730.89
B46: JUANI
B47: DETALLE | C47: HS TRABAJADAS | D47: VALOR / HORA | E47: IMPORTE
B48: SUELDO | C48: 180 | D48: 367.73 | E48: =C48*D48 -> 66191.4
B49: FERIADO 9/07/2022 | C49: 4 | D49: =+D48 -> 367.73 | E49: =C49*D49 -> 1470.92
B50: Presentismo | E50: 5000
B51: EXTRA al 50% | C51: 17 | D51: =+D48*1.5 -> 551.595 | E51: =C51*D51 -> 9377.115
B52: NO REMUNERATIVO | C52: 16500 | E52: =+C52 -> 16500
B53: PREMIO P/SAB.TRABAJADO | C53: 1 | D53: 1000 | E53: =+C53*D53 -> 1000
B54: PREMIO P/LOZA | C54: 2 | D54: 3000 | E54: =+C54*D54 -> 6000
B55: TOTAL SUELDO | E55: =SUM(E48:E54) -> 105539.44
B56: DEPOSITO 07/2022 | E56: -39224.52
B57: TOTAL A COBRAR | E57: =SUM(E55:E56) -> 66314.915
B60: JONA
B61: DETALLE | C61: HS TRABAJADAS | D61: VALOR / HORA | E61: IMPORTE
B62: SUELDO | C62: 136 | D62: 341.165 | E62: =+C62*D62 -> 46398.44
B63: FERIADO 9/07/2022 | C63: 4 | D63: =+D62 -> 341.165 | E63: =+C63*D63 -> 1364.66
B64: DIAS P/ENFERMEDAD | C64: 40 | D64: 341.17 | E64: =+C64*D64 -> 13646.8
B65: Presentismo
B66: EXTRA al 50% | C66: 7.5 | D66: =+D62*1.5 -> 511.7475 | E66: =+D66*C66 -> 3838.1063
B67: NO REMUNERATIVO | C67: 16000 | E67: =+C67 -> 16000
B68: PREMIO P/SAB.TRABAJADO | D68: 1000 | E68: =+C68*D68 -> 0
B69: PREMIO P/LOZA | C69: 1 | D69: 3000 | E69: 3000
B70: TOTAL SUELDO | E70: =SUM(E62:E69) -> 84248.006
B71: DEPOSITO 07/2022 | E71: -37098.6
B72: TOTAL A COBRAR | E72: =SUM(E70:E71) -> 47149.406
B76: LUCA
B77: DETALLE | C77: HS TRABAJADAS | D77: VALOR / HORA | E77: IMPORTE
B78: SUELDO | C78: 180 | D78: 255.2 | E78: =C78*D78 -> 45936
B79: FERIADO 9/07/2022 | C79: 4 | D79: =+D78 -> 255.2 | E79: =C79*D79 -> 1020.8
B80: Presentismo | D80: 5000 | E80: 5000
B81: EXTRA al 50% | C81: 10 | D81: =+D78*1.5 -> 382.8 | E81: =+C81*D81 -> 3828
B82: NO REMUNERATIVO | C82: 11000 | E82: =+C82 -> 11000
B84: TOTAL SUELDO | E84: =SUM(E78:E83) -> 66784.8
B85: ADELANTO | E85: -10000
B86: TOTAL A COBRAR | E86: =+E84+E85 -> 56784.8
B98: SANDRONE(CORCHO)
B99: DETALLE | C99: HS TRABAJADAS | D99: VALOR / HORA | E99: IMPORTE
B100: SUELDO | C100: 180 | D100: 272.965 | E100: =+C100*D100 -> 49133.7
B101: FERIADO 9/07/2022 | C101: 4 | D101: 272.97 | E101: =+C101*D101 -> 1091.88
B102: Presentismo | E102: 5000
B103: EXTRA al 50% | C103: 25 | D103: =+D100*1.5 -> 409.4475 | E103: =+C103*D103 -> 10236.188
B104: NO REMUNERATIVO | E104: 11000
B105: PREMIO P/SAB.TRABAJADO | C105: 1 | D105: 1000 | E105: =+C105*D105 -> 1000
B106: TOTAL SUELDO | E106: =SUM(E100:E105) -> 77461.767
B110: CARLE GERMAN
B111: DETALLE | C111: HS TRABAJADAS | D111: VALOR / HORA | E111: IMPORTE
B112: SUELDO | C112: 171 | D112: 230.175 | E112: =C112*D112 -> 39359.925
B113: FERIADO 9/07/2022 | C113: 4 | D113: 230.18 | E113: =C113*D113 -> 920.72
B114: DIA P/ENFERMEDAD 11/07 | C114: 8 | D114: 230.18 | E114: =+C114*D114 -> 1841.44
B115: Presentismo | E115: 2500
B116: EXTRA al 50% | C116: 24.5 | D116: =+D112*1.5 -> 345.2625 | E116: =+D116*C116 -> 8458.9313
B117: NO REMUNERATIVO | E117: 8000
B118: PREMIO P/SAB.TRABAJADO | C118: 2 | D118: 1000 | E118: =+C118*D118 -> 2000
B119: TOTAL SUELDO | E119: =SUM(E112:E118) -> 63081.016
B120: ADELANTO | E120: -5000
B121: TOTAL A COBRAR | E121: =+E119+E120 -> 58081.016
B124: GABRIEL
B125: DETALLE | C125: HS TRABAJADAS | D125: VALOR / HORA | E125: IMPORTE
B126: HORAS TRABAJADAS | C126: 106.5 | D126: 310 | E126: =+C126*D126 -> 33015
B130: PRESENTISMO | E130: 2500
B131: TOTAL A COBRAR | E131: =+E126+E130 -> 35515
B136: ANDREA
B137: DETALLE | C137: HS TRABAJADAS | D137: VALOR / HORA | E137: IMPORTE
...

Sheet RESUMEN0722
C2: 44743
B4: DETALLE | C4: IMPORTE A COBRAR
B5: PILU | C5: 35476.11
B6: FACU | C6: 91066.04
B7: CHACO | C7: 55730.89
B8: JUANI | C8: 66314.92
B9: JONA | C9: 47149.41
B10: LUCA | C10: 56784.8
B11: GERMAN | C11: 58081.02
B12: CORCHO | C12: 77461.77
B13: ANDREA | C13: 47200
B14: GABRIEL | C14: 35515
B15: TOTAL SUELDOS 03/2022 | C15: =SUM(C5:C14) -> 570779.96
B21: 44713
B22: DENOMINACION | C22: VALOR HORA | D22: PRESENTISMO
B23: PILU | C23: =291.6*1.1 -> 320.76 | D23: 5000
B24: FACU | C24: =334.3*1.1 -> 367.73 | D24: 5000
B25: CHACO | C25: 272.97 | D25: 5000
B26: JUANI | C26: =334.3*1.1 -> 367.73 | D26: 5000
B27: JONA | C27: 341.17 | D27: 5000
B28: LUCA | C28: =232*1.1 -> 255.2 | D28: 5000
B29: GERMAN | C29: 230.18 | D29: 5000
B30: CORCHO | C30: 272.97 | D30: 5000
B31: ANDREA | C31: 400 | D31: 5000
B32: GABRIEL | C32: 310 | D32: 2500

Sheet RESUMEN0822 
B1: 44774
B3: DETALLE | C3: IMPORTE A COBRAR
B4: PILU | C4: 68700
B5: FACU | C5: 135700
B6: CHACO | C6: 77900
B7: JUANI | C7: 88700
B8: JONA | C8: 95900
B9: LUCA | C9: 52300
B10: GERMAN | C10: 68200
B11: CORCHO | C11: 76500
B12: ANDREA | C12: 65200
B13: GABRIEL | C13: 40800
B14: MAXI | C14: 59900
B15: TOTAL 08/2022 | C15: =SUM(C4:C14) -> 829800
B20: 44774
B21: , | C21: VALOR HORA | D21: PRESENTISMO
B22: PILU | C22: 400 | D22: 10000
B23: FACU | C23: 600 | D23: 10000
B24: CHACO | C24: 350 | D24: 10000
B25: JUANI | C25: 500 | D25: 10000
B26: JONA | C26: 500 | D26: 10000
B27: LUCA
B28: GERMAN | C28: 248.6 | D28: 5000
B29: CORCHO | C29: 295 | D29: 5000
B30: ANDREA | C30: 432 | D30: 5000
B31: GABRIEL | C31: 334.8 | D31: 2500
B32: MAXI | C32: 245 | D32: 5000

Sheet AGOSTO2022
B2: PILU
B3: DETALLE | C3: HS TRABAJADAS | D3: VALOR / HORA | E3: IMPORTE
B4: SUELDO | C4: 194 | D4: 400 | E4: =+C4*D4 -> 77600
B5: FERIADO | C5: 8 | D5: =+D4 -> 400 | E5: =+C5*D5 -> 3200
B6: Presentismo | E6: 10000
B7: HORA EXTRA x 50%
B8: NO REMUNERATIVO | C8: 16000 | E8: =+C8 -> 16000
B9: PREMIO P/LOZA(MODENA) | C9: 1 | D9: 3000 | E9: =+C9*D9 -> 3000
B10: PREMIO P/SAB.TRABAJADO
B11: TOTAL SUELDO | E11: =SUM(E4:E10) -> 109800
B12: DEPOSITO 07/2022 | E12: -41071.42
B14: TOTAL A COBRAR | E14: =+E11+E12+E13 -> 68728.58
B17: FACU
B18: DETALLE | C18: HS TRABAJADAS | D18: VALOR / HORA | E18: IMPORTE
B19: SUELDO | C19: 194 | D19: 600 | E19: =+C19*D19 -> 116400
B20: FERIADO | C20: 8 | D20: =+D19 -> 600 | E20: =+C20*D20 -> 4800
B21: Presentismo | E21: 10000
B22: EXTRA al 50%
B23: NO REMUNERATIVO | E23: 20000
B24: PREMIO P/SAB.TRABAJADO
B25: PREMIO P/LOZA | C25: 1 | D25: 3000 | E25: =+C25*D25 -> 3000
B26: TOTAL SUELDO | E26: =+E19+E20+E21+E23+E25 -> 154200
B27: SEGURO CLIO | E27: -1524
B28: ADELANTO | E28: -15000
B29: TOTAL A COBRAR | E29: =+E26+E27+E28 -> 137676
B32: HEINLEIN (CHACO)
B33: DETALLE | C33: HS TRABAJADAS | D33: VALOR / HORA | E33: IMPORTE
B34: SUELDO | C34: 194 | D34: 350 | E34: =C34*D34 -> 67900
B35: FERIADO | C35: 8 | D35: 350 | E35: =+C35*D35 -> 2800
B36: Presentismo | E36: 10000
B37: EXTRA al 50% | C37: 8 | D37: =+D34*1.5 -> 525 | E37: =C37*D37 -> 4200
B38: NO REMUNERATIVO | C38: 11000 | E38: =+C38 -> 11000
B39: PREMIO P/SAB.TRABAJADO | C39: 2 | D39: 1000 | E39: =+C39*D39 -> 2000
B40: TOTAL SUELDO | E40: =SUM(E34:E39) -> 97900
B41: ADELANTO | E41: -20000
B42: TOTAL A COBRAR | E42: =+E40+E41 -> 77900
B46: JUANI
B47: DETALLE | C47: HS TRABAJADAS | D47: VALOR / HORA | E47: IMPORTE
B48: SUELDO | C48: 194 | D48: 500 | E48: =C48*D48 -> 97000
B49: FERIADO | C49: 8 | D49: =+D48 -> 500 | E49: =C49*D49 -> 4000
B50: Presentismo | E50: 10000
B51: EXTRA al 50%
B52: NO REMUNERATIVO | C52: 16500 | E52: =+C52 -> 16500
B53: PREMIO P/SAB.TRABAJADO
B54: PREMIO P/LOZA(MODENA) | C54: 1 | D54: 3000 | E54: =+C54+D54 -> 3001
B55: TOTAL SUELDO | E55: =SUM(E48:E54) -> 130501
B56: DEPOSITO 07/2022 | E56: -41863.17
B57: TOTAL A COBRAR | E57: =SUM(E55:E56) -> 88637.83
B60: JONA
B61: DETALLE | C61: HS TRABAJADAS | D61: VALOR / HORA | E61: IMPORTE
B62: SUELDO | C62: 194 | D62: 500 | E62: =+C62*D62 -> 97000
B63: FERIADO | C63: 8 | D63: =+D62 -> 500 | E63: =+C63*D63 -> 4000
B64: PRESENTISMO | E64: 10000
B65: EXTRA al 50% | C65: 6 | D65: =+D62*1.5 -> 750 | E65: =+D65*C65 -> 4500
B66: NO REMUNERATIVO | C66: 16000 | E66: =+C66 -> 16000
B67: PREMIO P/SAB.TRABAJADO | C67: 1 | D67: 1000 | E67: =+C67*D67 -> 1000
B68: PREMIO P/LOZA(MODENA) | C68: 1 | D68: 3000 | E68: =+C68*D68 -> 3000
B69: TOTAL SUELDO | E69: =SUM(E62:E68) -> 135500
B70: DEPOSITO 07/2022 | E70: -39587.9
B71: TOTAL A COBRAR | E71: =SUM(E69:E70) -> 95912.1
B75: LUCA
B76: DETALLE | C76: HS TRABAJADAS | D76: VALOR / HORA | E76: IMPORTE
B77: SUELDO | C77: 194 | D77: 275.65 | E77: =C77*D77 -> 53476.1
B78: FERIADO | C78: 8 | D78: =+D77 -> 275.65 | E78: =C78*D78 -> 2205.2
B79: Presentismo | D79: 5000 | E79: 5000
B80: EXTRA al 50% | C80: 1.5 | D80: =+D77*1.5 -> 413.475 | E80: =+C80*D80 -> 620.2125
B81: NO REMUNERATIVO | C81: 11000 | E81: =+C81 -> 11000
B83: TOTAL SUELDO | E83: =SUM(E77:E82) -> 72301.512
B84: ADELANTO | E84: -20000
B85: TOTAL A COBRAR | E85: =+E83+E84 -> 52301.512
B97: SANDRONE(CORCHO)
B98: DETALLE | C98: HS TRABAJADAS | D98: VALOR / HORA | E98: IMPORTE
B99: SUELDO | C99: 194 | D99: 295 | E99: =+C99*D99 -> 57230
B100: FERIADO | C100: 8 | D100: 295 | E100: =+C100*D100 -> 2360
B101: Presentismo | E101: 5000
B102: EXTRA al 50% | C102: 2 | D102: =+D99*1.5 -> 442.5 | E102: =+C102*D102 -> 885
B103: NO REMUNERATIVO | E103: 11000
B104: PREMIO P/SAB.TRABAJADO
B105: TOTAL SUELDO | E105: =SUM(E99:E104) -> 76475
B109: CARLE GERMAN
B110: DETALLE | C110: HS TRABAJADAS | D110: VALOR / HORA | E110: IMPORTE
B111: SUELDO | C111: 194 | D111: 248.6 | E111: =C111*D111 -> 48228.4
B112: FERIADO | C112: 8 | D112: 248.6 | E112: =C112*D112 -> 1988.8
B113: Presentismo | E113: 5000
B114: EXTRA al 50% | C114: 8 | D114: =+D111*1.5 -> 372.9 | E114: =+D114*C114 -> 2983.2
B115: NO REMUNERATIVO | E115: 8000
B116: PREMIO P/SAB.TRABAJADO | C116: 2 | D116: 1000 | E116: =+C116*D116 -> 2000
B117: TOTAL SUELDO | E117: =SUM(E111:E116) -> 68200.4
B118: ADELANTO
B119: TOTAL A COBRAR | E119: =+E117+E118 -> 68200.4
B122: GABRIEL
B123: DETALLE | C123: HS TRABAJADAS | D123: VALOR / HORA | E123: IMPORTE
B124: HORAS TRABAJADAS | C124: 114.5 | D124: 334.8 | E124: =+C124*D124 -> 38334.6
B125: ADICIONAL P/MATERIALES | E125: 10000
B126: PRESENTISMO | E126: 2500
B127: ADELANTO | E127: -10000
B129: TOTAL A COBRAR | E129: =+E124+E125+E126+E127 -> 40834.6
B134: ANDREA
B135: DETALLE | C135: HS TRABAJADAS | D135: VALOR / HORA | E135: IMPORTE
B136: SUELDO | C136: 184 | D136: 432 | E136: =+C136*D136 -> 79488
...

Sheet SETIEMBRE2022
B2: PILU
B3: DETALLE | C3: HS TRABAJADAS | D3: VALOR / HORA | E3: IMPORTE
B4: SUELDO | C4: 184 | D4: 400 | E4: =+C4*D4 -> 73600
B5: FERIADO | C5: 8 | D5: =+D4 -> 400 | E5: =+C5*D5 -> 3200
B6: Presentismo | E6: 10000
B7: HORA EXTRA x 50% | C7: 8.5 | D7: =+D4*1.5 -> 600 | E7: =+C7*D7 -> 5100
B8: NO REMUNERATIVO | C8: 16000 | E8: =+C8 -> 16000
B9: PREMIO P/LOZA | C9: 1 | D9: 3000 | E9: =+C9*D9 -> 3000
B10: PREMIO P/SAB.TRABAJADO | C10: 1 | D10: 1000 | E10: =+C10*D10 -> 1000
B11: TOTAL SUELDO | E11: =SUM(E4:E10) -> 111900
B12: DEPOSITO 07/2022 | E12: -43576.78
B13: REGALO P/NACIMIENTO | E13: -560
B14: TOTAL A COBRAR | E14: =+E11+E12+E13 -> 67763.22
B17: FACU
B18: DETALLE | C18: HS TRABAJADAS | D18: VALOR / HORA | E18: IMPORTE
B19: SUELDO | C19: 184 | D19: 660 | E19: =+C19*D19 -> 121440
B20: FERIADO | C20: 8 | D20: =+D19 -> 660 | E20: =+C20*D20 -> 5280
B21: Presentismo | E21: 10000
B22: EXTRA al 50% | C22: 13 | D22: =+D20*1.5 -> 990 | E22: =+C22*D22 -> 12870
B23: NO REMUNERATIVO | E23: 20000
B24: PREMIO P/SAB.TRABAJADO | C24: 1 | D24: 1000 | E24: =+C24*D24 -> 1000
B25: PREMIO P/LOZA | C25: 3 | D25: 3000 | E25: =+C25*D25 -> 9000
B26: TOTAL SUELDO | E26: =+E19+E20+E21+E22+E23+E24+E25 -> 179590
B27: SEGURO CLIO | E27: -1540
B28: REGALO P/NACIMIENTO | E28: -560
B29: ADELANTO | E29: -15000
B30: TOTAL A COBRAR | E30: =+E26+E27+E28+E29 -> 162490
B33: HEINLEIN (CHACO)
B34: DETALLE | C34: HS TRABAJADAS | D34: VALOR / HORA | E34: IMPORTE
B35: SUELDO | C35: 184 | D35: 350 | E35: =C35*D35 -> 64400
B36: FERIADO | C36: 8 | D36: 350 | E36: =+C36*D36 -> 2800
B37: Presentismo | E37: 10000
B38: EXTRA al 50% | C38: 14 | D38: =+D35*1.5 -> 525 | E38: =C38*D38 -> 7350
B39: NO REMUNERATIVO | C39: 11000 | E39: =+C39 -> 11000
B41: PREMIO P/SAB.TRABAJADO | C41: 2 | D41: 1000 | E41: =+C41*D41 -> 2000
B42: TOTAL SUELDO | E42: =SUM(E35:E41) -> 97550
B43: ADELANTO | E43: -20000
B44: REGALO P/NACIMIENTO | E44: -560
B45: TOTAL A COBRAR | E45: =+E42+E43+E44 -> 76990
B49: JUANI
B50: DETALLE | C50: HS TRABAJADAS | D50: VALOR / HORA | E50: IMPORTE
B51: SUELDO | C51: 184 | D51: 500 | E51: =C51*D51 -> 92000
B52: FERIADO | C52: 8 | D52: =+D51 -> 500 | E52: =C52*D52 -> 4000
B53: Presentismo | E53: 10000
B54: EXTRA al 50% | C54: 6.5 | D54: =+D52*1.5 -> 750 | E54: =+C54*D54 -> 4875
B55: NO REMUNERATIVO | C55: 16500 | E55: =+C55 -> 16500
B56: PREMIO P/SAB.TRABAJADO | C56: 1 | D56: 1000 | E56: =+C56*D56 -> 1000
B57: PREMIO P/LOZA(MODENA) | C57: 2 | D57: 3000 | E57: =+C57*D57 -> 6000
B58: TOTAL SUELDO | E58: =SUM(E51:E57) -> 134375
B59: DEPOSITO 07/2022 | E59: -44416.71
B60: REGALO P/NACIMIENTO | E60: -560
C61: TOTAL A COBRAR | E61: =+E58+E59+E60 -> 89398.29
B64: JONA
B65: DETALLE | C65: HS TRABAJADAS | D65: VALOR / HORA | E65: IMPORTE
B66: SUELDO | C66: 184 | D66: 500 | E66: =+C66*D66 -> 92000
B67: FERIADO | C67: 8 | D67: =+D66 -> 500 | E67: =+C67*D67 -> 4000
B69: EXTRA al 50% | C69: 11 | D69: =+D66*1.5 -> 750 | E69: =+D69*C69 -> 8250
B70: NO REMUNERATIVO | C70: 16000 | E70: =+C70 -> 16000
B71: PREMIO P/SAB.TRABAJADO | C71: 1 | D71: 1000 | E71: =+C71*D71 -> 1000
B72: PREMIO P/LOZA(MODENA) | C72: 1 | D72: 3000 | E72: =+C72*D72 -> 3000
B73: TOTAL SUELDO | E73: =+E66+E67+E69+E70+E71+E72 -> 124250
B74: DEPOSITO 07/2022 | E74: -41996.9
B75: ADELANTO | E75: -20000
C76: TOTAL A COBRAR | E76: =+E73+E74+E75 -> 62253.1
B79: SANDRONE(CORCHO)
B80: DETALLE | C80: HS TRABAJADAS | D80: VALOR / HORA | E80: IMPORTE
B81: SUELDO | C81: 184 | D81: 295 | E81: =+C81*D81 -> 54280
B82: FERIADO | C82: 8 | D82: 295 | E82: =+C82*D82 -> 2360
B83: Presentismo | E83: 5000
B84: EXTRA al 50% | C84: 17.5 | D84: =+D81*1.5 -> 442.5 | E84: =+C84*D84 -> 7743.75
B85: NO REMUNERATIVO | E85: 11000
B86: PREMIO P/SAB.TRABAJADO | C86: 3 | D86: 1000 | E86: =+C86*D86 -> 3000
B87: TOTAL SUELDO | E87: =SUM(E81:E86) -> 83383.75
B88: REGALO P/NACIMIENTO | E88: -560
C89: TOTAL A COBRAR | E89: =+E87+E88 -> 82823.75
B106: CARLE GERMAN
B107: DETALLE | C107: HS TRABAJADAS | D107: VALOR / HORA | E107: IMPORTE
B108: SUELDO | C108: 184 | D108: 248.6 | E108: =C108*D108 -> 45742.4
B109: FERIADO | C109: 8 | D109: 248.6 | E109: =C109*D109 -> 1988.8
B110: Presentismo | E110: 5000
B111: EXTRA al 50% | C111: 11.5 | D111: =+D108*1.5 -> 372.9 | E111: =+D111*C111 -> 4288.35
B112: NO REMUNERATIVO | E112: 8000
B113: PREMIO P/SAB.TRABAJADO | C113: 2 | D113: 1000 | E113: =+C113*D113 -> 2000
B115: TOTAL SUELDO | E115: =SUM(E108:E113) -> 67019.55
B116: ADELANTO | E116: -20000
B117: REGALO P/NACIMIENTO | E117: -560
B119: TOTAL A COBRAR | E119: =+E115+E116+E117 -> 46459.55
B123: GABRIEL
B124: DETALLE | C124: HS TRABAJADAS | D124: VALOR / HORA | E124: IMPORTE
B125: HORAS TRABAJADAS | C125: 110 | D125: 334.8 | E125: =+C125*D125 -> 36828
B126: ADICIONAL P/MATERIALES | E126: 10000
B127: PRESENTISMO | E127: 2500
C128: TOTAL SUELDO | E128: =+E125+E126+E127 -> 49328
B129: ADELANTO | E129: -1000
B130: REGALO P/NACIMIENTO | E130: -560
B131: TOTAL A COBRAR | E131: =+E128+E129+E130 -> 47768
B134: ANDREA
B135: DETALLE | C135: HS TRABAJADAS | D135: VALOR / HORA | E135: IMPORTE
B136: SUELDO | C136: 159.5 | D136: 500 | E136: =+C136*D136 -> 79750
B137: FERIADO | C137: 8 | D137: 500 | E137: =+C137*D137 -> 4000
...

Sheet RESUMENSET2022
B1: SET2022
B3: DETALLE | C3: IMPORTE A COBRAR
B4: PILU | C4: 67763.22
B5: FACU | C5: 162490
B6: CHACO | C6: 76990
B7: JUANI | C7: 89398.29
B8: JONA | C8: 62253.1
B10: GERMAN | C10: 46459.55
B11: CORCHO | C11: 82823.75
B12: ANDREA | C12: 67190
B13: GABRIEL | C13: 47768
B14: MAXI | C14: 59501.25
B15: TOTAL 09/2022 | C15: =SUM(C4:C14) -> 762637.16
B20: SET2022
B21: , | C21: VALOR HORA | D21: PRESENTISMO
B22: PILU | C22: 400 | D22: 10000
B23: FACU | C23: 660 | D23: 10000
B24: CHACO | C24: 350 | D24: 10000
B25: JUANI | C25: 500 | D25: 10000
B26: JONA | C26: 500 | D26: 10000
B27: LUCA
B28: GERMAN | C28: 248.6 | D28: 5000
B29: CORCHO | C29: 295 | D29: 5000
B30: ANDREA | C30: 500 | D30: 5000
B31: GABRIEL | C31: 334.8 | D31: 2500
B32: MAXI | C32: 245 | D32: 5000
B35: DIAS | C35: HS | D35: MAR
B36: 16 | C36: 9 | D36: =+B36*C36 -> 144 | E36: LABORAL
B37: 5 | C37: 8 | D37: =+B37*C37 -> 40 | E37: VIERNES
B38: 1 | C38: 8 | D38: =+B38*C38 -> 8 | E38: FERIADO
B39: =+B36+B37+B38 -> 22 | D39: =+D36+D37+D38 -> 192 | E39: TOTAL

Sheet OCTUBRE2022
B2: PILU
B3: DETALLE | C3: HS TRABAJADAS | D3: VALOR / HORA | E3: IMPORTE
B4: SUELDO | C4: 168 | D4: 432 | E4: =+C4*D4 -> 72576
B5: FERIADO (2) | C5: 16 | D5: =+D4 -> 432 | E5: =+C5*D5 -> 6912
B6: Presentismo | E6: 10000
B7: HORA EXTRA x 50% | C7: 8.5 | D7: =+D4*1.5 -> 648 | E7: =+C7*D7 -> 5508
B8: NO REMUNERATIVO | C8: 16000 | E8: =+C8 -> 16000
B9: PREMIO P/LOZA | D9: 3000 | E9: =+C9*D9 -> 0
B10: PREMIO P/SAB.TRABAJADO | C10: 2 | D10: 1000 | E10: =+C10*D10 -> 2000
B11: TOTAL SUELDO | E11: =SUM(E4:E10) -> 112996
B12: DEPOSITO 07/2022 | E12: -46165.65
B13: TOTAL A COBRAR
B16: FACU
B17: DETALLE | C17: HS TRABAJADAS | D17: VALOR / HORA | E17: IMPORTE
B18: SUELDO | C18: 168 | D18: 660 | E18: =+C18*D18 -> 110880
B19: FERIADO (2) | C19: 16 | D19: =+D18 -> 660 | E19: =+C19*D19 -> 10560
B20: Presentismo | E20: 10000
B21: EXTRA al 50% | C21: 13.5 | D21: =+D19*1.5 -> 990 | E21: =+C21*D21 -> 13365
B22: NO REMUNERATIVO | E22: 20000
B23: PREMIO P/SAB.TRABAJADO | C23: 2 | D23: 1000 | E23: =+C23*D23 -> 2000
B24: PREMIO P/LOZA | D24: 3000 | E24: =+C24*D24 -> 0
B25: TOTAL SUELDO | E25: =+E18+E19+E20+E21+E22+E23+E24 -> 166805
B26: SEGURO CLIO | E26: -1540
B27: ADELANTO | E27: -25000
B28: TOTAL A COBRAR
B31: HEINLEIN (CHACO)
B32: DETALLE | C32: HS TRABAJADAS | D32: VALOR / HORA | E32: IMPORTE
B33: SUELDO | C33: 168 | D33: 380 | E33: =C33*D33 -> 63840
B34: FERIADO (2) | C34: 16 | D34: 380 | E34: =+C34*D34 -> 6080
B35: Presentismo | E35: 10000
B36: EXTRA al 50% | C36: 8.5 | D36: =+D33*1.5 -> 570 | E36: =C36*D36 -> 4845
B37: NO REMUNERATIVO | C37: 11000 | E37: =+C37 -> 11000
B39: PREMIO P/SAB.TRABAJADO | C39: 2 | D39: 1000 | E39: =+C39*D39 -> 2000
B40: TOTAL SUELDO | E40: =SUM(E33:E39) -> 97765
B41: ADELANTO | E41: -20000
B42: TOTAL A COBRAR | E42: =+E40+E41 -> 77765
B45: JUANI
B46: DETALLE | C46: HS TRABAJADAS | D46: VALOR / HORA | E46: IMPORTE
B47: SUELDO | C47: 168 | D47: 540 | E47: =C47*D47 -> 90720
B48: FERIADO (2) | C48: 16 | D48: =+D47 -> 540 | E48: =C48*D48 -> 8640
B49: Presentismo | E49: 10000
B50: EXTRA al 50% | C50: 12.5 | D50: =+D48*1.5 -> 810 | E50: =+C50*D50 -> 10125
B51: NO REMUNERATIVO | C51: 16500 | E51: =+C51 -> 16500
B52: PREMIO P/SAB.TRABAJADO | C52: 2 | D52: 1000 | E52: =+C52*D52 -> 2000
B53: PREMIO P/LOZA(MODENA) | D53: 3000 | E53: =+C53*D53 -> 0
B54: TOTAL SUELDO | E54: =SUM(E47:E53) -> 137985
B55: DEPOSITO 07/2022 | E55: -47500.23
C56: TOTAL A COBRAR
B59: JONA
B60: DETALLE | C60: HS TRABAJADAS | D60: VALOR / HORA | E60: IMPORTE
B61: SUELDO | C61: 168 | D61: 540 | E61: =+C61*D61 -> 90720
B62: FERIADO (2) | C62: 16 | D62: =+D61 -> 540 | E62: =+C62*D62 -> 8640
B63: Presentismo | E63: 10000
B64: EXTRA al 50% | C64: 11 | D64: =+D61*1.5 -> 810 | E64: =+D64*C64 -> 8910
B65: NO REMUNERATIVO | C65: 16000 | E65: =+C65 -> 16000
B66: PREMIO P/SAB.TRABAJADO | C66: 2 | D66: 1000 | E66: =+C66*D66 -> 2000
B67: PREMIO P/LOZA(MODENA) | D67: 3000 | E67: =+C67*D67 -> 0
B68: TOTAL SUELDO | E68: =+E61+E62+E63+E64+E65+E66+E67 -> 136270
B69: DEPOSITO 07/2022 | E69: -44931.06
B70: ADELANTO | E70: -10000
C71: TOTAL A COBRAR
B74: SANDRONE(CORCHO)
B75: DETALLE | C75: HS TRABAJADAS | D75: VALOR / HORA | E75: IMPORTE
B76: SUELDO | C76: 168 | D76: 320 | E76: =+C76*D76 -> 53760
B77: FERIADO (2) | C77: 16 | D77: 320 | E77: =+C77*D77 -> 5120
B78: Presentismo | E78: 5000
B79: EXTRA al 50% | C79: 7.5 | D79: =+D76*1.5 -> 480 | E79: =+C79*D79 -> 3600
B80: NO REMUNERATIVO | E80: 11000
B81: PREMIO P/SAB.TRABAJADO | C81: 1 | D81: 1000 | E81: =+C81*D81 -> 1000
B82: TOTAL SUELDO | E82: =SUM(E76:E81) -> 79480
C84: TOTAL A COBRAR | E84: 74598.75
B101: CARLE GERMAN
B102: DETALLE | C102: HS TRABAJADAS | D102: VALOR / HORA | E102: IMPORTE
B103: SUELDO | C103: 168 | D103: 290 | E103: =C103*D103 -> 48720
B104: FERIADO (2) | C104: 16 | D104: 290 | E104: =C104*D104 -> 4640
B105: Presentismo | E105: 5000
B106: EXTRA al 50% | C106: 11 | D106: =+D103*1.5 -> 435 | E106: =+D106*C106 -> 4785
B107: NO REMUNERATIVO | E107: 8000
B108: PREMIO P/SAB.TRABAJADO | C108: 2 | D108: 1000 | E108: =+C108*D108 -> 2000
B109: TOTAL SUELDO | E109: =SUM(E103:E108) -> 73145
B110: ADELANTO | E110: -5000
B111: PRESTAMO CUOTA 1 | E111: -15000
B112: TOTAL A COBRAR | E112: =+E109+E110+E111 -> 53145
B116: GABRIEL
B117: DETALLE | C117: HS TRABAJADAS | D117: VALOR / HORA | E117: IMPORTE
B118: HORAS TRABAJADAS | C118: 105 | D118: 365 | E118: =+C118*D118 -> 38325
B119: ADICIONAL P/MATERIALES | E119: 10000
B120: PRESENTISMO | E120: 2500
C121: TOTAL SUELDO | E121: =+E118+E119+E120 -> 50825
B122: ADELANTO
B123: TOTAL A COBRAR | E123: =+E118+E119+E120 -> 50825
B126: ANDREA
B127: DETALLE | C127: HS TRABAJADAS | D127: VALOR / HORA | E127: IMPORTE
B128: SUELDO | C128: 151 | D128: 540 | E128: =+C128*D128 -> 81540
B129: FERIADO | C129: 16 | D129: 540 | E129: =+C129*D129 -> 8640
B130: HORAS EXTRAS 50% | C130: 14 | D130: =+D128*1.5 -> 810 | E130: =+C130*D130 -> 11340
B131: PRESENTISMO | E131: 5000
B132: TOTAL SUELDO | E132: =SUM(E128:E131) -> 106520
B133: ADELANTO | E133: -22000
B134: TALADRO | E134: -8500
...

Sheet RES102022
B1: OCT2022
B3: DETALLE | C3: IMPORTE A COBRAR
B4: PILU
B5: FACU
B6: CHACO
B7: JUANI
B8: JONA
B10: GERMAN
B11: CORCHO
B12: ANDREA
B13: GABRIEL
B14: MAXI
B15: TOTAL 10/2022 | C15: =SUM(C4:C14) -> 0
B20: OCT2022
B21: , | C21: VALOR HORA | D21: PRESENTISMO
B22: PILU | C22: 432 | D22: 10000
B23: FACU | C23: 660 | D23: 10000
B24: CHACO | C24: 380 | D24: 10000
B25: JUANI | C25: 540 | D25: 10000
B26: JONA | C26: 540 | D26: 10000
B27: GERMAN | C27: 290 | D27: 5000
B28: CORCHO | C28: 320 | D28: 5000
B29: ANDREA | C29: 540 | D29: 5000
B30: GABRIEL | C30: 365 | D30: 2500
B31: MAXI | C31: 285 | D31: 5000
B34: DIAS | C34: HS | D34: MAR
B35: 16 | C35: 9 | D35: =+B35*C35 -> 144 | E35: LABORAL
B36: 3 | C36: 8 | D36: =+B36*C36 -> 24 | E36: VIERNES
B37: 2 | C37: 8 | D37: =+B37*C37 -> 16 | E37: FERIADO
B38: =+B35+B36+B37 -> 21 | D38: =+D35+D36+D37 -> 184 | E38: TOTAL

Sheet NOVIEMBRE2022
B2: PILU
B3: DETALLE | C3: HS TRABAJADAS | D3: VALOR / HORA | E3: IMPORTE
B4: SUELDO | C4: 185 | D4: 454 | E4: =+C4*D4 -> 83990
B5: FERIADO (1) | C5: 8 | D5: =+D4 -> 454 | E5: =+C5*D5 -> 3632
B6: Presentismo | E6: 10000
B7: HORA EXTRA x 50%
B8: NO REMUNERATIVO | C8: 16000 | E8: =+C8 -> 16000
B9: PREMIO P/LOZA | C9: 2 | D9: 1500 | E9: =+C9*D9 -> 3000
B10: PREMIO P/SAB.TRABAJADO
B11: TOTAL SUELDO | E11: =+E4+E5+E6+E8+E9 -> 116622
B12: DIA 22/11/2022(MUNDIAL) | C12: 1.5 | D12: 454 | E12: -681
B13: DEPOSITO 07/2022 | E13: -48754.52
B14: TOTAL A COBRAR | E14: =+E11+E12+E13 -> 67186.48
B17: FACU
B18: DETALLE | C18: HS TRABAJADAS | D18: VALOR / HORA | E18: IMPORTE
B19: SUELDO | C19: 185 | D19: 970 | E19: =+C19*D19 -> 179450
B20: FERIADO (1) | C20: 8 | D20: =+D19 -> 970 | E20: =+C20*D20 -> 7760
B21: Presentismo | E21: 10000
B22: EXTRA al 50% | C22: 4.5 | D22: =+D20*1.5 -> 1455 | E22: =+C22*D22 -> 6547.5
B23: NO REMUNERATIVO | E23: 20000
B24: PREMIO P/SAB.TRABAJADO
B25: PREMIO P/LOZA | C25: 3 | E25: 6000
B26: TOTAL SUELDO | E26: =+E19+E20+E21+E22+E23+E25 -> 229757.5
B27: DIA 22/11/22 (MUNDIAL) | C27: 1.5 | D27: 693 | E27: -1039.5
B28: SEGURO CLIO | E28: -1540
B29: ADELANTO
B30: TOTAL A COBRAR | E30: =+E26+E27+E28 -> 227178
B33: HEINLEIN (CHACO)
B34: DETALLE | C34: HS TRABAJADAS | D34: VALOR / HORA | E34: IMPORTE
B35: SUELDO | C35: 185 | D35: 399 | E35: =C35*D35 -> 73815
B36: FERIADO (1) | C36: 8 | D36: 399 | E36: =+C36*D36 -> 3192
B37: Presentismo | E37: 10000
B38: EXTRA al 50% | C38: 1.5 | D38: =+D35*1.5 -> 598.5 | E38: =C38*D38 -> 897.75
B39: NO REMUNERATIVO | C39: 11000 | E39: =+C39 -> 11000
B40: PREMIO P/SAB.TRABAJADO
B41: TOTAL SUELDO | E41: =+E35+E36+E37+E38+E39 -> 98904.75
B42: DIA 22/11/22 (MUNDIAL) | C42: 1.5 | D42: 399 | E42: -598.5
B43: ADELANTO | E43: -40000
B44: TOTAL A COBRAR | E44: =+E41+E42+E43 -> 58306.25
B47: JUANI
B48: DETALLE | C48: HS TRABAJADAS | D48: VALOR / HORA | E48: IMPORTE
B49: SUELDO | C49: 185 | D49: 567 | E49: =+C49*D49 -> 104895
B50: FERIADO (1) | C50: 8 | D50: =+D49 -> 567 | E50: =C50*D50 -> 4536
B51: Presentismo | E51: 10000
B52: EXTRA al 50% | C52: 4 | D52: =+D50*1.5 -> 850.5 | E52: =+C52*D52 -> 3402
B53: NO REMUNERATIVO | C53: 16500 | E53: =+C53 -> 16500
B54: PREMIO P/SAB.TRABAJADO
B55: PREMIO P/LOZA | C55: 3 | D55: 1500 | E55: =+C55*D55 -> 4500
B56: TOTAL SUELDO | E56: =+E49+E50+E51+E52+E53+E55 -> 143833
B57: DIA 22/11/22 (MUNDIAL) | C57: 1.5 | D57: 567 | E57: -850.5
B58: DEPOSITO 07/2022 | E58: -50163.79
C59: TOTAL A COBRAR | E59: =+E56+E57+E58 -> 92818.71
B62: JONA
B63: DETALLE | C63: HS TRABAJADAS | D63: VALOR / HORA | E63: IMPORTE
B64: SUELDO | C64: 185 | D64: 567 | E64: =+C64*D64 -> 104895
B65: FERIADO (1) | C65: 8 | D65: =+D64 -> 567 | E65: =+C65*D65 -> 4536
B66: Presentismo | E66: 10000
B67: EXTRA al 50% | C67: 5 | D67: =+D64*1.5 -> 850.5 | E67: =+D67*C67 -> 4252.5
B68: NO REMUNERATIVO | C68: 16000 | E68: =+C68 -> 16000
B69: PREMIO P/SAB.TRABAJADO
B70: PREMIO P/LOZA | C70: 3 | D70: 1500 | E70: =+C70*D70 -> 4500
B71: TOTAL SUELDO | E71: =+E64+E65+E66+E67+E68+E70 -> 144183.5
B72: DIA 22/11/22 (MUNDIAL) | C72: 1.5 | D72: 567 | E72: -850.5
B73: DEPOSITO 11/2022 | E73: -47445.26
B74: ADELANTO | E74: -21000
C75: TOTAL A COBRAR | E75: =+E71+E72+E73+E74 -> 74887.74
B78: SANDRONE(CORCHO)
B79: DETALLE | C79: HS TRABAJADAS | D79: VALOR / HORA | E79: IMPORTE
B80: SUELDO | C80: 185 | D80: 352 | E80: =+C80*D80 -> 65120
B81: FERIADO (1) | C81: 8 | D81: 352 | E81: =+C81*D81 -> 2816
B82: Presentismo | E82: 5000
B83: EXTRA al 50% | C83: 5 | D83: =+D80*1.5 -> 528 | E83: =+C83*D83 -> 2640
B84: NO REMUNERATIVO | E84: 11000
B85: PREMIO P/SAB.TRABAJADO
B86: TOTAL SUELDO | E86: =+E80+E81+E82+E83+E84 -> 86576
B87: DIA 22/12/22 (MUNDIAL) | C87: 1.5 | D87: 336 | E87: -504
B88: MUTUAL NOBIS DIF. | E88: -3960
C89: TOTAL A COBRAR | E89: =+E86+E87+E88 -> 82112
B105: CARLE GERMAN
B106: DETALLE | C106: HS TRABAJADAS | D106: VALOR / HORA | E106: IMPORTE
B107: SUELDO | C107: 185 | D107: 319 | E107: =C107*D107 -> 59015
B108: FERIADO (1) | C108: 8 | D108: 319 | E108: =C108*D108 -> 2552
B109: Presentismo | E109: 5000
B110: EXTRA al 50% | C110: 1.5 | D110: =+D107*1.5 -> 478.5 | E110: =+C110*D110 -> 717.75
B111: NO REMUNERATIVO | E111: 8000
B112: PREMIO P/SAB.TRABAJADO
B113: TOTAL SUELDO | E113: =+E107+E108+E109+E110+E111 -> 75284.75
B114: DIA 22/11/2022 (MUNDIAL) | C114: 1.5 | D114: 305 | E114: -457.5
B115: ADELANTO | E115: -5000
B116: PRESTAMO CUOTA 2 | C116: SALDO ANT.$85000-$10000=S.ACTUAL | E116: -10000
B117: TOTAL A COBRAR | E117: =+E113+E114+E115+E116 -> 59827.25
B121: GABRIEL
B122: DETALLE | C122: HS TRABAJADAS | D122: VALOR / HORA | E122: IMPORTE
B123: HORAS TRABAJADAS | C123: 108.5 | D123: 384 | E123: =+C123*D123 -> 41664
B124: ADICIONAL P/MATERIALES | E124: 10000
B125: PRESENTISMO | E125: 2500
C126: TOTAL SUELDO | E126: =+E123+E124+E125 -> 54164
B127: ADELANTO
B128: TOTAL A COBRAR | E128: 54164
B131: ANDREA
...

Sheet RES112022
B1: OCT2022
B3: DETALLE | C3: IMPORTE A COBRAR
B4: PILU | C4: 67200
B5: FACU | C5: 227200
B6: CHACO | C6: 58310
B7: JUANI | C7: 92820
B8: JONA | C8: 74900
B10: GERMAN | C10: 59830
B11: CORCHO | C11: 82110
B12: ANDREA | C12: 73700
B13: GABRIEL | C13: 54200
B14: MAXI | C14: 52520
B15: TOTAL 10/2022 | C15: =SUM(C4:C14) -> 842790
B20: NOV.2022
B21: , | C21: VALOR HORA | D21: PRESENTISMO
B22: PILU | C22: 454 | D22: 10000
B23: FACU | C23: 970 | D23: 10000
B24: CHACO | C24: 399 | D24: 10000
B25: JUANI | C25: 567 | D25: 10000
B26: JONA | C26: 567 | D26: 10000
B27: GERMAN | C27: 319 | D27: 5000
B28: CORCHO | C28: 352 | D28: 5000
B29: ANDREA | C29: 567 | D29: 5000
B30: GABRIEL | C30: 384 | D30: 2500
B31: MAXI | C31: 313 | D31: 5000
A34: DIAS | B34: HS | C34: MAR
A35: 17 | B35: 9 | C35: =+A35*B35 -> 153 | D35: LABORAL
A36: 4 | B36: 8 | C36: =+A36*B36 -> 32 | D36: VIERNES
A37: 1 | B37: 8 | C37: =+A37*B37 -> 8 | D37: FERIADO
A38: =+A35+A36+A37 -> 22 | C38: =+C35+C36+C37 -> 193 | D38: TOTAL

Sheet DICYSA22022
B2: PILU
B3: DETALLE | C3: HS TRABAJADAS | D3: VALOR / HORA | E3: IMPORTE
B4: SUELDO | C4: 132 | D4: 454 | E4: =+C4*D4 -> 59928
B5: FERIADO (2) | C5: 16 | D5: =+D4 -> 454 | E5: =+C5*D5 -> 7264
B6: Presentismo | E6: 10000
B7: HORA EXTRA 50% | C7: 7 | D7: =+D4*1.5 -> 681 | E7: =+C7*D7 -> 4767
B8: NO REMUNERATIVO | C8: 16000 | E8: =+C8 -> 16000
B9: PREMIO P/LOZA (FRE/RAF) | C9: 2 | D9: 1500 | E9: =+C9*D9 -> 3000
B10: PREMIO P/LOZA(BRI/MOD) | C10: 2 | D10: 3000 | E10: =+C10*D10 -> 6000
B11: SAC CTA2/2022 | E11: 59498
B12: VACACIONES(21D) | C12: 168 | D12: 454 | E12: =+C12*D12 -> 76272
B13: TOTAL SUELDO | E13: =+E4+E5+E6+E7+E8+E9+E10+E11+E12 -> 242729
B14: DEPOSITO P/BCO S/REC | E14: -56930.45
B15: DEPOSITO P/BCO S/REC(SAC) | E15: -24327.26
B16: TOTAL A COBRAR | E16: =+E13+E14+E15 -> 161471.29
B19: FACU
B20: DETALLE | C20: HS TRABAJADAS | D20: VALOR / HORA | E20: IMPORTE
B21: SUELDO | C21: 176 | D21: 970 | E21: =+C21*D21 -> 170720
B22: FERIADO (2) | C22: 16 | D22: =+D21 -> 970 | E22: =+C22*D22 -> 15520
B23: Presentismo | E23: 10000
B24: EXTRA al 50% | C24: 8 | D24: =+D22*1.5 -> 1455 | E24: =+C24*D24 -> 11640
B25: NO REMUNERATIVO | E25: 20000
B26: LOZAS(RAF/FREY) | C26: 2 | D26: 1500 | E26: =+C26*D26 -> 3000
B27: LOZAS(MOD/BRI/FREY) | C27: 3 | D27: 3000 | E27: =+C27*D27 -> 9000
B28: TOTAL SUELDO | E28: =+E21+E22+E23+E24+E25+E26+E27 -> 239880
B30: SEGURO CLIO | E30: -1540
B32: TOTAL A COBRAR | E32: =+E28+E30 -> 238340
B35: HEINLEIN (CHACO)-DIC22+SAC2/2022-
B36: DETALLE | C36: HS TRABAJADAS | D36: VALOR / HORA | E36: IMPORTE
B37: SUELDO | C37: 115 | D37: 399 | E37: =C37*D37 -> 45885
B38: FERIADO (2) | C38: 16 | D38: 399 | E38: =+C38*D38 -> 6384
B39: Presentismo | E39: 10000
B40: EXTRA al 50% | C40: 11 | D40: =+D37*1.5 -> 598.5 | E40: =C40*D40 -> 6583.5
B41: NO REMUNERATIVO | C41: 11000 | E41: =+C41 -> 11000
B42: VACACIONES 2022 | C42: 128 | D42: 399 | E42: =+C42*D42 -> 51072
B43: TOTAL SUELDO | E43: =+E37+E38+E39+E40+E41+E42 -> 130924.5
C44: SAC CTA2/2022 | E44: 49452.5
B45: TOTAL A COBRAR | E45: =+E43+E44 -> 180377
B48: JUANI
B49: DETALLE | C49: HS TRABAJADAS | D49: VALOR / HORA | E49: IMPORTE
B50: SUELDO | C50: 132 | D50: 567 | E50: =+C50*D50 -> 74844
B51: FERIADO (2) | C51: 16 | D51: =+D50 -> 567 | E51: =C51*D51 -> 9072
B52: Presentismo | E52: 10000
B53: EXTRA al 50% | C53: 7.5 | D53: =+D51*1.5 -> 850.5 | E53: =+C53*D53 -> 6378.75
B54: NO REMUNERATIVO | C54: 16500 | E54: =+C54 -> 16500
B55: PREMIO P/LOZA(RAF/FREY) | C55: 2 | D55: 1500 | E55: =+C55*D55 -> 3000
B56: PREMIO P/LOZA (BRI/MOD) | C56: 2 | D56: 3000 | E56: =+C56*D56 -> 6000
B57: VACACIONES(7D) | C57: 56 | D57: 567 | E57: =+C57*D57 -> 31752
B58: SAC 2da.CTA,2022 | E58: 73492.5
B59: TOTAL SUELDO | E59: =+E50+E51+E52+E53+E54+E55+E56+E57+E58 -> 231039.25
B60: DEPOSITO P/BCO S/REC | E60: -58335.71
B61: DEPOSITO P/BCO S/REC(SAC2/22) | E61: -25031.89
C62: TOTAL A COBRAR | E62: =+E59+E60+E61 -> 147671.65
B65: JONA
B66: DETALLE | C66: HS TRABAJADAS | D66: VALOR / HORA | E66: IMPORTE
B67: SUELDO | C67: 150 | D67: 567 | E67: =+C67*D67 -> 85050
B68: FERIADO (2) | C68: 16 | D68: =+D67 -> 567 | E68: =+C68*D68 -> 9072
B69: DIAS X ENFERMEDAD (3) | C69: 24 | D69: 567 | E69: =+C69*D69 -> 13608
B70: EXTRA al 50% | C70: 3 | D70: =+D67*1.5 -> 850.5 | E70: =+D70*C70 -> 2551.5
B71: NO REMUNERATIVO | C71: 16000 | E71: =+C71 -> 16000
B72: PREMIO P/LOZA | C72: 2 | D72: 3000 | E72: =+C72*D72 -> 6000
B73: VACACIONES (7D) | C73: 56 | D73: 567 | E73: =+C73*D73 -> 31752
B74: TOTAL SUELDO | E74: =+E67+E68+E69+E70+E71+E72+E73 -> 164033.5
B75: DEPOSITO 12/2022 | E75: -52587.71
C77: TOTAL A COBRAR | E77: =+E74+E75 -> 111445.79
B80: SANDRONE(CORCHO)
B81: DETALLE | C81: HS TRABAJADAS | D81: VALOR / HORA | E81: IMPORTE
B82: SUELDO | C82: 176 | D82: 352 | E82: =+C82*D82 -> 61952
B83: FERIADO (2) | C83: 16 | D83: 352 | E83: =+C83*D83 -> 5632
B84: Presentismo | E84: 5000
B85: EXTRA al 50% | C85: 9 | D85: =+D82*1.5 -> 528 | E85: =+C85*D85 -> 4752
B86: NO REMUNERATIVO | E86: 11000
B87: VACACIONES(7D) | C87: 56 | D87: 352 | E87: =+C87*D87 -> 19712
B88: TOTAL SUELDO | E88: =+E82+E83+E84+E85+E86+E87 -> 108048
B89: MUTUAL NOBIS DIF. | E89: -4334
C90: TOTAL A COBRAR | E90: =+E88+E89 -> 103714
B106: CARLE GERMAN
B107: DETALLE | C107: HS TRABAJADAS | D107: VALOR / HORA | E107: IMPORTE
B108: SUELDO | C108: 132 | D108: 319 | E108: =+E109+E110+E111+E112+E113+E114 -> 94583.75
B109: FERIADO (2) | C109: 16 | D109: 319 | E109: =C109*D109 -> 5104
B110: Presentismo | E110: 5000
B111: EXTRA al 50% | C111: 6.5 | D111: =+D108*1.5 -> 478.5 | E111: =+C111*D111 -> 3110.25
B112: NO REMUNERATIVO | E112: 8000
B113: SAC CTA,2/2022 | E113: 37641.5
B114: VACACIONES(14D) | C114: 112 | D114: 319 | E114: =+C114*D114 -> 35728
B115: TOTAL SUELDO | E115: =+E108+E109+E110+E111+E112+E113+E114 -> 189167.5
B116: PRESTAMO CUOTA 3 | C116: SALDO ANT.$75000-$10000=S.ACTUAL | E116: -10000
B117: TOTAL A COBRAR | E117: =+E115+E116 -> 179167.5
B121: GABRIEL
B122: DETALLE | C122: HS TRABAJADAS | D122: VALOR / HORA | E122: IMPORTE
B123: HORAS TRABAJADAS | C123: 90 | D123: 384 | E123: =+C123*D123 -> 34560
B124: ADICIONAL P/MATERIALES | E124: 10000
B125: FERIADO (2) | C125: 10 | D125: 384 | E125: =+C125*D125 -> 3840
B126: DIA P/ENFERMEDAD | C126: 5 | D126: 384 | E126: =+C126*D126 -> 1920
B127: DIA X VIAJE | C127: 5 | D127: 384 | E127: =+C127*D127 -> 1920
B128: VACACIONES (7D) | C128: 35 | D128: 384 | E128: =+C128*D128 -> 13440
B129: HORAS EXTRAS | C129: 1.2 | D129: =+D123*1.5 -> 576 | E129: =+C129*D129 -> 691.2
B130: TOTAL A COBRAR | E130: =+E123+E124+E125+E126+E127+E128+E129 -> 66371.2
B133: ANDREA
B134: DETALLE | C134: HS TRABAJADAS | D134: VALOR / HORA | E134: IMPORTE
...

Sheet RES122022
B1: OCT2022
B3: DETALLE | C3: IMPORTE A COBRAR
B4: PILU | C4: 67200
B5: FACU | C5: 227200
B6: CHACO | C6: 58310
B7: JUANI | C7: 92820
B8: JONA | C8: 74900
B10: GERMAN | C10: 59830
B11: CORCHO | C11: 82110
B12: ANDREA | C12: 73700
B13: GABRIEL | C13: 54200
B14: MAXI | C14: 52520
B15: TOTAL 10/2022 | C15: =SUM(C4:C14) -> 842790
B20: NOV.2022
B21: , | C21: VALOR HORA | D21: PRESENTISMO
B22: PILU | C22: 454 | D22: 10000
B23: FACU | C23: 970 | D23: 10000
B24: CHACO | C24: 399 | D24: 10000
B25: JUANI | C25: 567 | D25: 10000
B26: JONA | C26: 567 | D26: 10000
B27: GERMAN | C27: 319 | D27: 5000
B28: CORCHO | C28: 352 | D28: 5000
B29: ANDREA | C29: 567 | D29: 5000
B30: GABRIEL | C30: 384 | D30: 2500
B31: MAXI | C31: 313 | D31: 5000
B32: DAVID | C32: 352 | D32: 10000
A34: DIAS | B34: HS | C34: MAR
A35: 17 | B35: 9 | C35: =+A35*B35 -> 153 | D35: LABORAL
A36: 4 | B36: 8 | C36: =+A36*B36 -> 32 | D36: VIERNES
A37: 1 | B37: 8 | C37: =+A37*B37 -> 8 | D37: FERIADO
A38: =+A35+A36+A37 -> 22 | C38: =+C35+C36+C37 -> 193 | D38: TOTAL

Sheet ENERO2023
B2: PILU
B3: DETALLE | C3: HS TRABAJADAS | D3: VALOR / HORA | E3: IMPORTE
B4: SUELDO | C4: 106 | D4: 500 | E4: =+C4*D4 -> 53000
B5: FERIADO
B6: Presentismo | E6: 10000
B7: HORA EXTRA 50%
B8: NO REMUNERATIVO | C8: 20000 | E8: =+C8 -> 20000
B9: PREMIO P/LOZA (1) | C9: 1 | D9: 1500 | E9: =+C9*D9 -> 1500
B10: TOTAL SUELDO | E10: =+E4+E6+E8+E9 -> 84500
B11: DEPOSITO P/BCO S/REC | E11: -50826.26
B12: TOTAL A COBRAR | E12: =+E10+E11 -> 33673.74
B15: FACU
B16: DETALLE | C16: HS TRABAJADAS | D16: VALOR / HORA | E16: IMPORTE
B17: SUELDO | C17: 106 | D17: 1020 | E17: =+C17*D17 -> 108120 | F17: AUMENTO 5%
B18: FERIADO
B19: Presentismo | E19: 10000
B20: EXTRA al 50%
B21: NO REMUNERATIVO | E21: 20000
B22: LOZAS | C22: 1 | D22: 3000 | E22: =+C22*D22 -> 3000
B23: VACACIONES(14D) | C23: 112 | D23: 1020 | E23: =+D23*C23 -> 114240
B24: TOTAL SUELDO | E24: =+E17+E19+E21+E22+E23 -> 255360
B25: SEGURO CLIO | E25: -1540
B26: TOTAL A COBRAR | E26: =+E24+E25 -> 253820
B29: HEINLEIN (CHACO)
B30: DETALLE | C30: HS TRABAJADAS | D30: VALOR / HORA | E30: IMPORTE
B31: SUELDO | C31: 150 | D31: 440 | E31: =C31*D31 -> 66000
B32: FERIADO (2D) | C32: 16 | D32: 440 | E32: =+C32*D32 -> 7040
B33: Presentismo | E33: 10000
B34: EXTRA al 50% | C34: 9 | D34: =+D31*1.5 -> 660 | E34: =C34*D34 -> 5940
B35: NO REMUNERATIVO | C35: 15000 | E35: 15000
B36: TOTAL SUELDO | E36: =+E31+E32+E33+E34+E35 -> 103980
B37: ADELANTO | E37: -30000
B38: TOTAL A COBRAR | E38: =+E36+E37 -> 73980
B44: JONA
B45: DETALLE | C45: HS TRABAJADAS | D45: VALOR / HORA | E45: IMPORTE
B46: SUELDO | C46: 150 | D46: 625 | E46: =+C46*D46 -> 93750 | F46: AUMENTO 10%
B47: FERIADO
B48: PRESENTISMO | C48: 10000 | E48: 10000
B49: EXTRA al 50%
B50: NO REMUNERATIVO | C50: 20000 | E50: =+C50 -> 20000 | F50: AUMENTO
B51: PREMIO P/LOZA | C51: 1 | D51: 3000 | E51: =+C51*D51 -> 3000
B52: TOTAL SUELDO | E52: =+E46+E48+E50+E51 -> 126750
B53: DEPOSITO 12/2022 | E53: -48986.21
B54: ADELANTO 01/2023 | E54: -20000
C55: TOTAL A COBRAR | E55: =+E52+E53+E54 -> 57763.79
B58: SANDRONE(CORCHO)
B59: DETALLE | C59: HS TRABAJADAS | D59: VALOR / HORA | E59: IMPORTE
B60: SUELDO | C60: 150 | D60: 405 | E60: =+C60*D60 -> 60750 | F60: AUMENTO 15%
B61: FERIADO
B62: Presentismo | E62: 5000
B63: EXTRA al 50% | C63: 0.5 | D63: =+D60*1.5 -> 607.5 | E63: =+C63*D63 -> 303.75
B64: NO REMUNERATIVO | C64: 15000 | E64: 15000 | F64: AUMENTO
B66: TOTAL SUELDO | E66: =+E60+E62+E63+E64 -> 81053.75
C68: TOTAL A COBRAR | E68: 81053.75
B112: ANDREA
B113: DETALLE | C113: HS TRABAJADAS | D113: VALOR / HORA | E113: IMPORTE
B114: SUELDO | C114: 165 | D114: 624 | E114: =+C114*D114 -> 102960
B115: FERIADO
B116: HORAS EXTRAS 50%
B117: NO REMUNERATIVO | E117: 10000
B118: PRESENTISMO | E118: 10000
B119: TOTAL SUELDO | E119: =+E114+E117+E118 -> 122960
B120: ADELANTO | E120: -30000
B122: TOTAL A COBRAR | E122: =+E119+E120 -> 92960
B125: JUANI
B126: DETALLE | C126: HS TRABAJADAS | D126: VALOR / HORA | E126: IMPORTE
B127: SUELDO | C127: 194 | D127: 625 | E127: =+C127*D127 -> 121250 | F127: AUMENTO 10%
B128: FERIADO
B129: Presentismo | E129: 10000
B130: EXTRA al 50% | C130: 5.5 | D130: =+D127*1.5 -> 937.5 | E130: =+D130*C130 -> 5156.25
B131: NO REMUNERATIVO | C131: 20000 | E131: =+C131 -> 20000 | F131: AUMENTO
B132: PREMIO P/LOZA | C132: 1 | D132: 3000 | E132: =+C132*D132 -> 3000
B133: TOTAL SUELDO | E133: =+E127+E129+E130+E131+E132 -> 159406.25
B134: DEPOSITO P/BCO S/REC | E134: -51796.28
C135: TOTAL A COBRAR | E135: =+E133+E134 -> 107609.97
B155: MAXI ARAGON
B156: DETALLE | C156: HS TRABAJADAS | D156: VALOR / HORA | E156: IMPORTE
B157: SUELDO | C157: 194 | D157: 351 | E157: =+C157*D157 -> 68094
B158: FERIADO
B159: PRESENTISMO | E159: 5000
B160: EXTRA al 50% | C160: 1.5 | D160: =+D157*1.5 -> 526.5 | E160: =+C160*D160 -> 789.75
B161: NO REMUNERATIVO | C161: 10000 | E161: 10000
B163: TOTAL SUELDO | E163: =+E157+E159+E160+E161 -> 83883.75
B164: ADELANTO | E164: -25000
C166: TOTAL A COBRAR | E166: =+E163+E164 -> 58883.75
B170: DAVID
B171: DETALLE | C171: HS TRABAJADAS | D171: VALOR / HORA | E171: IMPORTE
B172: SUELDO | C172: 194 | D172: 405 | E172: =+C172*D172 -> 78570 | F172: AUMENTO 15%
B173: FERIADO
B174: Presentismo | E174: 5000
B175: EXTRA al 50% | C175: 5 | D175: =+D172*1.5 -> 607.5 | E175: =+C175*D175 -> 3037.5
B176: NO REMUNERATIVO | C176: 15000 | E176: 15000 | F176: AUMENTO
B177: ADICIONAL P/MATERIALES | E177: 20000
B178: TOTAL SUELDO | E178: =+E172+E174+E175+E176+E177 -> 121607.5
C180: TOTAL A COBRAR | E180: 121607.5

Sheet RESUMEN012023
B1: ENERO 2023
B3: DETALLE | C3: IMPORTE A COBRAR
B4: PILU | C4: 33700
B5: FACU | C5: 253820
B6: CHACO | C6: 52000
B7: JUANI | C7: 107610
B8: JONA | C8: 57800
B10: GERMAN | C10: 48700
B11: CORCHO | C11: 81100
B12: ANDREA | C12: 92960
B13: MAXI | C13: 58900
B14: DAVID | C14: 121610
B15: TOTAL 10/2022 | C15: =SUM(C4:C14) -> 908200
B20: ENE2023
B21: , | C21: VALOR HORA | D21: PRESENTISMO
B22: PILU | C22: 500 | D22: 10000
B23: FACU | C23: 1020 | D23: 10000
B24: CHACO | C24: 440 | D24: 10000
B25: JUANI | C25: 625 | D25: 10000
B26: JONA | C26: 625 | D26: 10000
B27: GERMAN | C27: 351 | D27: 5000
B28: CORCHO | C28: 405 | D28: 5000
B29: ANDREA | C29: 624 | D29: 10000
B30: MAXI | C30: 351 | D30: 5000
B31: DAVID | C31: 405 | D31: 5000
A33: DIAS | B33: HS | C33: MAR
A34: 18 | B34: 9 | C34: =+A34*B34 -> 162 | D34: LABORAL
A35: 4 | B35: 8 | C35: =+A35*B35 -> 32 | D35: VIERNES
D36: FERIADO
C37: =+C34+C35 -> 194 | D37: TOTAL

Sheet FEBRERO2023
B2: PILU
B3: DETALLE | C3: HS TRABAJADAS | D3: VALOR / HORA | E3: IMPORTE
B4: SUELDO | C4: 158 | D4: 500 | E4: =+C4*D4 -> 79000
B5: FERIADO (2D) | C5: 16 | D5: 500 | E5: =+C5*D5 -> 8000
B6: Presentismo | E6: 10000
B7: HORA EXTRA 50% | C7: 9 | D7: =+D4*1.5 -> 750 | E7: =+C7*D7 -> 6750
B8: NO REMUNERATIVO | C8: 20000 | E8: =+C8 -> 20000
B9: LOZA FREYRE(22/12/2022) | C9: 1 | D9: 1500 | E9: =+C9*D9 -> 1500
B10: PREMIO P/LOZA(RA-BR-FR-MO) | C10: 4 | D10: 1500 | E10: =+C10*D10 -> 6000
B11: TOTAL SUELDO | E11: =+E4+E5+E6+E7+E8+E9+E10 -> 131250
B12: DEPOSITO P/BCO. S/REC | E12: -64822.55
B13: CTA.PRESTAMO(10% S/SUELDO) | E13: -13125
B14: TOTAL A COBRAR | E14: =+E11+E12+E13 -> 53302.45
B17: FACU
B18: DETALLE | C18: HS TRABAJADAS | D18: VALOR / HORA | E18: IMPORTE
B19: SUELDO | C19: 158 | D19: 1020 | E19: =+C19*D19 -> 161160
B20: FERIADO (2) | C20: 16 | D20: 1020 | E20: =+C20*D20 -> 16320
B21: Presentismo | E21: 10000
B22: EXTRA al 50% | C22: 23.5 | D22: =+D19*1.5 -> 1530 | E22: =+C22*D22 -> 35955
B23: NO REMUNERATIVO | E23: 20000
B24: LOZAS(RA-BRI-FRE-MOD) | C24: 4 | D24: 3000 | E24: =+C24*D24 -> 12000
B25: TOTAL SUELDO | E25: =+E19+E20+E21+E22+E23+E24 -> 255435
B26: SEGURO CLIO | E26: -2490.44
B27: TOTAL A COBRAR | E27: =+E25+E26 -> 252944.56
B30: HEINLEIN (CHACO)
B31: DETALLE | C31: HS TRABAJADAS | D31: VALOR / HORA | E31: IMPORTE
B32: SUELDO | C32: 158 | D32: 440 | E32: =C32*D32 -> 69520
B33: FERIADO (2D) | C33: 16 | D33: 440 | E33: =+C33*D33 -> 7040
B34: Presentismo | E34: 10000
B35: EXTRA al 50% | C35: 9 | D35: =+D32*1.5 -> 660 | E35: =C35*D35 -> 5940
B36: NO REMUNERATIVO | C36: 15000 | E36: 15000
B37: TOTAL SUELDO | E37: =+E32+E33+E34+E35+E36 -> 107500
B38: ADELANTO | E38: -30000
B39: TOTAL A COBRAR | E39: =+E37+E38 -> 77500
B42: JUANI
B43: DETALLE | C43: HS TRABAJADAS | D43: VALOR / HORA | E43: IMPORTE
B44: SUELDO | C44: 158 | D44: 662.5 | E44: =+C44*D44 -> 104675
B45: FERIADO (2D) | C45: 16 | D45: 662.5 | E45: =+C45*D45 -> 10600
B46: Presentismo | E46: 10000
B47: EXTRA al 50% | C47: 10 | D47: =+D44*1.5 -> 993.75 | E47: =+D47*C47 -> 9937.5
B48: NO REMUNERATIVO | C48: 20000 | E48: =+C48 -> 20000
B49: LOZA FREYRE(22/12/2022) | C49: 1 | D49: 3000 | E49: 3000
B50: PREMIO P/LOZA(RA-BR-FR-MO) | C50: 4 | D50: 3000 | E50: =+C50*D50 -> 12000
B51: TOTAL SUELDO | E51: =+E44+E45+E46+E47+E48+E49+E50 -> 170212.5
B52: DEPOSITO P/BCO S/REC | E52: -66059.17
C53: TOTAL A COBRAR | E53: =+E51+E52 -> 104153.33
B57: JONA
B58: DETALLE | C58: HS TRABAJADAS | D58: VALOR / HORA | E58: IMPORTE
B59: SUELDO | C59: 158 | D59: 662.5 | E59: =+C59*D59 -> 104675
B60: FERIADO (2D) | C60: 16 | D60: 662.5 | E60: =+C60*D60 -> 10600
B61: PRESENTISMO | C61: 10000 | E61: 10000
B62: EXTRA al 50% | C62: 15 | D62: =+D59*1.5 -> 993.75 | E62: =+C62*D62 -> 14906.25
B63: NO REMUNERATIVO | C63: 20000 | E63: =+C63 -> 20000
B64: PREMIO P/LOZA(RA-BR-FR-MO) | C64: 4 | D64: 3000 | E64: =+C64*D64 -> 12000
B65: TOTAL SUELDO | E65: =+E59+E60+E61+E62+E63+E64 -> 172181.25
B66: DEPOSITO P/BCO | E66: -62449.31
B67: ADELANTO | E67: -30000
C68: TOTAL A COBRAR | E68: =+E65+E66+E67 -> 79731.94
B71: SANDRONE(CORCHO)
B72: DETALLE | C72: HS TRABAJADAS | D72: VALOR / HORA | E72: IMPORTE
B73: SUELDO | C73: 158 | D73: 405 | E73: =+C73*D73 -> 63990
B74: FERIADO (2D) | C74: 16 | D74: 405 | E74: =+C74*D74 -> 6480
B75: Presentismo | E75: 10000
B76: EXTRA al 50% | C76: 12.5 | D76: =+D73*1.5 -> 607.5 | E76: =+C76*D76 -> 7593.75
B77: NO REMUNERATIVO | C77: 15000 | E77: 15000
B79: TOTAL SUELDO | E79: =+E73+E74+E75+E76+E77 -> 103063.75
C81: TOTAL A COBRAR | E81: =+E73+E74+E75+E76+E77 -> 103063.75
B85: MAXI ARAGON
B86: DETALLE | C86: HS TRABAJADAS | D86: VALOR / HORA | E86: IMPORTE
B87: SUELDO | C87: 114 | D87: 351 | E87: =+C87*D87 -> 40014
B88: FERIADO (2D) | C88: 16 | D88: 351 | E88: =+C88*D88 -> 5616
B89: PRESENTISMO | E89: 10000
B90: EXTRA al 50% | C90: 3 | D90: =+D87*1.5 -> 526.5 | E90: =+C90*D90 -> 1579.5
B91: NO REMUNERATIVO | C91: 10000 | E91: 10000
B92: VACACIONES(6D) | C92: 48 | D92: 351 | E92: =+C92*D92 -> 16848
B93: TOTAL SUELDO | E93: =+E87+E88+E89+E90+E91+E92 -> 84057.5
B94: ADELANTO | E94: -10000
B95: ADELANTO P/VACACIONES | E95: -16848
C96: TOTAL A COBRAR | E96: =+E93+E94+E95 -> 57209.5
B100: DAVID
B101: DETALLE | C101: HS TRABAJADAS | D101: VALOR / HORA | E101: IMPORTE
B102: SUELDO | C102: 158 | D102: 405 | E102: =+C102*D102 -> 63990
B103: FERIADO (2) | C103: 16 | D103: 405 | E103: =+C103*D103 -> 6480
B104: Presentismo | E104: 10000
B105: EXTRA al 50% | C105: 11.5 | D105: =+D102*1.5 -> 607.5 | E105: =+C105*D105 -> 6986.25
B106: NO REMUNERATIVO | C106: 15000 | E106: 15000
B107: ADICIONAL P/MATERIALES | E107: 20000
B108: TOTAL SUELDO | E108: =+E102+E103+E104+E105+E106+E107 -> 122456.25
B109: ADELANTO | E109: -20000
C110: TOTAL A COBRAR | E110: =+E108+E109 -> 102456.25
B113: ANDREA
B114: DETALLE | C114: HS TRABAJADAS | D114: VALOR / HORA | E114: IMPORTE
B115: SUELDO | C115: 77 | D115: 624 | E115: =+C115*D115 -> 48048
B116: FERIADO(2D) | C116: 16 | D116: 624 | E116: =+C116*D116 -> 9984
B117: VACACIONES(14D) | C117: 98 | D117: 624 | E117: =+C117*D117 -> 61152
B118: NO REMUNERATIVO | E118: 10000
B119: PRESENTISMO | E119: 10000
B120: TOTAL SUELDO | E120: =+E115+E116+E117+E118+E119 -> 139184
B121: ADELANTO | E121: -35000
B123: TOTAL A COBRAR | E123: =+E120+E121 -> 104184
...

Sheet RESUMEN022023
B1: FEBRERO2023
B3: DETALLE | C3: IMPORTE A COBRAR
B4: PILU | C4: 53320
B5: FACU | C5: 252950
B6: CHACO | C6: 77500
B7: JUANI | C7: 104200
B8: JONA | C8: 79750
B9: IGNACIO | C9: 43530
B10: GERMAN | C10: 75450
B11: CORCHO | C11: 103100
B12: ANDREA | C12: 104200
B13: MAXI | C13: 57210
B14: DAVID | C14: 102500
B15: TOTAL 10/2022 | C15: =SUM(C4:C14) -> 1053710
B20: FEB2023
B21: , | C21: VALOR HORA | D21: PRESENTISMO
B22: PILU | C22: 500 | D22: 10000
B23: FACU | C23: 1020 | D23: 10000
B24: CHACO | C24: 440 | D24: 10000
B25: JUANI | C25: 625 | D25: 10000
B26: JONA | C26: 625 | D26: 10000
B27: GERMAN | C27: 351 | D27: 10000
B28: CORCHO | C28: 405 | D28: 10000
B29: ANDREA | C29: 624 | D29: 10000
B30: MAXI | C30: 351 | D30: 10000
B31: DAVID | C31: 405 | D31: 10000
A33: DIAS | B33: HS | C33: MAR
A34: 14 | B34: 9 | C34: =+A34*B34 -> 126 | D34: LABORAL
A35: 4 | B35: 8 | C35: =+A35*B35 -> 32 | D35: VIERNES
A36: 2 | B36: 8 | C36: 16 | D36: FERIADO
C37: =+C34+C35 -> 158 | D37: TOTAL

Sheet MARZO2023
B2: PILU
B3: DETALLE | C3: HS TRABAJADAS | D3: VALOR / HORA | E3: IMPORTE
B4: SUELDO | C4: 194 | D4: 530 | E4: =+C4*D4 -> 102820 | F4: 6% AUMENTO
B5: FERIADO (1D) | C5: 8 | D5: 530 | E5: =+C5*D5 -> 4240
B6: Presentismo | E6: 10000
B7: HORA EXTRA 50% | C7: 10 | D7: =+D4*1.5 -> 795 | E7: =+C7*D7 -> 7950
B8: NO REMUNERATIVO | C8: 20000 | E8: =+C8 -> 20000
B9: PREMIO P/LOZA(FR-MO) | C9: 2 | D9: 1500 | E9: =+C9*D9 -> 3000
B10: TOTAL SUELDO | E10: =+E4+E5+E6+E7+E8+E9 -> 148010
B11: DEPOSITO P/BCO. S/REC | E11: -66424.54
B12: CTA.2/38(PRESTAMO(10% S/SUELDO) | E12: -14801
B13: TOTAL A COBRAR | E13: =+E10+E11+E12 -> 66784.46
B16: FACU
B17: DETALLE | C17: HS TRABAJADAS | D17: VALOR / HORA | E17: IMPORTE
B18: SUELDO | C18: 194 | D18: 1085 | E18: =+C18*D18 -> 210490 | F18: 6% AUMENTO
B19: FERIADO (1D) | C19: 8 | D19: 1085 | E19: =+C19*D19 -> 8680
B20: Presentismo | E20: 10000
B21: EXTRA al 50% | C21: 15.5 | D21: =+D18*1.5 -> 1627.5 | E21: =+C21*D21 -> 25226.25
B22: NO REMUNERATIVO | E22: 20000
B23: LOZAS(FRE-MOD) | C23: 2 | D23: 3000 | E23: =+C23*D23 -> 6000
B24: TOTAL SUELDO | E24: =+E18+E19+E20+E21+E22+E23 -> 280396.25
B25: MUNIC.PAT.CLIO | E25: -6814
B26: SEGURO CLIO | E26: -2480
B27: TOTAL A COBRAR | E27: =+E24+E25+E26 -> 271102.25
B30: HEINLEIN (CHACO)
B31: DETALLE | C31: HS TRABAJADAS | D31: VALOR / HORA | E31: IMPORTE
B32: SUELDO | C32: 194 | D32: 470 | E32: =C32*D32 -> 91180 | F32: 6% AUMENTO
B33: FERIADO (1D) | C33: 8 | D33: 470 | E33: =+C33*D33 -> 3760
B34: Presentismo | E34: 10000
B35: EXTRA al 50% | C35: 17 | D35: =+D32*1.5 -> 705 | E35: =C35*D35 -> 11985
B36: NO REMUNERATIVO | C36: 15000 | E36: 15000
B37: PREMIO P/TRABAJO EN FREYRE | E37: 10000
B38: TOTAL SUELDO | E38: =+E32+E33+E34+E35+E36+E37 -> 141925
B39: ADELANTO | E39: -40000
B40: TOTAL A COBRAR | E40: =+E38+E39 -> 101925
B43: JUANI
B44: DETALLE | C44: HS TRABAJADAS | D44: VALOR / HORA | E44: IMPORTE
B45: SUELDO | C45: 194 | D45: 702.5 | E45: =+C45*D45 -> 136285 | F45: 6% AUMENTO
B46: FERIADO (1D) | C46: 8 | D46: 702.5 | E46: =+C46*D46 -> 5620
B47: Presentismo | E47: 10000
B48: EXTRA al 50% | C48: 11 | D48: =+D45*1.5 -> 1053.75 | E48: =+D48*C48 -> 11591.25
B49: NO REMUNERATIVO | C49: 20000 | E49: =+C49 -> 20000
B50: PREMIO P/LOZA(FR-MO) | C50: 2 | D50: 3000 | E50: =+C50*D50 -> 6000
B51: TOTAL SUELDO | E51: =+E45+E46+E47+E48+E49+E50 -> 189496.25
B52: DEPOSITO P/BCO S/REC | E52: -67691.67
C53: TOTAL A COBRAR | E53: =+E51+E52 -> 121804.58
B57: JONA
B58: DETALLE | C58: HS TRABAJADAS | D58: VALOR / HORA | E58: IMPORTE
B59: SUELDO | C59: 132 | D59: 662.5 | E59: =+C59*D59 -> 87450
B60: FERIADO (1D) | C60: 8 | D60: 662.5 | E60: =+C60*D60 -> 5300
B61: DIAS X ENFERMEDAD (7,5) | C61: 60 | D61: 662.5 | E61: =+C61*D61 -> 39750
B62: PRESENTISMO
B63: EXTRA al 50% | C63: 7.5 | D63: =+D59*1.5 -> 993.75 | E63: =+C63*D63 -> 7453.125
B64: NO REMUNERATIVO | C64: 20000 | E64: =+C64 -> 20000
B65: PREMIO P/LOZA (FRE) | C65: 1 | D65: 3000 | E65: =+C65*D65 -> 3000
B66: TOTAL SUELDO | E66: =+E59+E60+E61+E63+E64+E65 -> 162953.12
B67: DEPOSITO P/BCO | E67: -63990.27
C68: TOTAL A COBRAR | E68: =+E66+E67 -> 98962.855
B71: SANDRONE(CORCHO)
B72: DETALLE | C72: HS TRABAJADAS | D72: VALOR / HORA | E72: IMPORTE
B73: SUELDO | C73: 194 | D73: 430 | E73: =+C73*D73 -> 83420 | F73: 6% AUMENTO
B74: FERIADO (1D) | C74: 8 | D74: 430 | E74: =+C74*D74 -> 3440
B75: Presentismo | E75: 10000
B76: EXTRA al 50% | C76: 15.5 | D76: =+D73*1.5 -> 645 | E76: =+C76*D76 -> 9997.5
B77: NO REMUNERATIVO | C77: 15000 | E77: 15000
B79: TOTAL SUELDO | E79: =+E73+E74+E75+E76+E77 -> 121857.5
C81: TOTAL A COBRAR | E81: =+E73+E74+E75+E76+E77 -> 121857.5
B85: MAXI ARAGON
B86: DETALLE | C86: HS TRABAJADAS | D86: VALOR / HORA | E86: IMPORTE
B87: SUELDO | C87: 194 | D87: 375 | E87: =+C87*D87 -> 72750 | F87: 6% AUMENTO
B88: FERIADO (1D) | C88: 8 | D88: 375 | E88: =+C88*D88 -> 3000
B89: PRESENTISMO | E89: 10000
B90: EXTRA al 50% | C90: 20.5 | D90: =+D87*1.5 -> 562.5 | E90: =+C90*D90 -> 11531.25
B91: NO REMUNERATIVO | C91: 10000 | E91: 10000
B93: TOTAL SUELDO | E93: =+E87+E88+E89+E90+E91 -> 107281.25
B94: ADELANTO | E94: -15000
B95: CTA.1(PRESTAMO) | E95: -10000
C96: TOTAL A COBRAR | E96: =+E93+E94+E95 -> 82281.25
B100: DAVID
B101: DETALLE | C101: HS TRABAJADAS | D101: VALOR / HORA | E101: IMPORTE
B102: SUELDO | C102: 194 | D102: 430 | E102: =+C102*D102 -> 83420 | F102: 6% AUMENTO
B103: FERIADO (1D) | C103: 8 | D103: 430 | E103: =+C103*D103 -> 3440
B104: Presentismo | E104: 10000
B105: EXTRA al 50% | C105: 12 | D105: =+D102*1.5 -> 645 | E105: =+C105*D105 -> 7740
B106: NO REMUNERATIVO | C106: 15000 | E106: 15000
B107: ADICIONAL P/MATERIALES | E107: 20000
B108: TOTAL SUELDO | E108: =+E102+E103+E104+E105+E106+E107 -> 139600
B109: ADELANTO | E109: -20000
C110: TOTAL A COBRAR | E110: =+E108+E109 -> 119600
B113: ANDREA
B114: DETALLE | C114: HS TRABAJADAS | D114: VALOR / HORA | E114: IMPORTE
B115: SUELDO | C115: 173.5 | D115: 662 | E115: =+C115*D115 -> 114857 | F115: 6% AUMENTO
B116: FERIADO(1D) | C116: 8 | D116: 662 | E116: =+C116*D116 -> 5296
B117: NO REMUNERATIVO | E117: 10000
B118: PRESENTISMO | E118: 10000
B119: TOTAL SUELDO | E119: =+E115+E116+E117+E118 -> 140153
B120: ADELANTO 1-3 | E120: -30000
B122: TOTAL A COBRAR | E122: =+E119+E120 -> 110153
B125: CARLE GERMAN
B126: DETALLE | C126: HS TRABAJADAS | D126: VALOR / HORA | E126: IMPORTE
...

Sheet RESUMEN032023
B1: MARZO 2023
B3: DETALLE | C3: IMPORTE A COBRAR
A4: 1 | B4: PILU | C4: 66800
A5: 2 | B5: FACU | C5: 271100
A6: 3 | B6: CHACO | C6: 101925
A7: 4 | B7: JUANI | C7: 121810
A8: 5 | B8: JONA | C8: 99000
A9: 6 | B9: GERMAN | C9: 75800
A10: 7 | B10: CORCHO | C10: 121900
A11: 8 | B11: ANDREA | C11: 110200
A12: 9 | B12: MAXI | C12: 82300
A13: 10 | B13: DAVID | C13: 119600
A14: 11 | B14: JAVIER | C14: 79000
A15: 12 | B15: LEO | C15: 70300
B16: TOTAL 10/2022 | C16: =+C4+C5+C6+C7+C8+C9+C10+C11+C12+C13+C14+C15 -> 1319735
B21: MAR2023
B22: , | C22: VALOR HORA | D22: PRESENTISMO
B23: PILU | C23: 530 | D23: 10000
B24: FACU | C24: 1085 | D24: 10000
B25: CHACO | C25: 470 | D25: 10000
B26: JUANI | C26: 702.5 | D26: 10000
B27: JONA | C27: 662.5 | D27: 10000
B28: GERMAN | C28: 375 | D28: 10000
B29: CORCHO | C29: 430 | D29: 10000
B30: ANDREA | C30: 662 | D30: 10000
B31: MAXI | C31: 375 | D31: 10000
B32: DAVID | C32: 430 | D32: 10000
B33: JAVIER | C33: 500 | D33: 10000
B34: LEO | C34: 375 | D34: 10000
A37: DIAS | B37: HS | C37: MAR
A38: 18 | B38: 9 | C38: =+A38*B38 -> 162 | D38: LABORAL
A39: 4 | B39: 8 | C39: =+A39*B39 -> 32 | D39: VIERNES
A40: 1 | B40: 8 | C40: 8 | D40: FERIADO
C41: =+C38+C39+C40 -> 202 | D41: TOTAL

Sheet RESUMEN042023
B1: ABRIL 2023
B3: DETALLE | C3: IMPORTE A COBRAR
B4: PILU | C4: 62400
B5: FACU | C5: 258200
B6: CHACO | C6: 102800
B7: JUANI | C7: 120600
B8: JONA | C8: 64000
B9: GERMAN | C9: 82700
B10: CORCHO | C10: 121600
B11: ANDREA | C11: 95300
B12: MAXI | C12: 67600
B13: DAVID | C13: 113100
B14: JORGE | C14: 22700
B15: LEO | C15: 100000
B16: JAVIER | C16: 84500
B17: TOTAL 10/2022 | C17: =+C4+C5+C6+C7+C8+C9+C10+C11+C12+C13+C14+C15+C16 -> 1295500
B22: ABRIL 2023
B23: , | C23: VALOR HORA | D23: PRESENTISMO
B24: PILU | C24: 600 | D24: 10000
B25: FACU | C25: 1195 | D25: 10000
B26: CHACO | C26: 540 | D26: 10000
B27: JUANI | C27: 750 | D27: 10000
B28: JONA | C28: 662.5 | D28: 10000
B29: GERMAN | C29: 450 | D29: 10000
B30: CORCHO | C30: 520 | D30: 10000
B31: ANDREA | C31: 700 | D31: 10000
B32: MAXI | C32: 450 | D32: 10000
B33: DAVID | C33: 460 | D33: 10000
B34: JORGE | C34: 450 | D34: 10000
B35: LEO | C35: 450 | D35: 10000
B36: JAVIER | C36: 530 | D36: 10000
A38: DIAS | B38: HS | C38: MAR
A39: 16 | B39: 9 | C39: =+A39*B39 -> 144 | D39: LABORAL
A40: 3 | B40: 8 | C40: =+A40*B40 -> 24 | D40: VIERNES
A41: 1 | B41: 8 | C41: =+A41*B41 -> 8 | D41: FERIADO
C42: =+C39+C40+C41 -> 176 | D42: TOTAL

Sheet ABRIL2023
B2: PILU
B3: DETALLE | C3: HS TRABAJADAS | D3: VALOR / HORA | E3: IMPORTE
B4: SUELDO | C4: 168 | D4: 600 | E4: =+C4*D4 -> 100800 | F4: 13% AUMENTO
B5: FERIADO (1D) | C5: 8 | D5: 600 | E5: =+C5*D5 -> 4800
B6: Presentismo | E6: 10000
B7: HORA EXTRA 50% | C7: 5 | D7: =+D4*1.5 -> 900 | E7: =+C7*D7 -> 4500
B8: NO REMUNERATIVO | C8: 20000 | E8: =+C8 -> 20000
B9: PREMIO P/LOZA(BR-MO) | C9: 2 | D9: 1500 | E9: =+C9*D9 -> 3000
B10: TOTAL SUELDO | E10: =+E4+E5+E6+E7+E8+E9 -> 143100
B11: DEPOSITO P/BCO. S/REC | E11: -66424.54
B12: CTA.3/38(PRESTAMO(10% S/SUELDO) | E12: -14310
B13: TOTAL A COBRAR | E13: =+E10+E11+E12 -> 62365.46
B16: FACU
B17: DETALLE | C17: HS TRABAJADAS | D17: VALOR / HORA | E17: IMPORTE
B18: SUELDO | C18: 168 | D18: 1195 | E18: =+C18*D18 -> 200760 | F18: 10% AUMENTO
B19: FERIADO (1D) | C19: 8 | D19: 1195 | E19: =+C19*D19 -> 9560
B20: Presentismo | E20: 10000
B21: EXTRA al 50% | C21: 8 | D21: =+D18*1.5 -> 1792.5 | E21: =+C21*D21 -> 14340
B22: NO REMUNERATIVO | E22: 20000
B23: LOZAS(BRI-MOD) | C23: 2 | D23: 3000 | E23: =+C23*D23 -> 6000
B24: TOTAL SUELDO | E24: =+E18+E19+E20+E21+E22+E23 -> 260660
B25: SEGURO CLIO | E25: -2480
B26: TOTAL A COBRAR | E26: =+E24+E25 -> 258180
B29: HEINLEIN (CHACO)
B30: DETALLE | C30: HS TRABAJADAS | D30: VALOR / HORA | E30: IMPORTE
B31: SUELDO | C31: 168 | D31: 540 | E31: =C31*D31 -> 90720 | F31: 15% AUMENTO
B32: FERIADO (1D) | C32: 8 | D32: 540 | E32: =+C32*D32 -> 4320
B33: Presentismo | E33: 10000
B34: EXTRA al 50% | C34: 9.5 | D34: =+D31*1.5 -> 810 | E34: =C34*D34 -> 7695
B35: NO REMUNERATIVO | C35: 20000 | E35: 20000
B36: PREMIO P/OBRA EN RAF/FRE | E36: 10000
B37: TOTAL SUELDO | E37: =+E31+E32+E33+E34+E35+E36 -> 142735
B38: ADELANTO | E38: -40000
B39: TOTAL A COBRAR | E39: =+E37+E38 -> 102735
B42: JUANI
B43: DETALLE | C43: HS TRABAJADAS | D43: VALOR / HORA | E43: IMPORTE
B44: SUELDO | C44: 80 | D44: 750 | E44: =+C44*D44 -> 60000 | F44: 6% AUMENTO
B45: FERIADO (1D) | C45: 8 | D45: 750 | E45: =+C45*D45 -> 6000
B46: VACACIONES(14D) | C46: 112 | D46: 750 | E46: =+C46*D46 -> 84000
B47: Presentismo | E47: 10000
B48: EXTRA al 50% | C48: 2 | D48: =+D44*1.5 -> 1125 | E48: =+D48*C48 -> 2250
B49: NO REMUNERATIVO | C49: 20000 | E49: =+C49 -> 20000
B50: PREMIO P/LOZA(BRI-MO) | C50: 2 | D50: 3000 | E50: =+C50*D50 -> 6000
B51: TOTAL SUELDO | E51: =+E44+E45+E46+E47+E48+E49+E50 -> 188250
B52: DEPOSITO P/BCO S/REC | E52: -67691.67
C53: TOTAL A COBRAR | E53: =+E51+E52 -> 120558.33
B57: JONA
B58: DETALLE | C58: HS TRABAJADAS | D58: VALOR / HORA | E58: IMPORTE
B59: SUELDO | C59: 172 | D59: 662.5 | E59: =+C59*D59 -> 113950
B60: FERIADO (1D) | C60: 8 | D60: 662.5 | E60: =+C60*D60 -> 5300
B61: PRESENTISMO
B62: EXTRA al 50%
B63: NO REMUNERATIVO | E63: 10000
B64: PREMIO P/LOZA | C64: 1
B65: TOTAL SUELDO | E65: =+E59+E60+E63 -> 129250
B66: DEPOSITO P/BCO | E66: -63990.27
C67: TOTAL A COBRAR | E67: =+E65+E66 -> 65259.73
B70: SANDRONE(CORCHO)
B71: DETALLE | C71: HS TRABAJADAS | D71: VALOR / HORA | E71: IMPORTE
B72: SUELDO | C72: 168 | D72: 520 | E72: =+C72*D72 -> 87360 | F72: 20% AUMENTO
B73: FERIADO (1D) | C73: 8 | D73: 520 | E73: =+C73*D73 -> 4160
B74: Presentismo | E74: 10000
B75: EXTRA al 50% | C75: 6.5 | D75: =+D72*1.5 -> 780 | E75: =+C75*D75 -> 5070
B76: NO REMUNERATIVO | C76: 15000 | E76: 15000
B78: TOTAL SUELDO | E78: =+E72+E73+E74+E75+E76 -> 121590
C80: TOTAL A COBRAR | E80: =+E72+E73+E74+E75+E76 -> 121590
B84: MAXI ARAGON
B85: DETALLE | C85: HS TRABAJADAS | D85: VALOR / HORA | E85: IMPORTE
B86: SUELDO | C86: 168 | D86: 450 | E86: =+C86*D86 -> 75600 | F86: 20% AUMENTO
B87: FERIADO (1D) | C87: 8 | D87: 450 | E87: =+C87*D87 -> 3600
B88: PRESENTISMO | E88: 10000
B89: EXTRA al 50% | C89: 5 | D89: =+D86*1.5 -> 675 | E89: =+C89*D89 -> 3375
B90: NO REMUNERATIVO | C90: 15000 | E90: 15000
B92: TOTAL SUELDO | E92: =+E86+E87+E88+E89+E90 -> 107575
B93: ADELANTO | E93: -30000
B94: CTA.2(PRESTAMO) | E94: -10000
C95: TOTAL A COBRAR | E95: =+E92+E93+E94 -> 67575
B99: DAVID
B100: DETALLE | C100: HS TRABAJADAS | D100: VALOR / HORA | E100: IMPORTE
B101: SUELDO | C101: 168 | D101: 460 | E101: =+C101*D101 -> 77280 | F101: 6% AUMENTO
B102: FERIADO (1D) | C102: 8 | D102: 460 | E102: =+C102*D102 -> 3680
B103: Presentismo | E103: 10000
B104: EXTRA al 50% | C104: 17.5 | D104: =+D101*1.5 -> 690 | E104: =+C104*D104 -> 12075
B105: NO REMUNERATIVO | C105: 15000 | E105: 15000
B106: ADICIONAL P/MATERIALES | E106: 35000
B107: TOTAL SUELDO | E107: =+E101+E102+E103+E104+E105+E106 -> 153035
B108: ADELANTO | E108: -40000
C109: TOTAL A COBRAR | E109: =+E107+E108 -> 113035
B112: ANDREA
B113: DETALLE | C113: HS TRABAJADAS | D113: VALOR / HORA | E113: IMPORTE
B114: SUELDO | C114: 149.5 | D114: 700 | E114: =+C114*D114 -> 104650 | F114: 6% AUMENTO
B115: FERIADO(1D) | C115: 8 | D115: 700 | E115: =+C115*D115 -> 5600
B116: NO REMUNERATIVO | E116: 15000
B117: PRESENTISMO | E117: 10000
B118: TOTAL SUELDO | E118: =+E114+E115+E116+E117 -> 135250
B119: ADELANTO 1-3 | E119: -40000
B121: TOTAL A COBRAR | E121: =+E118+E119 -> 95250
B124: CARLE GERMAN
B125: DETALLE | C125: HS TRABAJADAS | D125: VALOR / HORA | E125: IMPORTE
B126: SUELDO | C126: 168 | D126: 450 | E126: =+D126*C126 -> 75600 | F126: 20% AUMENTO
...

Sheet RESUMEN0523
B1: MAYO 2023
B3: PILU | C3: 72500
B4: FACU | C4: 295800
B5: CHACO | C5: 126100
B6: JUANI | C6: 133300
B7: JONA | C7: 69200
B8: GERMAN | C8: 95600
B9: CORCHO | C9: 143200
B10: ANDREA | C10: 70300
B11: MAXI | C11: 67500
B12: DAVID | C12: 93700
B13: JORGE | C13: 72500
B14: LEO | C14: 129300
... B17: GALLO | C17: 13600
B18: TOTAL 10/2022 | C18: =+C3+C4+C5+C6+C7+C8+C9+C10+C11+C12+C13+C14+C15+C16+C17 -> 1603940
B23: MAYO2023
B24: , | C24: VALOR HORA | D24: PRESENTISMO
B25: PILU | C25: 600 | D25: 10000
B26: FACU | C26: 1195 | D26: 10000
B27: CHACO | C27: 540 | D27: 10000
B28: JUANI | C28: 750 | D28: 10000
B29: JONA | C29: 662.5 | D29: 10000
B30: GERMAN | C30: 450 | D30: 10000
B31: CORCHO | C31: 520 | D31: 10000
B32: ANDREA | C32: 700 | D32: 10000
B33: MAXI | C33: 450 | D33: 10000
B34: DAVID | C34: 460 | D34: 10000
B35: JORGE | C35: 450 | D35: 10000
B36: LEO | C36: 450 | D36: 10000
... B39: GALLO | C39: 600 | D39: 10000
A42: DIAS | B42: HS | C42: MAR
A43: 17 | B43: 9 | C43: =+A43*B43 -> 153 | D43: LABORAL
A44: 3 | B44: 8 | C44: =+A44*B44 -> 24 | D44: VIERNES
A45: 3 | B45: 8 | C45: =+A45*B45 -> 24 | D45: FERIADO
C46: =+C43+C44+C45 -> 201 | D46: TOTAL

Sheet MAYO2023
B2: PILU
B3: DETALLE | C3: HS TRABAJADAS | D3: VALOR / HORA | E3: IMPORTE
B4: SUELDO | C4: 177 | D4: 660 | E4: =+C4*D4 -> 116820 | F4: AUMENTO 10%
B5: FERIADO (3D) | C5: 24 | D5: 660 | E5: =+C5*D5 -> 15840
B6: Presentismo | E6: 10000
B7: HORA EXTRA 50% | C7: 2.5 | D7: =+D4*1.5 -> 990 | E7: =+C7*D7 -> 2475
B8: NO REMUNERATIVO | C8: 20000 | E8: =+C8 -> 20000
B9: PREMIO P/LOZA(BR) | C9: 1 | D9: 1500 | E9: =+C9*D9 -> 1500
B10: TOTAL SUELDO | E10: =+E4+E5+E6+E7+E8+E9 -> 166635
B11: DEPOSITO P/BCO. S/REC | E11: -66424.54
B12: CTA.4/38(PRESTAMO(10% S/SUELDO) | E12: -16663.5
B13: TOTAL A COBRAR | E13: =+E10+E11+E12 -> 83546.96
B16: FACU
B17: DETALLE | C17: HS TRABAJADAS | D17: VALOR / HORA | E17: IMPORTE
B18: SUELDO | C18: 177 | D18: 1195 | E18: =+C18*D18 -> 211515
B19: FERIADO (3D) | C19: 24 | D19: 1195 | E19: =+C19*D19 -> 28680
B20: Presentismo | E20: 10000
B21: EXTRA al 50% | C21: 10 | D21: =+D18*1.5 -> 1792.5 | E21: =+C21*D21 -> 17925
B22: EXTRAS AL 100% | C22: 3 | D22: =+D18*2 -> 2390 | E22: =+C22*D22 -> 7170
B23: NO REMUNERATIVO | E23: 20000
B24: LOZAS(BRI) | C24: 1 | D24: 3000 | E24: =+C24*D24 -> 3000
B25: TOTAL SUELDO | E25: =+E18+E19+E20+E21+E22+E23+E24 -> 298290
B26: SEGURO CLIO | E26: -2480
B27: TOTAL A COBRAR | E27: =+E25+E26 -> 295810
B30: HEINLEIN (CHACO)
B31: DETALLE | C31: HS TRABAJADAS | D31: VALOR / HORA | E31: IMPORTE
B32: SUELDO | C32: 177 | D32: 540 | E32: =C32*D32 -> 95580
B33: FERIADO (3D) | C33: 24 | D33: 540 | E33: =+C33*D33 -> 12960
B34: Presentismo | E34: 10000
B35: EXTRA al 50% | C35: 15.5 | D35: =+D32*1.5 -> 810 | E35: =C35*D35 -> 12555
B36: NO REMUNERATIVO | C36: 20000 | E36: 20000
B37: PREMIO P/OBRA EN RAF/FRE | E37: 15000
B38: TOTAL SUELDO | E38: =+E32+E33+E34+E35+E36+E37 -> 166095
B39: ADELANTO | E39: -40000
B40: TOTAL A COBRAR | E40: =+E38+E39 -> 126095
B43: JUANI
B44: DETALLE | C44: HS TRABAJADAS | D44: VALOR / HORA | E44: IMPORTE
B45: SUELDO | C45: 177 | D45: 750 | E45: =+C45*D45 -> 132750
B46: FERIADO (3D) | C46: 24 | D46: 750 | E46: =+C46*D46 -> 18000
B47: Presentismo | E47: 10000
B48: EXTRA al 50% | C48: 10 | D48: =+D45*1.5 -> 1125 | E48: =+D48*C48 -> 11250
B49: EXTRAS AL 100% | C49: 4 | D49: =+D45*2 -> 1500 | E49: =+C49*D49 -> 6000
B50: NO REMUNERATIVO | C50: 20000 | E50: =+C50 -> 20000
B51: PREMIO P/LOZA(BRI) | C51: 1 | D51: 3000 | E51: =+C51*D51 -> 3000
B52: TOTAL SUELDO | E52: =+E45+E46+E47+E48+E49+E50+E51 -> 201000
B53: DEPOSITO P/BCO S/REC | E53: -67691.67
C54: TOTAL A COBRAR | E54: =+E52+E53 -> 133308.33
B58: JONA
B59: DETALLE | C59: HS TRABAJADAS | D59: VALOR / HORA | E59: IMPORTE
B60: SUELDO | C60: 177 | D60: 662.5 | E60: =+C60*D60 -> 117262.5
B61: FERIADO (3D) | C61: 24 | D61: 662.5 | E61: =+C61*D61 -> 15900
B62: PRESENTISMO
B63: EXTRA al 50%
B64: NO REMUNERATIVO
B65: PREMIO P/LOZA | C65: 1
B66: TOTAL SUELDO | E66: =+E60+E61 -> 133162.5
B67: DEPOSITO P/BCO | E67: -63990.27
C68: TOTAL A COBRAR | E68: =+E66+E67 -> 69172.23
B71: SANDRONE(CORCHO)
B72: DETALLE | C72: HS TRABAJADAS | D72: VALOR / HORA | E72: IMPORTE
B73: SUELDO | C73: 177 | D73: 520 | E73: =+C73*D73 -> 92040
B74: FERIADO (3D) | C74: 24 | D74: 520 | E74: =+C74*D74 -> 12480
B75: Presentismo | E75: 10000
B76: EXTRA al 50% | C76: 13.5 | D76: =+D73*1.5 -> 780 | E76: =+C76*D76 -> 10530
B77: EXTRAS AL 100% | C77: 3 | D77: =+D73*2 -> 1040 | E77: =+C77*D77 -> 3120
B78: NO REMUNERATIVO | C78: 15000 | E78: 15000
B80: TOTAL SUELDO | E80: =+E73+E74+E75+E76+E77+E78 -> 143170
C82: TOTAL A COBRAR | E82: =+E73+E74+E75+E76+E77+E78 -> 143170
B86: MAXI ARAGON
B87: DETALLE | C87: HS TRABAJADAS | D87: VALOR / HORA | E87: IMPORTE
B88: SUELDO | C88: 177 | D88: 450 | E88: =+C88*D88 -> 79650
B89: FERIADO (3D) | C89: 24 | D89: 450 | E89: =+C89*D89 -> 10800
B90: PRESENTISMO | E90: 10000
B91: EXTRA al 50% | C91: 3 | D91: =+D88*1.5 -> 675 | E91: =+C91*D91 -> 2025
B92: NO REMUNERATIVO | C92: 15000 | E92: 15000
B94: TOTAL SUELDO | E94: =+E88+E89+E90+E91+E92 -> 117475
B95: ADELANTO | E95: -40000
B96: CTA.3(PRESTAMO) | E96: -10000
C97: TOTAL A COBRAR | E97: =+E94+E95+E96 -> 67475
B101: DAVID
B102: DETALLE | C102: HS TRABAJADAS | D102: VALOR / HORA | E102: IMPORTE
B103: SUELDO | C103: 177 | D103: 460 | E103: =+C103*D103 -> 81420
B104: FERIADO (3D) | C104: 24 | D104: 460 | E104: =+C104*D104 -> 11040
B105: Presentismo | E105: 10000
B106: EXTRA al 50% | C106: 9 | D106: =+D103*1.5 -> 690 | E106: =+C106*D106 -> 6210
B107: NO REMUNERATIVO | C107: 15000 | E107: 15000
B108: ADICIONAL P/MATERIALES | E108: 20000
B109: TOTAL SUELDO | E109: =+E103+E104+E105+E106+E107+E108 -> 143670
B110: ADELANTO | E110: -50000
C111: TOTAL A COBRAR | E111: =+E109+E110 -> 93670
B114: ANDREA
B115: DETALLE | C115: HS TRABAJADAS | D115: VALOR / HORA | E115: IMPORTE
B116: SUELDO | C116: 148 | D116: 700 | E116: =+C116*D116 -> 103600
B117: FERIADO(3D) | C117: 21 | D117: 700 | E117: =+C117*D117 -> 14700
B118: NO REMUNERATIVO | E118: 15000
B119: PRESENTISMO | E119: 10000
B120: TOTAL SUELDO | E120: =+E116+E117+E118+E119 -> 143300
B121: ADELANTO | E121: -40000
B122: CTA.2/3 | E122: -33000
B123: TOTAL A COBRAR | E123: =+E120+E121+E122 -> 70300
...

Sheet Hoja1
B2: 45078
B5: GALLO LEANDRO
B6: DETALLE | C6: HS.TRABAJADAS | D6: VALOR HORA | E6: IMPORTE
B7: SUELDO | C7: 88 | D7: 600 | E7: =+C7*D7 -> 52800
B8: FERIADO
B9: HORAS EXTRAS
B11: PRESENTISMO (PROP) | E11: 5000
B12: SUB-TOTAL | E12: =+E7+E11 -> 57800
B14: TOTAL A COBRAR | E14: 57800

Sheet JUNIOYSAC1
B1: PILU
B2: DETALLE | C2: HS TRABAJADAS | D2: VALOR / HORA | E2: IMPORTE
B3: SUELDO* | C3: 171 | D3: 660 | E3: =+C3*D3 -> 112860
B4: FERIADO (2,5D)* | C4: 20 | D4: 660 | E4: =+C4*D4 -> 13200
B5: Presentismo* | E5: 10000
B6: HORAS EXTRAS 50% | C6: 4 | D6: =+D3*1.5 -> 990 | E6: =+C6*D6 -> 3960
B7: HORAS EXTRAS AL 100% | C7: 11 | D7: =+D3*2 -> 1320 | E7: =+C7*D7 -> 14520
B8: NO REMUNERATIVO* | C8: 20000 | E8: =+C8 -> 20000
B9: PREMIO P/LOZA
B10: TOTAL SUELDO | E10: =+E3+E4+E5+E6+E7+E8 -> 174540
B11: SAC CTA.1/2023 | E11: =+E10/2 -> 87270
B12: DEPOSITO P/BCO. S/REC | E12: -66424.54
B13: DEPOSITO P/BCO. S/REC SAC,1/23 | E13: -33162.27
B14: CTA.5/38(PRESTAMO(10% S/SUELDO)* | C14: NETO | E14: -15606
B15: TOTAL A COBRAR | E15: =+E10+E11+E12+E13+E14 -> 146617.19
B17: FACU
B18: DETALLE | C18: HS TRABAJADAS | D18: VALOR / HORA | E18: IMPORTE
B19: SUELDO | C19: 171 | D19: 1195 | E19: =+C19*D19 -> 204345
B20: FERIADO (2,5D) | C20: 20 | D20: 1195 | E20: =+C20*D20 -> 23900
B21: Presentismo | E21: 10000
B22: NO REMUNERATIVO | E22: 20000
B23: EXTRA al 50% | C23: 9 | D23: =+D19*1.5 -> 1792.5 | E23: =+C23*D23 -> 16132.5
B24: EXTRAS AL 100% | C24: 11 | D24: =+D19*2 -> 2390 | E24: =+C24*D24 -> 26290
B25: LOZAS
B26: TOTAL SUELDO | E26: =+E19+E20+E21+E22+E23+E24 -> 300667.5
B27: SAC CTA.1/2023 | E27: =+E26/2 -> 150333.75
B28: SEGURO CLIO | E28: -2480
B29: TOTAL A COBRAR | E29: =+E26+E27+E28 -> 448521.25
B31: HEINLEIN (CHACO)
B32: DETALLE | C32: HS TRABAJADAS | D32: VALOR / HORA | E32: IMPORTE
B33: SUELDO | C33: 171 | D33: 540 | E33: =C33*D33 -> 92340
B34: FERIADO (2,5D) | C34: 20 | D34: 540 | E34: =+C34*D34 -> 10800
B35: Presentismo | E35: 10000
B36: NO REMUNERATIVO | E36: 20000
B37: HORAS EXTRAS AL 50% | C37: 12 | D37: =+D33*1.5 -> 810 | E37: =C37*D37 -> 9720
B38: HORAS EXTRAS AL 100% | C38: 11.5 | D38: =+D33*2 -> 1080 | E38: =+C38*D38 -> 12420
B39: PREMIO P/OBRA EN RAF+ | E39: 15000
B40: TOTAL SUELDO | E40: =+E33+E34+E35+E36+E37+E38+E39 -> 170280
B41: SAC CTA.1/2023 | E41: =+E40/2 -> 85140
B42: ADELANTO | E42: -43000
B43: TOTAL A COBRAR | E43: =+E40+E41+E42 -> 212420
B46: JUANI
B47: DETALLE | C47: HS TRABAJADAS | D47: VALOR / HORA | E47: IMPORTE
B48: SUELDO | C48: 171 | D48: 750 | E48: =+C48*D48 -> 128250
B49: FERIADO (2,5D) | C49: 20 | D49: 750 | E49: =+C49*D49 -> 15000
B50: Presentismo | E50: 10000
B51: NO REMUNERATIVO | E51: 20000
B52: EXTRA al 50% | C52: 8.5 | D52: =+D48*1.5 -> 1125 | E52: =+D52*C52 -> 9562.5
B53: EXTRAS AL 100% | C53: 12 | D53: =+D48*2 -> 1500 | E53: =+C53*D53 -> 18000
B54: PREMIO P/LOZA
B55: TOTAL SUELDO | E55: =+E48+E49+E50+E51+E52+E53 -> 200812.5
B56: SAC CTA.1/2023 | E56: =201000/2 -> 100500
B57: DEPOSITO P/BCO S/REC | E57: -67691.67
B58: DEPOSITO P/BCO S/REC | E58: -33795.83
C59: TOTAL A COBRAR | E59: =+E55+E56+E57+E58 -> 199825
B63: JONA
B64: DETALLE | C64: HS TRABAJADAS | D64: VALOR / HORA | E64: IMPORTE
B65: SUELDO | C65: 171 | D65: 662.5 | E65: =+C65*D65 -> 113287.5
B66: FERIADO (2,5D) | C66: 20 | D66: 662.5 | E66: =+C66*D66 -> 13250
B67: PRESENTISMO
B68: EXTRA al 50%
B69: NO REMUNERATIVO
B70: SAC CTA.1/2023 | E70: 86090.5
B71: TOTAL SUELDO | E71: =+E65+E66+E70 -> 212628
B72: ADELANTO | E72: -30000
B73: DEPOSITO P/BCO | E73: -63990.27
B74: DEPOSITO P/BCO SAC 1/2023 | E74: -15997.57
C75: TOTAL A COBRAR | E75: =+E71+E72+E73+E74 -> 102640.16
B78: SANDRONE(CORCHO)
B79: DETALLE | C79: HS TRABAJADAS | D79: VALOR / HORA | E79: IMPORTE
B80: SUELDO* | C80: 171 | D80: 520 | E80: =+C80*D80 -> 88920 | F80: =+E80+E81+E82+E83 -> 124320
B81: FERIADO2,5D) * | C81: 20 | D81: 520 | E81: =+C81*D81 -> 10400
B82: Presentismo * | E82: 10000
B83: NO REMUNERATIVO* | E83: 15000
B84: EXTRA al 50% | C84: 20.5 | D84: =+D80*1.5 -> 780 | E84: =+C84*D84 -> 15990
B85: EXTRAS AL 100%
B87: TOTAL SUELDO | E87: =+E80+E81+E82+E83+E84 -> 140310
B88: SAC CTA.1/2023 | E88: =143170/2 -> 71585
B89: CTA,1/16 (% DE SUELDO NETO)* | E89: -12432
C90: TOTAL A COBRAR | E90: =+E87+E88+E89 -> 199463
B94: MAXI ARAGON
B95: DETALLE | C95: HS TRABAJADAS | D95: VALOR / HORA | E95: IMPORTE
B96: SUELDO | C96: 129 | D96: 450 | E96: =+C96*D96 -> 58050
B97: FERIADO (2,5D) | C97: 20 | D97: 450 | E97: =+C97*D97 -> 9000
B98: DIAS P/ACCIDENTE(5,5) | C98: 42 | D98: 450 | E98: =+C98*D98 -> 18900
B99: PRESENTISMO
B100: NO REMUNERATIVO | E100: 15000
B101: HORAS EXTRAS 50% | C101: 4.5 | D101: =+D96*1.5 -> 675 | E101: =+C101*D101 -> 3037.5
B103: TOTAL SUELDO | E103: =+E96+E97+E98+E100+E101 -> 103987.5
B104: SAC CTA.1/2023 | E104: =117500/2 -> 58750
B105: ADELANTO | E105: -50000
B106: CTA.4(PRESTAMO) | E106: -10000
C107: TOTAL A COBRAR | E107: =+E103+E104+E105+E106 -> 102737.5
B111: DAVID
B112: DETALLE | C112: HS TRABAJADAS | D112: VALOR / HORA | E112: IMPORTE
B113: SUELDO | C113: 171 | D113: 460 | E113: =+C113*D113 -> 78660
B114: FERIADO (2,5D) | C114: 20 | D114: 460 | E114: =+C114*D114 -> 9200
B115: Presentismo | E115: 10000
B116: NO REMUNERATIVO | E116: 20000
B117: EXTRA al 50% | C117: 16 | D117: =+D113*1.5 -> 690 | E117: =+C117*D117 -> 11040
...

Sheet RESUMENJULIO2023
B1: JULIO 2023
B3: PILU | C3: 110800
B4: FACU | C4: 174100
B5: CHACO | C5: 108050
B6: JUANI | C6: 133700
B7: JONA | C7: 58000
B8: GERMAN | C8: 116700
B9: CORCHO | C9: 140700
B10: ANDREA | C10: 107000
B11: MAXI | C11: 50600
B12: DAVID | C12: 110400
B13: JORGE | C13: 50200
B14: LEO | C14: 125000
... B16: RUBEN | C16: 142500
B18: TOTAL 07/2023 | C18: =+C3+C4+C5+C6+C7+C8+C9+C10+C11+C12+C13+C14+C15+C16 -> 1550150
B21: JULIO 2023
B22: , | C22: VALOR HORA | D22: PRESENTISMO
B23: PILU | C23: 726 | D23: 10000
B24: FACU | C24: 1315 | D24: 10000
B25: CHACO | C25: 621 | D25: 10000
B26: JUANI | C26: 862.5 | D26: 10000
B27: JONA | C27: 728.75 | D27: 10000
B28: GERMAN | C28: 540 | D28: 10000
B29: CORCHO | C29: 598 | D29: 10000
B30: ANDREA | C30: 805 | D30: 10000
B31: MAXI | C31: 540 | D31: 10000
B32: DAVID | C32: 552 | D32: 10000
B33: JORGE | C33: 517.5 | D33: 10000
B34: LEO | C34: 540 | D34: 10000
... B36: RUBEN | C36: 600 | D36: 10000
A40: DIAS | B40: HS | C40: MAR
A41: 17 | B41: 9 | C41: =+A41*B41 -> 153 | D41: LABORAL
A42: 4 | B42: 8 | C42: =+A42*B42 -> 32 | D42: **VIERNES
A43: 0 | B43: 8 | C43: =+A43*B43 -> 0 | D43: FERIADO
C44: =+C41+C42+C43 -> 185 | D44: TOTAL

Sheet JULIO2023
B1: PILU
B2: DETALLE | C2: HS TRABAJADAS | D2: VALOR / HORA | E2: IMPORTE
B3: SUELDO* | C3: 185 | D3: =660*1.1 -> 726 | E3: =+C3*D3 -> 134310 | F3: AUMENTO 10%
B4: FERIADO ( )*
B5: Presentismo* | E5: 10000
B6: HORAS EXTRAS 50% | C6: 9 | D6: =+D3*1.5 -> 1089 | E6: =+C6*D6 -> 9801
B7: HORAS EXTRAS AL 100%
B8: NO REMUNERATIVO* | E8: 35000
B9: PREMIO P/LOZA(BR-FR) | C9: 2 | D9: 3000 | E9: =+C9*D9 -> 6000
B10: TOTAL SUELDO | E10: =+E3+E5+E6+E8+E9 -> 195111
B11: DEPOSITO P/BCO. S/REC | E11: -66424.54
B12: CTA.6/38(PRESTAMO(10% S/SUELDO)* | C12: NETO | D12: =+E3+E5+E8 -> 179310 | E12: -17931
B13: TOTAL A COBRAR | E13: =+E10+E11+E12 -> 110755.46
B15: FACU
B16: DETALLE | C16: HS TRABAJADAS | D16: VALOR / HORA | E16: IMPORTE
B17: SUELDO | C17: 185 | D17: 1315 | E17: =+C17*D17 -> 243275 | F17: AUMENTO 10%
B18: FERIADO ( )
B19: Presentismo | E19: 10000
B20: NO REMUNERATIVO | E20: 20000
B21: EXTRAS al 50% | C21: 2.5 | D21: =+D17*1.5 -> 1972.5 | E21: =+C21*D21 -> 4931.25
B22: EXTRAS AL 100% | C22: 8.5 | D22: =+D17*2 -> 2630 | E22: =+C22*D22 -> 22355
B23: LOZAS(BR-FR) | C23: 2 | D23: 3000 | E23: =+C23*D23 -> 6000
B24: TOTAL SUELDO | E24: =+E17+E19+E20+E21+E22+E23 -> 306561.25
B25: EDIF.MODENA | E25: 20000
B26: DEPOSITO P/BCO. | E26: -150000
B27: SEGURO CLIO | E27: -2480
B28: TOTAL A COBRAR | E28: =+E24+E25+E26+E27 -> 174081.25
B30: HEINLEIN (CHACO)
B31: DETALLE | C31: HS TRABAJADAS | D31: VALOR / HORA | E31: IMPORTE
B32: SUELDO | C32: 141 | D32: =540*1.15 -> 621 | E32: =+C32*D32 -> 87561 | F32: AUMENTO 15%
B33: VACACIONES (7D) | C33: 56 | D33: 621 | E33: =+C33*D33 -> 34776
B34: FERIADO ( )
B35: Presentismo | E35: 10000
B36: NO REMUNERATIVO | E36: 20000
B37: HORAS EXTRAS AL 50% | C37: 1 | D37: =+D32*1.5 -> 931.5 | E37: =C37*D37 -> 931.5
B38: HORAS EXTRAS AL 100%
B39: PREMIO P/OBRA EN RAF(X SEM) | D39: 5000 | E39: 5000
B40: TOTAL SUELDO | E40: =+E32+E33+E35+E36+E37+E39 -> 158268.5
B41: ADELANTO | E41: -50240
B42: TOTAL A COBRAR | E42: =+E40+E41 -> 108028.5
B45: JUANI
B46: DETALLE | C46: HS TRABAJADAS | D46: VALOR / HORA | E46: IMPORTE
B47: SUELDO | C47: 185 | D47: =750*1.15 -> 862.5 | E47: =+C47*D47 -> 159562.5 | F47: AUMENTO 15%
B48: FERIADO ( )
B49: Presentismo | E49: 10000
B50: NO REMUNERATIVO | E50: 20000
B51: EXTRA al 50% | C51: 4.5 | D51: =+D47*1.5 -> 1293.75 | E51: =+C51*D51 -> 5821.875
B52: EXTRAS AL 100%
B53: PREMIO P/LOZA (BR-FR) | C53: 2 | D53: 3000 | E53: =+C53*D53 -> 6000
B54: TOTAL SUELDO | E54: =+E47+E49+E50+E51+E53 -> 201384.37
B55: DEPOSITO P/BCO S/REC | E55: -67691.67
C56: TOTAL A COBRAR | E56: =+E54+E55 -> 133692.7
B60: JONA
B61: DETALLE | C61: HS TRABAJADAS | D61: VALOR / HORA | E61: IMPORTE
B62: SUELDO | C62: 184 | D62: =662.5*1.1 -> 728.75 | E62: =+C62*D62 -> 134090 | F62: AUMENTO 10%
B63: FERIADO ( )
B64: PRESENTISMO
B65: EXTRA al 50%
B66: NO REMUNERATIVO
B67: TOTAL SUELDO | E67: =+E62 -> 134090
B68: DEPOSITO P/BCO | E68: -63990.27
C70: TOTAL A COBRAR | E70: =+E67+E68 -> 70099.73
B73: SANDRONE(CORCHO)
B74: DETALLE | C74: HS TRABAJADAS | D74: VALOR / HORA | E74: IMPORTE
B75: SUELDO * | C75: 141 | D75: =520*1.15 -> 598 | E75: =+C75*D75 -> 84318 | F75: AUMENTO 15%
B76: VACACIONES * (7D) | C76: 56 | D76: =+D75 -> 598 | E76: =+C76*D76 -> 33488
B77: FERIADO ( ) *
B78: Presentismo * | E78: 10000
B79: NO REMUNERATIVO* | E79: 20000
B80: EXTRA al 50% | C80: 8.5 | D80: =+D75*1.5 -> 897 | E80: =+C80*D80 -> 7624.5
B81: EXTRAS AL 100%
B83: TOTAL SUELDO | E83: =+E75+E76+E78+E79+E80 -> 155430.5
B84: CTA. 2/16 (10% DE SUELDO NETO)* | C84: =+E75+E76+E78+E79 -> 147806 | E84: -14780
C85: TOTAL A COBRAR | E85: =+E83+E84 -> 140650.5
B89: MAXI ARAGON
B90: DETALLE | C90: HS TRABAJADAS | D90: VALOR / HORA | E90: IMPORTE
B91: SUELDO | C91: 177 | D91: =450*1.2 -> 540 | E91: =+C91*D91 -> 95580 | F91: AUMENTO 20%
B92: FERIADO ( )
B93: PRESENTISMO | E93: 0
B94: NO REMUNERATIVO | E94: 15000
B95: HORAS EXTRAS 50%
B97: TOTAL SUELDO | E97: =+E91+E93+E94 -> 110580
B98: ADELANTO | E98: -50000
B99: CTA.5(PRESTAMO) | E99: -10000
C100: TOTAL A COBRAR | E100: =+E97+E98+E99 -> 50580
B104: DAVID
B105: DETALLE | C105: HS TRABAJADAS | D105: VALOR / HORA | E105: IMPORTE
B106: SUELDO | C106: 185 | D106: =460*1.2 -> 552 | E106: =+C106*D106 -> 102120 | F106: AUMENTO 20%
B107: FERIADO ( )
B108: Presentismo | E108: 10000
B109: NO REMUNERATIVO | E109: 20000
B110: EXTRA al 50% | C110: 10 | D110: =+D106*1.5 -> 828 | E110: =+C110*D110 -> 8280
B111: EXTRAS AL 100%
B112: ADICIONAL P/MATERIALES | E112: 20000
B113: TOTAL SUELDO | E113: =+E106+E108+E109+E110+E112 -> 160400
B114: ADELANTO | E114: -50000
C115: TOTAL A COBRAR | E115: =+E113+E114 -> 110400
B118: ANDREA
B119: DETALLE | C119: HS TRABAJADAS | D119: VALOR / HORA | E119: IMPORTE
B120: SUELDO | C120: 160 | D120: =700*1.15 -> 805 | E120: =+C120*D120 -> 128800 | F120: AUMENTO 15%
...

Sheet AGOSTO2023
B1: PILU
B2: DETALLE | C2: HS TRABAJADAS | D2: VALOR / HORA | E2: IMPORTE
B3: SUELDO* | C3: 194 | D3: =660*1.1 -> 726 | E3: =+C3*D3 -> 140844
B4: FERIADO ( 1 )* | C4: 8 | D4: =+D3 -> 726 | E4: =+C4*D4 -> 5808
B5: Presentismo* | E5: 10000
B6: HORAS EXTRAS 50% | C6: 1 | D6: =+D3*1.5 -> 1089 | E6: =+C6*D6 -> 1089
B7: NO REMUNERATIVO* | E7: 35000
B8: BONO GOB.NAC | E8: 30000
B9: PREMIO P/LOZA (BRINK) | C9: 2 | D9: 3000 | E9: =+C9*D9 -> 6000
B10: TOTAL SUELDO | E10: =+E3+E4+E5+E6+E7+E8+E9 -> 228741
B11: DEPOSITO P/BCO. S/REC | E11: -110249.51
